Workbook

Sheet Gesamtplanung
A1: Details | B1: Total | C1: PCGB | D1: PD | E1: PKO | F1: POF | G1: PIT | H1: TRK | I1: PCL | J1: PIB SPA | K1: PNO | L1: PIB POR | M1: PCH | N1: PTW | O1: PCA | P1: PPL | Q1: PJ | R1: PBR | S1: PCNA
A2: CPL | B2: Macan BEV | C2: 1586 | D2: 2782 | E2: - | F2: 2109 | G2: 715 | H2: 403 | I2: 7059 | J2: 3577 | K2: 3964 | L2: 896 | M2: 4951 | O2: 4904 | P2: - | Q2: - | S2: -
B3: Cayenne E3 II | C3: 1245 | D3: 1499 | E3: 1069 | F3: - | G3: 2356 | H3: - | I3: 2145 | J3: 4133 | K3: - | L3: - | M3: - | N3: - | O3: 2540 | P3: 4290 | Q3: - | R3: - | S3: 916
B4: 25% von CTG | C4: =(AVERAGE(C2,C3))/4 -> 353.875 | D4: =(AVERAGE(D2,D3))/4 -> 535.125 | E4: =(AVERAGE(E2,E3))/4 -> 267.25 | F4: =(AVERAGE(F2,F3))/4 -> 527.25 | G4: =(AVERAGE(G2,G3))/4 -> 383.875 | H4: =(AVERAGE(H2,H3))/4 -> 100.75 | I4: =(AVERAGE(I2,I3))/4 -> 1150.5 | J4: =(AVERAGE(J2,J3))/4 -> 963.75 | ... M4: =(AVERAGE(M2,M3))/4 -> 1237.75 | N4: =272/4 -> 68 | O4: =(AVERAGE(O2,O3))/4 -> 930.5 | P4: =(AVERAGE(P2,P3))/4 -> 1072.5 | Q4: =AVERAGE(C4:P4,S4) -> 602.34167 | R4: =AVERAGE(C4:Q4,S4) -> 602.34167 | S4: =(AVERAGE(S2,S3))/4 -> 229 | T4: =(AVERAGE(T2,T3))/2 -> #DIV/0! | U4: =(AVERAGE(U2,U3))/2 -> #DIV/0! | V4: =(AVERAGE(V2,V3))/2 -> #DIV/0!
B5: Macan BEV (25%) | C5: =C2/4 -> 396.5 | D5: =D2/4 -> 695.5 | E5: =E4 -> 267.25 | F5: =F2/4 -> 527.25 | G5: =G2/4 -> 178.75 | H5: =H2/4 -> 100.75 | I5: =I2/4 -> 1764.75 | J5: =J2/4 -> 894.25 | K5: =K2/4 -> 991 | L5: =L2/4 -> 224 | M5: =M2/4 -> 1237.75 | ... O5: =O2/4 -> 1226 | P5: =P3/4 -> 1072.5 | S5: =AVERAGE(C5:P5) -> 684.01786
B6: Cayenne E3 II (25%) | C6: =C3/4 -> 311.25 | D6: =D3/4 -> 374.75 | E6: =E3/4 -> 267.25 | F6: =F4 -> 527.25 | G6: =G3/4 -> 589 | H6: =H4 -> 100.75 | I6: =I3/4 -> 536.25 | J6: =J3/4 -> 1033.25 | K6: =K4 -> 991 | L6: =L4 -> 224 | M6: =M4 -> 1237.75 | N6: 0 | O6: =O3/4 -> 635 | P6: =P3/4 -> 1072.5 | S6: =S3/4 -> 229
B7: Cayenne E4 (25%) | C7: =AVERAGE(C2:C3)/4 -> 353.875 | D7: =AVERAGE(D2:D3)/4 -> 535.125 | E7: =AVERAGE(E2:E3)/4 -> 267.25 | F7: =AVERAGE(F2:F3)/4 -> 527.25 | G7: =AVERAGE(G2:G3)/4 -> 383.875 | H7: =AVERAGE(H2:H3)/4 -> 100.75 | I7: =AVERAGE(I2:I3)/4 -> 1150.5 | J7: =AVERAGE(J2:J3)/4 -> 963.75 | ... M7: =AVERAGE(M2:M3)/4 -> 1237.75 | N7: =AVERAGE(E7,H7,L7,R7,S7) -> 205.25 | O7: =AVERAGE(O2:O3)/4 -> 930.5 | P7: =AVERAGE(P2:P3)/4 -> 1072.5 | S7: =AVERAGE(S2:S3)/4 -> 229
A8: Planned sales | B8: Macan BEV | C8: 5457 | D8: 4700 | E8: 1500 | F8: 1607 | G8: 1655 | H8: 388 | I8: 606 | J8: =1100*0.7 -> 770 | K8: 629 | L8: =J8/0.7*0.3 -> 330 | M8: 658 | N8: 573 | O8: 563 | P8: 374 | Q8: 862 | R8: 1356 | S8: 5358
B9: Cayenne E3 II | C9: 2622 | D9: 3800 | E9: 826 | F9: 450 | G9: 1920 | H9: 136 | I9: 2242 | J9: =1178*0.7 -> 824.6 | K9: 19 | L9: =J9/0.7*0.3 -> 353.4 | M9: 738 | N9: 1348 | O9: 1679 | P9: 1366 | Q9: 586 | R9: 1760 | S9: 20820
B10: Cayenne E4 | C10: 2068 | D10: 2200 | E10: 2000 | F10: 800 | G10: 410 | H10: 383 | I10: 298 | J10: =800*0.7 -> 560 | K10: 529 | L10: =J10/0.7*0.3 -> 240 | M10: 328 | N10: 535 | O10: 368 | P10: 218 | Q10: 357 | R10: 295 | S10: 3440 | U10: PIB SPA | V10: PIB POR | W10: =SUM(C10:S10)-S10 -> 11589 | X10: =SUM(SUM(C10:V10)) -> 15029 | Y10: =X10/X14 -> 1 | Z10: =Y10+#REF!/2 -> #REF! | AA10: =W10-H10 -> 11206
A11: Planned sales from media | B11: Macan BEV | C11: =C8*$C$20 -> 818.55 | D11: =D8*$C$20 -> 705 | E11: =E8*$C$20 -> 225 | F11: =F8*$C$20 -> 241.05 | G11: =G8*$C$20 -> 248.25 | H11: =H8*$C$20 -> 58.2 | I11: =I8*$C$20 -> 90.9 | J11: =J8*$C$20 -> 115.5 | ... S11: =S8*$C$20 -> 803.7
B12: Cayenne E3 II | C12: =C9*$C$20 -> 393.3 | D12: =D9*$C$20 -> 570 | E12: =E9*$C$20 -> 123.9 | F12: =F9*$C$20 -> 67.5 | G12: =G9*$C$20 -> 288 | H12: =H9*$C$20 -> 20.4 | I12: =I9*$C$20 -> 336.3 | J12: =J9*$C$20 -> 123.69 | ... S12: =S9*$C$20 -> 3123
B13: Cayenne E4 | C13: =C10*$C$20 -> 310.2 | D13: =D10*$C$20 -> 330 | E13: =E10*$C$20 -> 300 | F13: =F10*$C$20 -> 120 | G13: =G10*$C$20 -> 61.5 | H13: =H10*$C$20 -> 57.45 | I13: =I10*$C$20 -> 44.7 | J13: =J10*$C$20 -> 84 | ... S13: =S10*$C$20 -> 516
A14: Currently planned market media budget 2026 | B14: Macan BEV | C14: =[1]Übersicht!$I$5 -> 532249.63 | D14: =[1]Übersicht!$I$9 -> 754400 | E14: =[1]Übersicht!$I$14 -> 0 | F14: =[1]Übersicht!$I$16 -> 0 | G14: =[1]Übersicht!$I$12 -> 202952 | H14: 0 | I14: =[1]Übersicht!$I$7 -> 314801.99 | J14: =[1]Übersicht!$I$11 -> 421000 | K14: =[1]Übersicht!$I$15 -> 143485.8 | L14: =[1]Übersicht!$I$10 -> 65010.76 | M14: =[1]Übersicht!$I$6 -> 32831.888 | N14: =[1]Übersicht!$I$18 -> 67638.043 | O14: =[1]Übersicht!$I$3 -> 470545.54 | P14: =[1]Übersicht!$I$17 -> 27761.577 | Q14: =[1]Übersicht!$I$13 -> 100338.83 | R14: =[1]Übersicht!$I$2 -> 26553.282 | S14: =[1]Übersicht!$I$8 -> 374048.77 | T14: =J16+L16 -> 200000 | U14: =J16/T14 -> 1 | V14: =L16/T14 -> 0 | X14: =SUM(SUM(X10:X10)) -> 15029
B15: Cayenne E3 II | C15: =[1]Übersicht!$E$5 -> 197311 | D15: =[1]Übersicht!$E$9 -> 477500 | E15: =[1]Übersicht!$E$14 -> 0 | F15: 0 | G15: =[1]Übersicht!$E$12 -> 0 | H15: 0 | I15: =[1]Übersicht!$E$7 -> 944405.97 | J15: =[1]Übersicht!$E$11 -> 150000 | K15: =[1]Übersicht!$E$15 -> 0 | L15: 0 | M15: =[1]Übersicht!$E$6 -> 9553.091 | N15: =[1]Übersicht!$E$18 -> 101502.17 | O15: =[1]Übersicht!$E$3 -> 711261.64 | P15: =[1]Übersicht!$E$17 -> 648664.41 | Q15: =[1]Übersicht!$E$13 -> 13662.695 | R15: =[1]Übersicht!$E$2 -> 47340.399 | S15: =[1]Übersicht!$E$8 -> 4042327.2
B16: Cayenne E4 | C16: =[1]Übersicht!$F$5 -> 379717.79 | D16: =[1]Übersicht!$F$9 -> 694200 | E16: =[1]Übersicht!$F$14 -> 1034179.3 | F16: =[1]Übersicht!$F$16 -> 200000 | G16: =[1]Übersicht!$F$12 -> 180144.48 | H16: =346667/3 -> 115555.67 | I16: =[1]Übersicht!$F$7 -> 245545.55 | J16: =[1]Übersicht!$F$11 -> 200000 | K16: =[1]Übersicht!$F$15 -> 110681.42 | L16: =[1]Übersicht!$F$10 -> 0 | M16: =[1]Übersicht!$F$6 -> 274074.89 | N16: =[1]Übersicht!$F$18 -> 86288.906 | O16: =[1]Übersicht!$F$3 -> 687673.88 | P16: =[1]Übersicht!$F$17 -> 845678.29 | Q16: =[1]Übersicht!$F$13 -> 230134.44 | R16: =[1]Übersicht!$F$2 -> 56232.027 | S16: =[1]Übersicht!$F$8 -> 210222.3
A17: Total media budget 2026 | C17: 3282787 | D17: 4220000 | E17: 1924837 | F17: 1388000 | G17: 1502000 | H17: 346667 | I17: 2679368 | J17: 851861 | K17: 647059 | L17: 350000 | M17: 1251505 | N17: 988533 | O17: 3395262 | P17: 1961839 | Q17: 1128085 | R17: 337000 | S17: 20612760 | T17: =SUM(C17:S17) -> 46867563
A18: Share of focus model lines in total media | C18: =(SUM(C14:C16)/C17) -> 0.33790752 | D18: =(SUM(D14:D16)/D17) -> 0.4564218 | E18: =(SUM(E14:E16)/E17) -> 0.5372815 | F18: =(SUM(F14:F16)/F17) -> 0.14409222 | G18: =(SUM(G14:G16)/G17) -> 0.25505758 | H18: =(SUM(H14:H16)/H17) -> 0.33333333 | I18: =(SUM(I14:I16)/I17) -> 0.56160763 | J18: =(SUM(J14:J16)/J17) -> 0.90507724 | ... S18: =(SUM(S14:S16)/S17) -> 0.22445312
A19: Difference to target value: 60% media in focus model lines | C19: =60%-C18 -> 0.26209248 | D19: =60%-D18 -> 0.1435782 | E19: =60%-E18 -> 0.062718496 | F19: =60%-F18 -> 0.45590778 | G19: =60%-G18 -> 0.34494242 | H19: =60%-H18 -> 0.26666667 | I19: =60%-I18 -> 0.038392371 | J19: =60%-J18 -> -0.30507724 | ... S19: =60%-S18 -> 0.37554688
A20: Target value share of planned sales influenced by media | C20: 0.15 | D20: 0.15 | E20: 0.15 | F20: 0.15 | G20: 0.15 | H20: 0.15 | I20: 0.15 | J20: 0.15 | K20: 0.15 | L20: 0.15 | M20: 0.15 | N20: 0.15 | O20: 0.15 | P20: 0.15 | Q20: 0.15 | R20: 0.15 | S20: 0.15 | T20: 0.2 | U20: 0.2 | V20: 0.2
A21: Lead to Sales Rate | C21: 0.26 | D21: 0.27 | E21: 0.19 | F21: 0.12 | G21: 0.12 | H21: 0.19 | I21: 0.36 | J21: 0.1 | K21: 0.12 | L21: 0.19 | M21: 0.19 | N21: 0.19 | O21: 0.12 | P21: 0.19 | Q21: 0.19 | R21: 0.19 | S21: 0.19 | W21: =AVERAGE(C21:S21) -> 0.18705882
A22: Required Leads (Total) | B22: Macan BEV | C22: =C11/C21 -> 3148.2692 | D22: =D11/D21 -> 2611.1111 | E22: =E11/E21 -> 1184.2105 | F22: =F11/F21 -> 2008.75 | G22: =G11/G21 -> 2068.75 | H22: =H11/H21 -> 306.31579 | I22: =I11/I21 -> 252.5 | J22: =J11/J21 -> 1155 | ... S22: =S11/S21 -> 4230 | W22: =SUM(C22:S22)-S22 -> 17503.591
B23: Cayenne E3 II | C23: =C12/C21 -> 1512.6923 | D23: =D12/D21 -> 2111.1111 | E23: =E12/E21 -> 652.10526 | F23: =F12/F21 -> 562.5 | G23: =G12/G21 -> 2400 | H23: =H12/H21 -> 107.36842 | I23: =I12/I21 -> 934.16667 | J23: =J12/J21 -> 1236.9 | ... S23: =S12/S21 -> 16436.842
B24: Cayenne E4 | C24: =C13/C21 -> 1193.0769 | D24: =D13/D21 -> 1222.2222 | E24: =E13/E21 -> 1578.9474 | F24: =F13/F21 -> 1000 | G24: =G13/G21 -> 512.5 | H24: =H13/H21 -> 302.36842 | I24: =I13/I21 -> 124.16667 | J24: =J13/J21 -> 840 | ... S24: =S13/S21 -> 2715.7895
A25: Required Media Budget | B25: Macan BEV | C25: =C22*C5 -> 1248288.8 | D25: =D22*D5 -> 1816027.8 | E25: =E22*E5 -> 316480.26 | F25: =F22*F5 -> 1059113.4 | G25: =G22*G5 -> 369789.06 | H25: =H22*H5 -> 30861.316 | I25: =I22*I5 -> 445599.37 | J25: =J22*J5 -> 1032858.8 | ... S25: =S22*S5 -> 2893395.5
B26: Cayenne E3 II | C26: =C23*C6 -> 470825.48 | D26: =D23*D6 -> 791138.89 | E26: =E23*E6 -> 174275.13 | F26: =F23*F6 -> 296578.12 | G26: =G23*G6 -> 1413600 | H26: =H23*H6 -> 10817.368 | I26: =I23*I6 -> 500946.88 | J26: =J23*J6 -> 1278026.9 | ... S26: =S23*S6 -> 3764036.8
B27: Cayenne E4 | C27: =C24*C7 -> 422200.1 | D27: =D24*D7 -> 654041.67 | E27: =E24*E7 -> 421973.68 | F27: =F24*F7 -> 527250 | G27: =G24*G7 -> 196735.94 | H27: =H24*H7 -> 30463.618 | I27: =I24*I7 -> 142853.75 | J27: =J24*J7 -> 809550 | ... S27: =S24*S7 -> 621915.79 | T27: =SUM(C25:S27) -> 29413676
A28: Budget gap for 2026 (currently planned) | B28: Macan BEV | C28: =(C25-C14)/(1+C19) -> 567342.83 | D28: =(D25-D14)/(1+D19) -> 928338.59 | E28: =(E25-E14)/(1+E19) -> 297802.54 | F28: =(F25-F14)/(1+F19) -> 727459.15 | G28: =(G25-G14)/(1+G19) -> 124047.74 | H28: =(H25-H14)/(1+H19) -> 24364.197 | I28: =(I25-I14)/(1+I19) -> 125961.43 | J28: =J25-J14 -> 611858.75 | K28: =(K25-K14)/(1+C19) -> 503677.79 | L28: =(L25-L14)/(1+D19) -> -5817.5866 | M28: =(M25-M14)/(1+E19) -> 574137.62 | N28: =(N25-N14)/(1+F19) -> -46457.642 | O28: =(O25-O14)/(1+G19) -> 291649.63 | P28: =P25-P14 -> 288908.16 | Q28: =(Q25-Q14)/(1+G19) -> -74604.558 | R28: =(R25-R14)/(1+H19) -> -20963.118 | S28: =(S25-S14)/(1+I19) -> 2426199.2 | T28: =SUM(SUM(C28:S28)) -> 7343904.7 | U28: =#REF!-#REF! -> #REF! | V28: =#REF!-#REF! -> #REF! | W28: =SUM(C28:S28) -> 7343904.7
B29: Cayenne E3 II | C29: =(C26-C15)/(1+C19) -> 216715.09 | D29: =(D26-D15)/(1+D19) -> 274260.99 | E29: =(E26-E15)/(1+E19) -> 163989.93 | F29: =(F26-F15)/(1+F19) -> 203706.67 | G29: =(G26-G15)/(1+G19) -> 1051048.7 | H29: =(H26-H15)/(1+H19) -> 8540.0277 | I29: =(I26-I15)/(1+I19) -> -427063.13 | J29: =(J26-J15) -> 1128026.9 | K29: =(K26-K15)/(1+K19) -> 19496.623 | L29: =(L26-L15)/(1+L19) -> 44190.051 | M29: =(M26-M15)/(1+M19) -> 528230.89 | N29: =(N26-N15)/(1+N19) -> -75657.103 | O29: =(O26-O15)/(1+O19) -> 592198.68 | P29: =(P26-P15) -> 507942.17 | Q29: =(Q26-Q15)/(1+Q19) -> -10550.85 | R29: =(R26-R15)/(1+R19) -> -38999.553 | S29: =(S26-S15)/(1+S19) -> -202312.55 | T29: =SUM(SUM(C29:S29)) -> 3983763.6
B30: Cayenne E4 | C30: =(C27-C16)/(1+C19) -> 33660.214 | D30: =(D27-D16)/(1+D19) -> -35116.386 | E30: =(E27-E16)/(1+E19) -> -576075.07 | F30: =(F27-F16)/(1+F19) -> 224773.85 | G30: =(G27-G16)/(1+G19) -> 12336.184 | H30: =(H27-H16)/(1+H19) -> -67177.933 | I30: =(I27-I16)/(1+I19) -> -98894.989 | J30: =(J27-J16)/(1+J19) -> 877147.84 | ... O30: =(O27-O16)/(1+O19) -> -247424.73 | P30: =(P27-P16) -> -661095.4 | Q30: 0 | R30: =(R27-R16)/(1+R19) -> -46324.576 | S30: =(S27-S16)/(1+S19) -> 299294.41 | T30: =SUM(SUM(C30:S30)) -> 231026.83
B31: Total | C31: =SUM(C28:C30) -> 817718.13 | D31: =SUM(D28:D30) -> 1167483.2 | E31: =SUM(E28:E30) -> -114282.61 | F31: =SUM(F28:F30) -> 1155939.7 | G31: =SUM(G28:G30) -> 1187432.6 | H31: =SUM(H28:H30) -> -34273.708 | I31: =SUM(I28:I30) -> -399996.69 | J31: =SUM(J28:J30) -> 2617033.5 | ... S31: =SUM(S28:S30) -> 2523181.1 | T31: =SUM(SUM(C31:S31)) -> 11558695
A32: Efficiency Recommendation (CPL und L2S-Rate)
A33: Sales Gap Recommendation | J33: Macan, E4 | K33: Macan, E4 | L33: Macan, E4 | M33: Macan, E4
C35: PCGB | D35: PD | E35: PKO | F35: POF | G35: PIT | H35: TRK | I35: PCL | J35: PIB SPA | K35: PNO | L35: PIB POR | M35: PCH | N35: PTW | O35: PCA | P35: PPL | Q35: PJ | R35: PBR | S35: PCNA | T35: TOTAL | U35: TOTAL without PJ, PBR, PCNA
A36: Scenario 1 (Cover budget gaps) | B36: Macan BEV | C36: 100000 | D36: 150000 | E36: 50000 | F36: 150000 | G36: 50000 | H36: 10000 | I36: 50000 | J36: 50000 | K36: 40000 | L36: 30000 | M36: 40000 | N36: 10000 | O36: 30000 | P36: 10000 | Q36: 20000 | R36: 25000 | S36: 200000 | T36: =SUM(C36:S36) -> 1015000 | U36: =SUM(D36:T36) -> 1930000
B37: Cayenne E3 II | C37: 50000 | D37: 50000 | E37: 30000 | F37: 50000 | G37: 160000 | H37: 10000 | I37: 20000 | J37: 0 | K37: 0 | L37: 0 | M37: 0 | N37: 30000 | O37: 60000 | P37: 30000 | Q37: 20000 | R37: 25000 | S37: 50000 | T37: =SUM(C37:S37) -> 585000 | U37: =SUM(D37:T37) -> 1120000
B38: Cayenne E4 | C38: 130000 | D38: 100000 | E38: 20000 | F38: 100000 | G38: 90000 | H38: 40000 | I38: 30000 | J38: 100000 | K38: 60000 | L38: 30000 | M38: 20000 | N38: 20000 | O38: 10000 | P38: 20000 | Q38: 20000 | R38: 10000 | S38: 0 | T38: =SUM(C38:S38) -> 800000 | U38: =SUM(D38:T38) -> 1470000
B39: Total | C39: =SUM(C36:C38) -> 280000 | D39: =SUM(D36:D38) -> 300000 | E39: =SUM(E36:E38) -> 100000 | F39: =SUM(F36:F38) -> 300000 | G39: =SUM(G36:G38) -> 300000 | H39: =SUM(H36:H38) -> 60000 | I39: =SUM(I36:I38) -> 100000 | J39: =SUM(J36:J38) -> 150000 | ... S39: =SUM(S36:S38) -> 250000 | T39: =SUM(C39:S39) -> 2400000 | U39: =SUM(D39:T39) -> 4520000
A40: Scenario 2 (Efficiency Co Pilot) | B40: Macan BEV | C40: 73000 | D40: 43000 | E40: 79000 | F40: 25000 | G40: 74000 | H40: 204000 | I40: 23000 | J40: 0 | K40: 0 | L40: 94000 | M40: 0 | N40: 0 | O40: 0 | P40: 0 | Q40: 0 | R40: 74000 | S40: 31000 | T40: 720000 | U40: 720000
B41: Cayenne E3 II | C41: 92000 | D41: 80000 | E41: 79000 | F41: 25000 | G41: 23000 | H41: 209000 | I41: 74000 | J41: 0 | K41: 0 | L41: 94000 | M41: 0 | N41: 0 | O41: 0 | P41: 0 | Q41: 0 | R41: 37000 | S41: 92000 | T41: 805000 | U41: 805000
B42: Cayenne E4 | C42: 81000 | D42: 56000 | E42: 79000 | F42: 25000 | G42: 35000 | H42: 209000 | I42: 35000 | J42: 0 | K42: 0 | L42: 94000 | M42: 0 | N42: 95000 | O42: 0 | P42: 0 | Q42: 0 | R42: 74000 | S42: 92000 | T42: 875000 | U42: 875000
B43: Total | C43: 246000 | D43: 179000 | E43: 237000 | F43: 75000 | G43: 132000 | H43: 622000 | I43: 132000 | J43: 0 | K43: 0 | L43: 282000 | M43: 0 | N43: 95000 | O43: 0 | P43: 0 | Q43: 0 | R43: 185000 | S43: 215000 | T43: 2400000 | U43: 2400000
A44: Scenario 3 (Efficiency) | B44: Macan BEV | C44: 150000 | D44: 100000 | E44: 95000 | F44: 75000 | G44: 85000 | H44: 75000 | I44: 50000 | J44: 25000 | K44: 0 | L44: 25000 | M44: 0 | N44: 50000 | O44: 0 | P44: 0 | Q44: 20000 | R44: 25000 | S44: 100000 | T44: =SUM(C44:S44) -> 875000 | U44: =SUM(D44:T44) -> 1600000
B45: Cayenne E3 II | C45: 100000 | D45: 60000 | E45: 80000 | F45: 25000 | G45: 40000 | H45: 25000 | I45: 70000 | J45: 0 | K45: 0 | L45: 0 | M45: 0 | N45: 120000 | O45: 0 | P45: 0 | Q45: 20000 | R45: 25000 | S45: 150000 | T45: =SUM(C45:S45) -> 715000 | U45: =SUM(D45:T45) -> 1330000
B46: Cayenne E4 | C46: 100000 | D46: 120000 | E46: 120000 | F46: 60000 | G46: 35000 | H46: 125000 | I46: 40000 | J46: 60000 | K46: 0 | L46: 60000 | M46: 0 | N46: 60000 | O46: 0 | P46: 0 | Q46: 20000 | R46: 10000 | S46: 0 | T46: =SUM(C46:S46) -> 810000 | U46: =SUM(D46:T46) -> 1520000
B47: Total | C47: =SUM(C44:C46) -> 350000 | D47: =SUM(D44:D46) -> 280000 | E47: =SUM(E44:E46) -> 295000 | F47: =SUM(F44:F46) -> 160000 | G47: =SUM(G44:G46) -> 160000 | H47: =SUM(H44:H46) -> 225000 | I47: =SUM(I44:I46) -> 160000 | J47: =SUM(J44:J46) -> 85000 | ... S47: =SUM(S44:S46) -> 250000 | T47: =SUM(C47:S47) -> 2400000 | U47: =SUM(D47:T47) -> 4450000
A48: Scenario 4 (Coverage) | B48: Macan BEV | C48: 150000 | D48: 90000 | E48: 80000 | F48: 75000 | G48: 65000 | H48: 75000 | I48: 40000 | J48: 20000 | K48: 30000 | L48: 20000 | M48: 30000 | N48: 40000 | O48: 25000 | P48: 25000 | Q48: 20000 | R48: 25000 | S48: 95000 | T48: =SUM(C48:S48) -> 905000 | U48: =SUM(D48:P48) -> 615000
B49: Cayenne E3 II | C49: 75000 | D49: 60000 | E49: 80000 | F49: 25000 | G49: 40000 | H49: 25000 | I49: 45000 | J49: 0 | K49: 0 | L49: 0 | M49: 0 | N49: 100000 | O49: 25000 | P49: 25000 | Q49: 20000 | R49: 25000 | S49: 150000 | T49: =SUM(C49:S49) -> 695000 | U49: =SUM(D49:P49) -> 425000
B50: Cayenne E4 | C50: 75000 | D50: 100000 | E50: 100000 | F50: 60000 | G50: 35000 | H50: 100000 | I50: 50000 | J50: 55000 | K50: 30000 | L50: 55000 | M50: 30000 | N50: 60000 | O50: 10000 | P50: 10000 | Q50: 20000 | R50: 10000 | S50: 0 | T50: =SUM(C50:S50) -> 800000 | U50: =SUM(D50:P50) -> 695000
B51: Total | C51: =SUM(C48:C50) -> 300000 | D51: =SUM(D48:D50) -> 250000 | E51: =SUM(E48:E50) -> 260000 | F51: =SUM(F48:F50) -> 160000 | G51: =SUM(G48:G50) -> 140000 | H51: =SUM(H48:H50) -> 200000 | I51: =SUM(I48:I50) -> 135000 | J51: =SUM(J48:J50) -> 75000 | ... S51: =SUM(S48:S50) -> 245000 | T51: =SUM(C51:S51) -> 2400000 | U51: =SUM(D51:P51) -> 1735000
A52: Scenario 5 (Coverage after PHD check) | B52: Macan BEV | C52: 125000 | D52: 100000 | E52: 90000 | F52: 67000 | G52: 70000 | H52: 75000 | I52: 40000 | J52: 30000 | K52: 30000 | L52: 30000 | M52: 40000 | N52: 50000 | O52: 30000 | P52: 30000 | Q52: 20000 | R52: 25000 | S52: 95000 | T52: =SUM(C52:S52) -> 947000 | U52: =SUM(D52:P52) -> 682000
B53: Cayenne E3 II | C53: 75000 | D53: 60000 | E53: 75000 | F53: 25000 | G53: 40000 | H53: 25000 | I53: 40000 | J53: 0 | K53: 0 | L53: 0 | M53: 0 | N53: 100000 | O53: 30000 | P53: 30000 | Q53: 20000 | R53: 25000 | S53: 150000 | T53: =SUM(C53:S53) -> 695000 | U53: =SUM(D53:P53) -> 425000
B54: Cayenne E4 | C54: 75000 | D54: 100000 | E54: 105000 | F54: 60000 | G54: 35000 | H54: 125000 | I54: 40000 | J54: 50000 | K54: 40000 | L54: 50000 | M54: 40000 | N54: 80000 | O54: 10000 | P54: 10000 | Q54: 20000 | R54: 10000 | S54: 0 | T54: =SUM(C54:S54) -> 850000 | U54: =SUM(D54:P54) -> 745000
B55: Total | C55: =SUM(C52:C54) -> 275000 | D55: =SUM(D52:D54) -> 260000 | E55: =SUM(E52:E54) -> 270000 | F55: =SUM(F52:F54) -> 152000 | G55: =SUM(G52:G54) -> 145000 | H55: =SUM(H52:H54) -> 225000 | I55: =SUM(I52:I54) -> 120000 | J55: =SUM(J52:J54) -> 80000 | ... S55: =SUM(S52:S54) -> 245000 | T55: =SUM(C55:S55) -> 2492000 | U55: =SUM(C55:P55) -> 2127000
A56: Search | B56: All | C56: 0.65 | D56: 0.65 | E56: 0.65 | F56: 0.54 | G56: 0.65 | H56: 0.35 | I56: 0.54 | J56: 0.54 | K56: 0.54 | L56: 0.35 | M56: 0.54 | N56: 0.35 | O56: 0.54 | P56: 0.35 | Q56: 0.54 | R56: 0.54 | S56: 0.65
A57: Social | B57: All | C57: 0.35 | D57: 0.35 | E57: 0.35 | F57: 0.46 | G57: 0.35 | H57: 0.65 | I57: 0.46 | J57: 0.46 | K57: 0.46 | L57: 0.65 | M57: 0.46 | N57: 0.65 | O57: 0.46 | P57: 0.65 | Q57: 0.46 | R57: 0.46 | S57: 0.35
A62: Leads Scenario 1 (Cover budget gaps) | B62: =SUM(C62:S62) -> 2500.7095 | C62: =SUM(C39/C4)/2*0.75 -> 296.71494 | D62: =SUM(D39/D4)/2*0.75 -> 210.23125 | E62: =SUM(E39/E4)/2*0.75 -> 140.31805 | F62: =SUM(F39/F4)/2*0.75 -> 213.37127 | G62: =SUM(G39/G4)/2*0.75 -> 293.06415 | H62: =SUM(H39/H4)/2*0.75 -> 223.32506 | I62: =SUM(I39/I4)/2*0.75 -> 32.594524 | J62: =SUM(J39/J4)/2*0.75 -> 58.365759 | ... S62: =SUM(S39/S4)/2*0.75 -> 409.38865
A63: Sales Scenario 1 (Cover budget gaps) | B63: =SUM(C63:S63) -> 472.09112 | C63: =SUM(C62*C21) -> 77.145885 | D63: =SUM(D62*D21) -> 56.762439 | E63: =SUM(E62*E21) -> 26.66043 | F63: =SUM(F62*F21) -> 25.604552 | G63: =SUM(G62*G21) -> 35.167698 | H63: =SUM(H62*H21) -> 42.431762 | I63: =SUM(I62*I21) -> 11.734029 | J63: =SUM(J62*J21) -> 5.8365759 | ... S63: =SUM(S62*S21) -> 77.783843
A64: CPL Scenario | B64: =SUM(T39/B62) -> 959.72762 | C64: =SUM(C39/C62) -> 943.66667 | D64: =SUM(D39/D62) -> 1427 | E64: =SUM(E39/E62) -> 712.66667 | F64: =SUM(F39/F62) -> 1406 | G64: =SUM(G39/G62) -> 1023.6667 | H64: =SUM(H39/H62) -> 268.66667 | I64: =SUM(I39/I62) -> 3068 | J64: =SUM(J39/J62) -> 2570 | ... S64: =SUM(S39/S62) -> 610.66667
A65: CPS Scenario 1 | B65: =SUM(T39/B63) -> 5083.7643 | C65: =SUM(C39/C63) -> 3629.4872 | D65: =SUM(D39/D63) -> 5285.1852 | E65: =SUM(E39/E63) -> 3750.8772 | F65: =SUM(F39/F63) -> 11716.667 | G65: =SUM(G39/G63) -> 8530.5556 | H65: =SUM(H39/H63) -> 1414.0351 | I65: =SUM(I39/I63) -> 8522.2222 | J65: =SUM(J39/J63) -> 25700 | ... S65: =SUM(S39/S63) -> 3214.0351
A66: Leads Scenario 2 | B66: =SUM(C66:S66) -> 4722.3743 | C66: =SUM(C43/C4)/2*0.75 -> 260.68527 | D66: =SUM(D43/D4)/2*0.75 -> 125.43798 | E66: =SUM(E43/E4)/2*0.75 -> 332.55379 | F66: =SUM(F43/F4)/2*0.75 -> 53.342817 | G66: =SUM(G43/G4)/2*0.75 -> 128.94823 | H66: =SUM(H43/H4)/2*0.75 -> 2315.1365 | I66: =SUM(I43/I4)/2*0.75 -> 43.024772 | J66: =SUM(J43/J4)/2*0.75 -> 0 | ... S66: =SUM(S43/S4)/2*0.75 -> 352.07424
A67: Sales Scenario 2 | B67: =SUM(C67:S67) -> 920.08797 | C67: =SUM(C66*C21) -> 67.77817 | D67: =SUM(D66*D21) -> 33.868255 | E67: =SUM(E66*E21) -> 63.18522 | F67: =SUM(F66*F21) -> 6.401138 | G67: =SUM(G66*G21) -> 15.473787 | H67: =SUM(H66*H21) -> 439.87593 | I67: =SUM(I66*I21) -> 15.488918 | J67: =SUM(J66*J21) -> 0 | ... S67: =SUM(S66*S21) -> 66.894105
A68: CPL Scenario 2 | B68: =SUM(T43/B66) -> 508.21892 | C68: =SUM(C43/C66) -> 943.66667 | D68: =SUM(D43/D66) -> 1427 | E68: =SUM(E43/E66) -> 712.66667 | F68: =SUM(F43/F66) -> 1406 | G68: =SUM(G43/G66) -> 1023.6667 | H68: =SUM(H43/H66) -> 268.66667 | I68: =SUM(I43/I66) -> 3068 | J68: 0 | K68: 0 | L68: =SUM(L43/L66) -> 597.33333 | M68: 0 | N68: =SUM(N43/N66) -> 181.33333 | O68: 0 | P68: 0 | Q68: 0 | R68: =SUM(R43/R66) -> 1606.2444 | S68: =SUM(S43/S66) -> 610.66667
A69: CPS Scenario 2 | B69: =SUM(T43/B67) -> 2608.4462 | C69: =SUM(C43/C67) -> 3629.4872 | D69: =SUM(D43/D67) -> 5285.1852 | E69: =SUM(E43/E67) -> 3750.8772 | F69: =SUM(F43/F67) -> 11716.667 | G69: =SUM(G43/G67) -> 8530.5556 | H69: =SUM(H43/H67) -> 1414.0351 | I69: =SUM(I43/I67) -> 8522.2222 | J69: 0 | K69: 0 | L69: =SUM(L43/L67) -> 3143.8596 | M69: 0 | N69: =SUM(N43/N67) -> 954.38596 | O69: 0 | P69: 0 | Q69: 0 | R69: =SUM(R43/R67) -> 8453.9181 | S69: =SUM(S43/S67) -> 3214.0351
A70: Leads Scenario 3 | B70: =SUM(C70:S70) -> 4068.6193 | C70: =SUM(C47/C4)/2*0.75 -> 370.89368 | D70: =SUM(D47/D4)/2*0.75 -> 196.21584 | E70: =SUM(E47/E4)/2*0.75 -> 413.93826 | F70: =SUM(F47/F4)/2*0.75 -> 113.79801 | G70: =SUM(G47/G4)/2*0.75 -> 156.30088 | H70: =SUM(H47/H4)/2*0.75 -> 837.46898 | I70: =SUM(I47/I4)/2*0.75 -> 52.151239 | J70: =SUM(J47/J4)/2*0.75 -> 33.07393 | ... S70: =SUM(S47/S4)/2*0.75 -> 409.38865
A71: Sales Scenario 3 | B71: =SUM(C71:S71) -> 801.67964 | C71: =SUM(C70*C21) -> 96.432356 | D71: =SUM(D70*D21) -> 52.978276 | E71: =SUM(E70*E21) -> 78.648269 | F71: =SUM(F70*F21) -> 13.655761 | G71: =SUM(G70*G21) -> 18.756106 | H71: =SUM(H70*H21) -> 159.11911 | I71: =SUM(I70*I21) -> 18.774446 | J71: =SUM(J70*J21) -> 3.307393 | ... S71: =SUM(S70*S21) -> 77.783843
A72: CPL Scenario 3 | B72: =SUM(T47/B70) -> 589.88069 | C72: =SUM(C47/C70) -> 943.66667 | D72: =SUM(D47/D70) -> 1427 | E72: =SUM(E47/E70) -> 712.66667 | F72: =SUM(F47/F70) -> 1406 | G72: =SUM(G47/G70) -> 1023.6667 | H72: =SUM(H47/H70) -> 268.66667 | I72: =SUM(I47/I70) -> 3068 | J72: =SUM(J47/J70) -> 2570 | K72: 0 | L72: =SUM(L47/L70) -> 597.33333 | M72: 0 | N72: =SUM(N47/N70) -> 181.33333 | O72: 0 | P72: 0 | Q72: =SUM(Q47/Q70) -> 1606.2444 | R72: =SUM(R47/R70) -> 1606.2444 | S72: =SUM(S47/S70) -> 610.66667
A73: CPS Scenario 3 | B73: =SUM(T47/B71) -> 2993.7146 | C73: =SUM(C47/C71) -> 3629.4872 | D73: =SUM(D47/D71) -> 5285.1852 | E73: =SUM(E47/E71) -> 3750.8772 | F73: =SUM(F47/F71) -> 11716.667 | G73: =SUM(G47/G71) -> 8530.5556 | H73: =SUM(H47/H71) -> 1414.0351 | I73: =SUM(I47/I71) -> 8522.2222 | J73: =SUM(J47/J71) -> 25700 | K73: 0 | L73: =SUM(L47/L71) -> 3143.8596 | M73: 0 | N73: =SUM(N47/N71) -> 954.38596 | O73: 0 | P73: 0 | Q73: =SUM(Q47/Q71) -> 8453.9181 | R73: =SUM(R47/R71) -> 8453.9181 | S73: =SUM(S47/S71) -> 3214.0351
A74: Leads Scenario 4 | B74: =SUM(C74:S74) -> 3716.5427 | C74: =SUM(C51/C4)/2*0.75 -> 317.90887 | D74: =SUM(D51/D4)/2*0.75 -> 175.19271 | E74: =SUM(E51/E4)/2*0.75 -> 364.82694 | F74: =SUM(F51/F4)/2*0.75 -> 113.79801 | G74: =SUM(G51/G4)/2*0.75 -> 136.76327 | H74: =SUM(H51/H4)/2*0.75 -> 744.41687 | I74: =SUM(I51/I4)/2*0.75 -> 44.002608 | J74: =SUM(J51/J4)/2*0.75 -> 29.182879 | ... S74: =SUM(S51/S4)/2*0.75 -> 401.20087
A75: Sales Scenario 4 | B75: =SUM(C75:S75) -> 726.44491 | C75: =SUM(C74*C21) -> 82.656305 | D75: =SUM(D74*D21) -> 47.302032 | E75: =SUM(E74*E21) -> 69.317119 | F75: =SUM(F74*F21) -> 13.655761 | G75: =SUM(G74*G21) -> 16.411592 | H75: =SUM(H74*H21) -> 141.43921 | I75: =SUM(I74*I21) -> 15.840939 | J75: =SUM(J74*J21) -> 2.9182879 | ... S75: =SUM(S74*S21) -> 76.228166
A76: CPL Scenario 4 | B76: =SUM(T51/B74) -> 645.76144 | C76: =SUM(C51/C74) -> 943.66667 | D76: =SUM(D51/D74) -> 1427 | E76: =SUM(E51/E74) -> 712.66667 | F76: =SUM(F51/F74) -> 1406 | G76: =SUM(G51/G74) -> 1023.6667 | H76: =SUM(H51/H74) -> 268.66667 | I76: =SUM(I51/I74) -> 3068 | J76: =SUM(J51/J74) -> 2570 | ... S76: =SUM(S51/S74) -> 610.66667
A77: CPS Scenario 4 | B77: =SUM(T51/B75) -> 3303.7605 | C77: =SUM(C51/C75) -> 3629.4872 | D77: =SUM(D51/D75) -> 5285.1852 | E77: =SUM(E51/E75) -> 3750.8772 | F77: =SUM(F51/F75) -> 11716.667 | G77: =SUM(G51/G75) -> 8530.5556 | H77: =SUM(H51/H75) -> 1414.0351 | I77: =SUM(I51/I75) -> 8522.2222 | J77: =SUM(J51/J75) -> 25700 | ... S77: =SUM(S51/S75) -> 3214.0351
A78: Leads Scenario 5 | B78: =SUM(C78:S78) -> 3991.5745 | C78: =SUM(C55/C4)/2*0.75 -> 291.41646 | D78: =SUM(D55/D4)/2*0.75 -> 182.20042 | E78: =SUM(E55/E4)/2*0.75 -> 378.85875 | F78: =SUM(F55/F4)/2*0.75 -> 108.10811 | G78: =SUM(G55/G4)/2*0.75 -> 141.64767 | H78: =SUM(H55/H4)/2*0.75 -> 837.46898 | I78: =SUM(I55/I4)/2*0.75 -> 39.113429 | J78: =SUM(J55/J4)/2*0.75 -> 31.128405 | ... S78: =SUM(S55/S4)/2*0.75 -> 401.20087
A79: Sales Scenario 5 | B79: =SUM(C79:S79) -> 775.91024 | C79: =SUM(C78*C21) -> 75.76828 | D79: =SUM(D78*D21) -> 49.194114 | E79: =SUM(E78*E21) -> 71.983162 | F79: =SUM(F78*F21) -> 12.972973 | G79: =SUM(G78*G21) -> 16.997721 | H79: =SUM(H78*H21) -> 159.11911 | I79: =SUM(I78*I21) -> 14.080834 | J79: =SUM(J78*J21) -> 3.1128405 | ... S79: =SUM(S78*S21) -> 76.228166
A80: CPL Scenario 5 | B80: =SUM(T55/B78) -> 624.31504 | C80: =SUM(C55/C78) -> 943.66667 | D80: =SUM(D55/D78) -> 1427 | E80: =SUM(E55/E78) -> 712.66667 | F80: =SUM(F55/F78) -> 1406 | G80: =SUM(G55/G78) -> 1023.6667 | H80: =SUM(H55/H78) -> 268.66667 | I80: =SUM(I55/I78) -> 3068 | J80: =SUM(J55/J78) -> 2570 | ... S80: =SUM(S55/S78) -> 610.66667
A81: CPS Scenario 5 | B81: =SUM(T55/B79) -> 3211.7117 | C81: =SUM(C55/C79) -> 3629.4872 | D81: =SUM(D55/D79) -> 5285.1852 | E81: =SUM(E55/E79) -> 3750.8772 | F81: =SUM(F55/F79) -> 11716.667 | G81: =SUM(G55/G79) -> 8530.5556 | H81: =SUM(H55/H79) -> 1414.0351 | I81: =SUM(I55/I79) -> 8522.2222 | J81: =SUM(J55/J79) -> 25700 | ... S81: =SUM(S55/S79) -> 3214.0351
A82: ROMI | B82: =((B79*30000)-T55)/T55 -> 8.3408135
A83: Weekly budget Scenario 1 (16 weeks) | B83: =SUM(C83:S83) -> 150000 | C83: =C39/16 -> 17500 | D83: =D39/16 -> 18750 | E83: =E39/16 -> 6250 | F83: =F39/16 -> 18750 | G83: =G39/16 -> 18750 | H83: =H39/16 -> 3750 | I83: =I39/16 -> 6250 | J83: =J39/16 -> 9375 | ... S83: =S39/16 -> 15625
A84: Weekly budget Scenario 2 (16 weeks) | B84: =SUM(C84:S84) -> 150000 | C84: =C43/16 -> 15375 | D84: =D43/16 -> 11187.5 | E84: =E43/16 -> 14812.5 | F84: =F43/16 -> 4687.5 | G84: =G43/16 -> 8250 | H84: =H43/16 -> 38875 | I84: =I43/16 -> 8250 | J84: =J43/16 -> 0 | ... S84: =S43/16 -> 13437.5
A85: Weekly budgeScenario 3 (16 weeks) | B85: =SUM(C85:S85) -> 150000 | C85: =C47/16 -> 21875 | D85: =D47/16 -> 17500 | E85: =E47/16 -> 18437.5 | F85: =F47/16 -> 10000 | G85: =G47/16 -> 10000 | H85: =H47/16 -> 14062.5 | I85: =I47/16 -> 10000 | J85: =J47/16 -> 5312.5 | ... S85: =S47/16 -> 15625
A86: Weekly budgeScenario 4 (20 weeks) | B86: =SUM(C86:S86) -> 120000 | C86: =C51/20 -> 15000 | D86: =D51/20 -> 12500 | E86: =E51/20 -> 13000 | F86: =F51/20 -> 8000 | G86: =G51/20 -> 7000 | H86: =H51/20 -> 10000 | I86: =I51/20 -> 6750 | J86: =J51/20 -> 3750 | ... S86: =S51/20 -> 12250
A88: Weekly budgeScenario 5 (20 weeks) | B88: =SUM(C88:S88) -> 124600 | C88: =C55/20 -> 13750 | D88: =D55/20 -> 13000 | E88: =E55/20 -> 13500 | F88: =F55/20 -> 7600 | G88: =G55/20 -> 7250 | H88: =H55/20 -> 11250 | I88: =I55/20 -> 6000 | J88: =J55/20 -> 4000 | ... S88: =S55/20 -> 12250
C90: PCGB | D90: PD | E90: PKO | F90: POF | G90: PIT | H90: TRK | I90: PCL | J90: PIB SPA | K90: PNO | L90: PIB POR | M90: PCH | N90: PTW | O90: PCA | P90: PPL | Q90: PJ | R90: PBR | S90: PCNA | T90: Total
A91: TVC Budget allocation (Initial scenario) | B91: TVC Budget allocation (Initial scenario) | C91: 273000 | D91: 315000 | E91: 189000 | F91: 210000 | G91: 168000 | H91: 0 | I91: 231000 | J91: 147000 | K91: 63000 | L91: 42000 | M91: 105000 | N91: 84000 | O91: 210000 | P91: 63000 | Q91: 0 | R91: 0 | S91: 0 | T91: =SUM(C91:S91) -> 2100000
A92: TVC Budget allocation (Scenario incl. PJ, BBR) | C92: 250000 | D92: 300000 | E92: 170000 | F92: 200000 | G92: 150000 | H92: 0 | I92: 200000 | J92: 140000 | K92: 65000 | L92: 45000 | M92: 105000 | N92: 85000 | O92: 210000 | P92: 60000 | Q92: 65000 | R92: 55000 | S92: 0 | T92: =SUM(C92:S92) -> 2100000
A94: Assumptions:
A95: For CPL and lead-to-sales rate for PJ/PBR, an average of comparable markets from CTG 1.0 was assumed
A96: Split TVC budget according to sales targets & PHD potential calculation
A97: Budget reallocation only to Porsche subsidiaries
A99: Budget origin
A100: VMK Budget | B100: 800000
A101: E4 HY1 | B101: 500000
A102: E4 HY2 | B102: 300000
A103: VM budget | B103: 1000000
A104: Total budget CTG 2.0 | B104: =SUM(B100:B103) -> 2600000
A106: Team PHD (Non working media) | B106: 107977
A107: Total net media budget incl. PCNA, PJ, PBR | B107: =B104-B106 -> 2492023
A108: Budget reallocation PCNA, PJ, PBR | B108: 365000
A109: Working media | B109: =B104-B106-B108 -> 2127023

Sheet Media Mix
A1: Close the gap 2026 | C1: PCGB | D1: PCGB | E1: PD | F1: PD | G1: PKO | H1: PKO | I1: POF | J1: POF | K1: PIT | L1: PIT | M1: TRK | N1: TRK | O1: PCL | P1: PCL | Q1: PIB SPA | R1: PIB SPA | S1: PNO | T1: PNO | U1: PIB POR | V1: PIB POR | W1: PCH | X1: PCH | Y1: PTW | Z1: PTW | AA1: PCA | AB1: PCA | AC1: PPL | AD1: PPL
C2: Start | D2: Ende | E2: Start | F2: Ende | G2: Start | H2: Ende | I2: Start | J2: Ende | K2: Start | L2: Ende | M2: Start | N2: Ende | O2: Start | P2: Ende | Q2: Start | R2: Ende | S2: Start | T2: Ende | U2: Start | V2: Ende | W2: Start | X2: Ende | Y2: Start | Z2: Ende | AA2: Start | AB2: Ende | AC2: Start | AD2: Ende
A3: Macan BEV | B3: Google Ads | C3: 46143 | D3: 46264 | E3: 46143 | F3: 46264 | G3: 46143 | H3: 46264 | I3: 46143 | J3: 46264 | K3: 46143 | L3: 46264 | M3: 46143 | N3: 46264 | O3: 46143 | P3: 46264 | Q3: 46143 | R3: 46264 | S3: 46143 | T3: 46264 | U3: 46143 | V3: 46264 | W3: 46143 | X3: 46264 | Y3: 46143 | Z3: 46264 | AA3: 46143 | AB3: 46264 | AC3: 46143 | AD3: 46264
A4: Macan BEV | B4: Google Inventory Ads | C4: 46143 | D4: 46264 | G4: 46143 | H4: 46264 | I4: 46143 | J4: 46264 | K4: 46174 | L4: 46264 | O4: 46143 | P4: 46264 | Q4: 46143 | R4: 46264
A5: Macan BEV | B5: META Inventory Ads | C5: 46143 | D5: 46264 | E5: 46143 | F5: 46264 | G5: 46143 | H5: 46264 | I5: 46143 | J5: 46264 | K5: 46143 | L5: 46264 | M5: 46143 | N5: 46264 | O5: 46143 | P5: 46264 | Q5: 46143 | R5: 46264 | S5: 46143 | T5: 46264 | U5: 46143 | V5: 46264 | W5: 46143 | X5: 46264 | Y5: 46143 | Z5: 46264 | AA5: 46143 | AB5: 46264 | AC5: 46143 | AD5: 46264
A6: Macan BEV | B6: Paid Social | C6: 46204 | D6: 46264 | E6: 46204 | F6: 46264 | G6: 46204 | H6: 46264 | I6: 46204 | J6: 46264 | K6: 46204 | L6: 46264 | M6: 46204 | N6: 46264 | O6: 46204 | P6: 46264 | Q6: 46204 | R6: 46264 | S6: 46204 | T6: 46264 | U6: 46204 | V6: 46264 | W6: 46204 | X6: 46264 | Y6: 46204 | Z6: 46264 | AA6: 46204 | AB6: 46264 | AC6: 46204 | AD6: 46264
A7: Cayenne E3 II | B7: Google Ads | C7: 46143 | D7: 46264 | E7: 46143 | F7: 46264 | G7: 46143 | H7: 46264 | I7: 46143 | J7: 46264 | K7: 46143 | L7: 46264 | M7: 46174 | N7: 46264 | O7: 46143 | P7: 46264 | Y7: 46143 | Z7: 46264 | AA7: 46174 | AB7: 46264 | AC7: 46174 | AD7: 46264
A8: Cayenne E3 II | B8: Google Inventory Ads | C8: 46143 | D8: 46264 | G8: 46143 | H8: 46264 | I8: 46143 | J8: 46264 | K8: 46174 | L8: 46264 | O8: 46143 | P8: 46264 | Y8: 46143 | Z8: 46264
A9: Cayenne E3 II | B9: META Inventory Ads | C9: 46143 | D9: 46264 | E9: 46143 | F9: 46264 | G9: 46143 | H9: 46264 | I9: 46143 | J9: 46264 | K9: 46143 | L9: 46264 | M9: 46143 | N9: 46264 | O9: 46143 | P9: 46264 | Y9: 46143 | Z9: 46264 | AA9: 46143 | AB9: 46264 | AC9: 46143 | AD9: 46264
A10: Cayenne E3 II | B10: Paid Social | C10: 46204 | D10: 46264 | E10: 46204 | F10: 46264 | G10: 46204 | H10: 46264 | K10: 46204 | L10: 46264 | M10: 46204 | N10: 46264 | O10: 46204 | P10: 46264 | Y10: 46204 | Z10: 46264 | AA10: 46204 | AB10: 46264 | AC10: 46204 | AD10: 46264
A11: Cayenne E4 | B11: Google Ads | C11: 46143 | D11: 46264 | E11: 46143 | F11: 46264 | G11: 46143 | H11: 46264 | I11: 46143 | J11: 46264 | K11: 46143 | L11: 46264 | M11: 46143 | N11: 46264 | O11: 46143 | P11: 46264 | Q11: 46143 | R11: 46264 | S11: 46143 | T11: 46264 | U11: 46143 | V11: 46264 | W11: 46143 | X11: 46264 | Y11: 46143 | Z11: 46264 | AA11: 46143 | AB11: 46264 | AC11: 46143 | AD11: 46264
A12: Cayenne E4 | B12: Google Inventory Ads | C12: 46204 | D12: 46264 | G12: 46204 | H12: 46264 | I12: 46204 | J12: 46264 | K12: 46204 | L12: 46264 | O12: 46204 | P12: 46264 | Q12: 46204 | R12: 46264
A13: Cayenne E4 | B13: META Inventory Ads | C13: 46204 | D13: 46264 | E13: 46204 | F13: 46264 | G13: 46204 | H13: 46264 | I13: 46204 | J13: 46264 | K13: 46204 | L13: 46264 | M13: 46204 | N13: 46264 | O13: 46204 | P13: 46264 | Q13: 46204 | R13: 46264 | S13: 46204 | T13: 46264 | U13: 46204 | V13: 46264 | W13: 46204 | X13: 46264 | Y13: 46204 | Z13: 46264 | AA13: 46204 | AB13: 46264 | AC13: 46204 | AD13: 46264
A14: Cayenne E4 | B14: Paid Social | C14: 46204 | D14: 46264 | E14: 46204 | F14: 46264 | G14: 46204 | H14: 46264 | I14: 46204 | J14: 46264 | K14: 46204 | L14: 46264 | M14: 46204 | N14: 46264 | O14: 46204 | P14: 46264 | Q14: 46204 | R14: 46264 | S14: 46204 | T14: 46264 | U14: 46204 | V14: 46264 | W14: 46204 | X14: 46264 | Y14: 46204 | Z14: 46264 | AA14: 46204 | AB14: 46264 | AC14: 46204 | AD14: 46264

Sheet Zeitstrahl nach Markt
A1: 📅 Zeitstrahl (Wochenansicht) – Measuren je Markt
A2: Legende (Baureihen): | B2: Macan BEV | C2: Cayenne E3 II | D2: Cayenne E4
E3: 46139 | F3: 46146 | G3: 46153 | H3: 46160 | I3: 46167 | J3: 46174 | K3: 46181 | L3: 46188 | M3: 46195 | N3: 46202 | O3: 46209 | P3: 46216 | Q3: 46223 | R3: 46230 | S3: 46237 | T3: 46244 | U3: 46251 | V3: 46258 | AB3: 46139 | AC3: 46146 | AD3: 46153 | AE3: 46160 | AF3: 46167 | AG3: 46174 | AH3: 46181 | AI3: 46188 | AJ3: 46195 | AK3: 46202 | AL3: 46209 | AM3: 46216 | AN3: 46223 | AO3: 46230 | AP3: 46237 | AQ3: 46244 | AR3: 46251 | AS3: 46258
A4: Markt: PCGB | X4: Markt: PCGB (Survey)
A5: Model | B5: CTG Measure | C5: Start | D5: Ende | E5: CW18 | F5: CW19 | G5: CW20 | H5: CW21 | I5: CW22 | J5: CW23 | K5: CW24 | L5: CW25 | M5: CW26 | N5: CW27 | O5: CW28 | P5: CW29 | Q5: CW30 | R5: CW31 | S5: CW32 | T5: CW33 | U5: CW34 | V5: CW35 | X5: Model | Y5: Local Measure | Z5: Start | AA5: Ende | AB5: CW18 | AC5: CW19 | AD5: CW20 | AE5: CW21 | AF5: CW22 | AG5: CW23 | AH5: CW24 | AI5: CW25 | AJ5: CW26 | AK5: CW27 | AL5: CW28 | AM5: CW29 | AN5: CW30 | AO5: CW31 | AP5: CW32 | AQ5: CW33 | AR5: CW34 | AS5: CW35 | AT5: Channel | AU5: Budget | AV5: KPI | AW5: Audience
A6: Macan BEV | B6: Google Ads | C6: 46143 | D6: 46264 | E6: =IFERROR(IF(OR($A6="",$A6="Model",LEFT($A6,5)="Markt"),"",IF(AND($C6<=E$3+6,$D6>=E$3),"■","")),"") -> ■ | F6: =IFERROR(IF(OR($A6="",$A6="Model",LEFT($A6,5)="Markt"),"",IF(AND($C6<=F$3+6,$D6>=F$3),"■","")),"") -> ■ | G6: =IFERROR(IF(OR($A6="",$A6="Model",LEFT($A6,5)="Markt"),"",IF(AND($C6<=G$3+6,$D6>=G$3),"■","")),"") -> ■ | H6: =IFERROR(IF(OR($A6="",$A6="Model",LEFT($A6,5)="Markt"),"",IF(AND($C6<=H$3+6,$D6>=H$3),"■","")),"") -> ■ | I6: =IFERROR(IF(OR($A6="",$A6="Model",LEFT($A6,5)="Markt"),"",IF(AND($C6<=I$3+6,$D6>=I$3),"■","")),"") -> ■ | J6: =IFERROR(IF(OR($A6="",$A6="Model",LEFT($A6,5)="Markt"),"",IF(AND($C6<=J$3+6,$D6>=J$3),"■","")),"") -> ■ | K6: =IFERROR(IF(OR($A6="",$A6="Model",LEFT($A6,5)="Markt"),"",IF(AND($C6<=K$3+6,$D6>=K$3),"■","")),"") -> ■ | L6: =IFERROR(IF(OR($A6="",$A6="Model",LEFT($A6,5)="Markt"),"",IF(AND($C6<=L$3+6,$D6>=L$3),"■","")),"") -> ■ | ... V6: =IFERROR(IF(OR($A6="",$A6="Model",LEFT($A6,5)="Markt"),"",IF(AND($C6<=V$3+6,$D6>=V$3),"■","")),"") -> ■ | X6: Cayenne E3 II | Y6: Always on | AB6: =IF(AND($Z6<=AB$3+6,$AA6>=AB$3),"■","") | AC6: =IF(AND($Z6<=AC$3+6,$AA6>=AC$3),"■","") | AD6: =IF(AND($Z6<=AD$3+6,$AA6>=AD$3),"■","") | AE6: =IF(AND($Z6<=AE$3+6,$AA6>=AE$3),"■","") | AF6: =IF(AND($Z6<=AF$3+6,$AA6>=AF$3),"■","") | AG6: =IF(AND($Z6<=AG$3+6,$AA6>=AG$3),"■","") | AH6: =IF(AND($Z6<=AH$3+6,$AA6>=AH$3),"■","") | AI6: =IF(AND($Z6<=AI$3+6,$AA6>=AI$3),"■","") | ... AS6: =IF(AND($Z6<=AS$3+6,$AA6>=AS$3),"■","")
A7: Macan BEV | B7: Google Inventory Ads | C7: 46143 | D7: 46264 | E7: =IFERROR(IF(OR($A7="",$A7="Model",LEFT($A7,5)="Markt"),"",IF(AND($C7<=E$3+6,$D7>=E$3),"■","")),"") -> ■ | F7: =IFERROR(IF(OR($A7="",$A7="Model",LEFT($A7,5)="Markt"),"",IF(AND($C7<=F$3+6,$D7>=F$3),"■","")),"") -> ■ | G7: =IFERROR(IF(OR($A7="",$A7="Model",LEFT($A7,5)="Markt"),"",IF(AND($C7<=G$3+6,$D7>=G$3),"■","")),"") -> ■ | H7: =IFERROR(IF(OR($A7="",$A7="Model",LEFT($A7,5)="Markt"),"",IF(AND($C7<=H$3+6,$D7>=H$3),"■","")),"") -> ■ | I7: =IFERROR(IF(OR($A7="",$A7="Model",LEFT($A7,5)="Markt"),"",IF(AND($C7<=I$3+6,$D7>=I$3),"■","")),"") -> ■ | J7: =IFERROR(IF(OR($A7="",$A7="Model",LEFT($A7,5)="Markt"),"",IF(AND($C7<=J$3+6,$D7>=J$3),"■","")),"") -> ■ | K7: =IFERROR(IF(OR($A7="",$A7="Model",LEFT($A7,5)="Markt"),"",IF(AND($C7<=K$3+6,$D7>=K$3),"■","")),"") -> ■ | L7: =IFERROR(IF(OR($A7="",$A7="Model",LEFT($A7,5)="Markt"),"",IF(AND($C7<=L$3+6,$D7>=L$3),"■","")),"") -> ■ | ... V7: =IFERROR(IF(OR($A7="",$A7="Model",LEFT($A7,5)="Markt"),"",IF(AND($C7<=V$3+6,$D7>=V$3),"■","")),"") -> ■
A8: Macan BEV | B8: META Inventory Ads | C8: 46143 | D8: 46264 | E8: =IFERROR(IF(OR($A8="",$A8="Model",LEFT($A8,5)="Markt"),"",IF(AND($C8<=E$3+6,$D8>=E$3),"■","")),"") -> ■ | F8: =IFERROR(IF(OR($A8="",$A8="Model",LEFT($A8,5)="Markt"),"",IF(AND($C8<=F$3+6,$D8>=F$3),"■","")),"") -> ■ | G8: =IFERROR(IF(OR($A8="",$A8="Model",LEFT($A8,5)="Markt"),"",IF(AND($C8<=G$3+6,$D8>=G$3),"■","")),"") -> ■ | H8: =IFERROR(IF(OR($A8="",$A8="Model",LEFT($A8,5)="Markt"),"",IF(AND($C8<=H$3+6,$D8>=H$3),"■","")),"") -> ■ | I8: =IFERROR(IF(OR($A8="",$A8="Model",LEFT($A8,5)="Markt"),"",IF(AND($C8<=I$3+6,$D8>=I$3),"■","")),"") -> ■ | J8: =IFERROR(IF(OR($A8="",$A8="Model",LEFT($A8,5)="Markt"),"",IF(AND($C8<=J$3+6,$D8>=J$3),"■","")),"") -> ■ | K8: =IFERROR(IF(OR($A8="",$A8="Model",LEFT($A8,5)="Markt"),"",IF(AND($C8<=K$3+6,$D8>=K$3),"■","")),"") -> ■ | L8: =IFERROR(IF(OR($A8="",$A8="Model",LEFT($A8,5)="Markt"),"",IF(AND($C8<=L$3+6,$D8>=L$3),"■","")),"") -> ■ | ... V8: =IFERROR(IF(OR($A8="",$A8="Model",LEFT($A8,5)="Markt"),"",IF(AND($C8<=V$3+6,$D8>=V$3),"■","")),"") -> ■
A9: Macan BEV | B9: Paid Social | C9: 46204 | D9: 46264 | E9: =IFERROR(IF(OR($A9="",$A9="Model",LEFT($A9,5)="Markt"),"",IF(AND($C9<=E$3+6,$D9>=E$3),"■","")),"") | F9: =IFERROR(IF(OR($A9="",$A9="Model",LEFT($A9,5)="Markt"),"",IF(AND($C9<=F$3+6,$D9>=F$3),"■","")),"") | G9: =IFERROR(IF(OR($A9="",$A9="Model",LEFT($A9,5)="Markt"),"",IF(AND($C9<=G$3+6,$D9>=G$3),"■","")),"") | H9: =IFERROR(IF(OR($A9="",$A9="Model",LEFT($A9,5)="Markt"),"",IF(AND($C9<=H$3+6,$D9>=H$3),"■","")),"") | I9: =IFERROR(IF(OR($A9="",$A9="Model",LEFT($A9,5)="Markt"),"",IF(AND($C9<=I$3+6,$D9>=I$3),"■","")),"") | J9: =IFERROR(IF(OR($A9="",$A9="Model",LEFT($A9,5)="Markt"),"",IF(AND($C9<=J$3+6,$D9>=J$3),"■","")),"") | K9: =IFERROR(IF(OR($A9="",$A9="Model",LEFT($A9,5)="Markt"),"",IF(AND($C9<=K$3+6,$D9>=K$3),"■","")),"") | L9: =IFERROR(IF(OR($A9="",$A9="Model",LEFT($A9,5)="Markt"),"",IF(AND($C9<=L$3+6,$D9>=L$3),"■","")),"") | ... V9: =IFERROR(IF(OR($A9="",$A9="Model",LEFT($A9,5)="Markt"),"",IF(AND($C9<=V$3+6,$D9>=V$3),"■","")),"") -> ■
A10: Cayenne E3 II | B10: Google Ads | C10: 46143 | D10: 46264 | E10: =IFERROR(IF(OR($A10="",$A10="Model",LEFT($A10,5)="Markt"),"",IF(AND($C10<=E$3+6,$D10>=E$3),"■","")),"") -> ■ | F10: =IFERROR(IF(OR($A10="",$A10="Model",LEFT($A10,5)="Markt"),"",IF(AND($C10<=F$3+6,$D10>=F$3),"■","")),"") -> ■ | G10: =IFERROR(IF(OR($A10="",$A10="Model",LEFT($A10,5)="Markt"),"",IF(AND($C10<=G$3+6,$D10>=G$3),"■","")),"") -> ■ | H10: =IFERROR(IF(OR($A10="",$A10="Model",LEFT($A10,5)="Markt"),"",IF(AND($C10<=H$3+6,$D10>=H$3),"■","")),"") -> ■ | I10: =IFERROR(IF(OR($A10="",$A10="Model",LEFT($A10,5)="Markt"),"",IF(AND($C10<=I$3+6,$D10>=I$3),"■","")),"") -> ■ | J10: =IFERROR(IF(OR($A10="",$A10="Model",LEFT($A10,5)="Markt"),"",IF(AND($C10<=J$3+6,$D10>=J$3),"■","")),"") -> ■ | K10: =IFERROR(IF(OR($A10="",$A10="Model",LEFT($A10,5)="Markt"),"",IF(AND($C10<=K$3+6,$D10>=K$3),"■","")),"") -> ■ | L10: =IFERROR(IF(OR($A10="",$A10="Model",LEFT($A10,5)="Markt"),"",IF(AND($C10<=L$3+6,$D10>=L$3),"■","")),"") -> ■ | ... V10: =IFERROR(IF(OR($A10="",$A10="Model",LEFT($A10,5)="Markt"),"",IF(AND($C10<=V$3+6,$D10>=V$3),"■","")),"") -> ■
A11: Cayenne E3 II | B11: Google Inventory Ads | C11: 46143 | D11: 46264 | E11: =IFERROR(IF(OR($A11="",$A11="Model",LEFT($A11,5)="Markt"),"",IF(AND($C11<=E$3+6,$D11>=E$3),"■","")),"") -> ■ | F11: =IFERROR(IF(OR($A11="",$A11="Model",LEFT($A11,5)="Markt"),"",IF(AND($C11<=F$3+6,$D11>=F$3),"■","")),"") -> ■ | G11: =IFERROR(IF(OR($A11="",$A11="Model",LEFT($A11,5)="Markt"),"",IF(AND($C11<=G$3+6,$D11>=G$3),"■","")),"") -> ■ | H11: =IFERROR(IF(OR($A11="",$A11="Model",LEFT($A11,5)="Markt"),"",IF(AND($C11<=H$3+6,$D11>=H$3),"■","")),"") -> ■ | I11: =IFERROR(IF(OR($A11="",$A11="Model",LEFT($A11,5)="Markt"),"",IF(AND($C11<=I$3+6,$D11>=I$3),"■","")),"") -> ■ | J11: =IFERROR(IF(OR($A11="",$A11="Model",LEFT($A11,5)="Markt"),"",IF(AND($C11<=J$3+6,$D11>=J$3),"■","")),"") -> ■ | K11: =IFERROR(IF(OR($A11="",$A11="Model",LEFT($A11,5)="Markt"),"",IF(AND($C11<=K$3+6,$D11>=K$3),"■","")),"") -> ■ | L11: =IFERROR(IF(OR($A11="",$A11="Model",LEFT($A11,5)="Markt"),"",IF(AND($C11<=L$3+6,$D11>=L$3),"■","")),"") -> ■ | ... V11: =IFERROR(IF(OR($A11="",$A11="Model",LEFT($A11,5)="Markt"),"",IF(AND($C11<=V$3+6,$D11>=V$3),"■","")),"") -> ■
A12: Cayenne E3 II | B12: META Inventory Ads | C12: 46143 | D12: 46264 | E12: =IFERROR(IF(OR($A12="",$A12="Model",LEFT($A12,5)="Markt"),"",IF(AND($C12<=E$3+6,$D12>=E$3),"■","")),"") -> ■ | F12: =IFERROR(IF(OR($A12="",$A12="Model",LEFT($A12,5)="Markt"),"",IF(AND($C12<=F$3+6,$D12>=F$3),"■","")),"") -> ■ | G12: =IFERROR(IF(OR($A12="",$A12="Model",LEFT($A12,5)="Markt"),"",IF(AND($C12<=G$3+6,$D12>=G$3),"■","")),"") -> ■ | H12: =IFERROR(IF(OR($A12="",$A12="Model",LEFT($A12,5)="Markt"),"",IF(AND($C12<=H$3+6,$D12>=H$3),"■","")),"") -> ■ | I12: =IFERROR(IF(OR($A12="",$A12="Model",LEFT($A12,5)="Markt"),"",IF(AND($C12<=I$3+6,$D12>=I$3),"■","")),"") -> ■ | J12: =IFERROR(IF(OR($A12="",$A12="Model",LEFT($A12,5)="Markt"),"",IF(AND($C12<=J$3+6,$D12>=J$3),"■","")),"") -> ■ | K12: =IFERROR(IF(OR($A12="",$A12="Model",LEFT($A12,5)="Markt"),"",IF(AND($C12<=K$3+6,$D12>=K$3),"■","")),"") -> ■ | L12: =IFERROR(IF(OR($A12="",$A12="Model",LEFT($A12,5)="Markt"),"",IF(AND($C12<=L$3+6,$D12>=L$3),"■","")),"") -> ■ | ... V12: =IFERROR(IF(OR($A12="",$A12="Model",LEFT($A12,5)="Markt"),"",IF(AND($C12<=V$3+6,$D12>=V$3),"■","")),"") -> ■
A13: Cayenne E3 II | B13: Paid Social | C13: 46204 | D13: 46264 | E13: =IFERROR(IF(OR($A13="",$A13="Model",LEFT($A13,5)="Markt"),"",IF(AND($C13<=E$3+6,$D13>=E$3),"■","")),"") | F13: =IFERROR(IF(OR($A13="",$A13="Model",LEFT($A13,5)="Markt"),"",IF(AND($C13<=F$3+6,$D13>=F$3),"■","")),"") | G13: =IFERROR(IF(OR($A13="",$A13="Model",LEFT($A13,5)="Markt"),"",IF(AND($C13<=G$3+6,$D13>=G$3),"■","")),"") | H13: =IFERROR(IF(OR($A13="",$A13="Model",LEFT($A13,5)="Markt"),"",IF(AND($C13<=H$3+6,$D13>=H$3),"■","")),"") | I13: =IFERROR(IF(OR($A13="",$A13="Model",LEFT($A13,5)="Markt"),"",IF(AND($C13<=I$3+6,$D13>=I$3),"■","")),"") | J13: =IFERROR(IF(OR($A13="",$A13="Model",LEFT($A13,5)="Markt"),"",IF(AND($C13<=J$3+6,$D13>=J$3),"■","")),"") | K13: =IFERROR(IF(OR($A13="",$A13="Model",LEFT($A13,5)="Markt"),"",IF(AND($C13<=K$3+6,$D13>=K$3),"■","")),"") | L13: =IFERROR(IF(OR($A13="",$A13="Model",LEFT($A13,5)="Markt"),"",IF(AND($C13<=L$3+6,$D13>=L$3),"■","")),"") | ... V13: =IFERROR(IF(OR($A13="",$A13="Model",LEFT($A13,5)="Markt"),"",IF(AND($C13<=V$3+6,$D13>=V$3),"■","")),"") -> ■
A14: Cayenne E4 | B14: Google Ads | C14: 46143 | D14: 46264 | E14: =IFERROR(IF(OR($A14="",$A14="Model",LEFT($A14,5)="Markt"),"",IF(AND($C14<=E$3+6,$D14>=E$3),"■","")),"") -> ■ | F14: =IFERROR(IF(OR($A14="",$A14="Model",LEFT($A14,5)="Markt"),"",IF(AND($C14<=F$3+6,$D14>=F$3),"■","")),"") -> ■ | G14: =IFERROR(IF(OR($A14="",$A14="Model",LEFT($A14,5)="Markt"),"",IF(AND($C14<=G$3+6,$D14>=G$3),"■","")),"") -> ■ | H14: =IFERROR(IF(OR($A14="",$A14="Model",LEFT($A14,5)="Markt"),"",IF(AND($C14<=H$3+6,$D14>=H$3),"■","")),"") -> ■ | I14: =IFERROR(IF(OR($A14="",$A14="Model",LEFT($A14,5)="Markt"),"",IF(AND($C14<=I$3+6,$D14>=I$3),"■","")),"") -> ■ | J14: =IFERROR(IF(OR($A14="",$A14="Model",LEFT($A14,5)="Markt"),"",IF(AND($C14<=J$3+6,$D14>=J$3),"■","")),"") -> ■ | K14: =IFERROR(IF(OR($A14="",$A14="Model",LEFT($A14,5)="Markt"),"",IF(AND($C14<=K$3+6,$D14>=K$3),"■","")),"") -> ■ | L14: =IFERROR(IF(OR($A14="",$A14="Model",LEFT($A14,5)="Markt"),"",IF(AND($C14<=L$3+6,$D14>=L$3),"■","")),"") -> ■ | ... V14: =IFERROR(IF(OR($A14="",$A14="Model",LEFT($A14,5)="Markt"),"",IF(AND($C14<=V$3+6,$D14>=V$3),"■","")),"") -> ■
A15: Cayenne E4 | B15: Google Inventory Ads | C15: 46204 | D15: 46264 | E15: =IFERROR(IF(OR($A15="",$A15="Model",LEFT($A15,5)="Markt"),"",IF(AND($C15<=E$3+6,$D15>=E$3),"■","")),"") | F15: =IFERROR(IF(OR($A15="",$A15="Model",LEFT($A15,5)="Markt"),"",IF(AND($C15<=F$3+6,$D15>=F$3),"■","")),"") | G15: =IFERROR(IF(OR($A15="",$A15="Model",LEFT($A15,5)="Markt"),"",IF(AND($C15<=G$3+6,$D15>=G$3),"■","")),"") | H15: =IFERROR(IF(OR($A15="",$A15="Model",LEFT($A15,5)="Markt"),"",IF(AND($C15<=H$3+6,$D15>=H$3),"■","")),"") | I15: =IFERROR(IF(OR($A15="",$A15="Model",LEFT($A15,5)="Markt"),"",IF(AND($C15<=I$3+6,$D15>=I$3),"■","")),"") | J15: =IFERROR(IF(OR($A15="",$A15="Model",LEFT($A15,5)="Markt"),"",IF(AND($C15<=J$3+6,$D15>=J$3),"■","")),"") | K15: =IFERROR(IF(OR($A15="",$A15="Model",LEFT($A15,5)="Markt"),"",IF(AND($C15<=K$3+6,$D15>=K$3),"■","")),"") | L15: =IFERROR(IF(OR($A15="",$A15="Model",LEFT($A15,5)="Markt"),"",IF(AND($C15<=L$3+6,$D15>=L$3),"■","")),"") | ... V15: =IFERROR(IF(OR($A15="",$A15="Model",LEFT($A15,5)="Markt"),"",IF(AND($C15<=V$3+6,$D15>=V$3),"■","")),"") -> ■
A16: Cayenne E4 | B16: META Inventory Ads | C16: 46204 | D16: 46264 | E16: =IFERROR(IF(OR($A16="",$A16="Model",LEFT($A16,5)="Markt"),"",IF(AND($C16<=E$3+6,$D16>=E$3),"■","")),"") | F16: =IFERROR(IF(OR($A16="",$A16="Model",LEFT($A16,5)="Markt"),"",IF(AND($C16<=F$3+6,$D16>=F$3),"■","")),"") | G16: =IFERROR(IF(OR($A16="",$A16="Model",LEFT($A16,5)="Markt"),"",IF(AND($C16<=G$3+6,$D16>=G$3),"■","")),"") | H16: =IFERROR(IF(OR($A16="",$A16="Model",LEFT($A16,5)="Markt"),"",IF(AND($C16<=H$3+6,$D16>=H$3),"■","")),"") | I16: =IFERROR(IF(OR($A16="",$A16="Model",LEFT($A16,5)="Markt"),"",IF(AND($C16<=I$3+6,$D16>=I$3),"■","")),"") | J16: =IFERROR(IF(OR($A16="",$A16="Model",LEFT($A16,5)="Markt"),"",IF(AND($C16<=J$3+6,$D16>=J$3),"■","")),"") | K16: =IFERROR(IF(OR($A16="",$A16="Model",LEFT($A16,5)="Markt"),"",IF(AND($C16<=K$3+6,$D16>=K$3),"■","")),"") | L16: =IFERROR(IF(OR($A16="",$A16="Model",LEFT($A16,5)="Markt"),"",IF(AND($C16<=L$3+6,$D16>=L$3),"■","")),"") | ... V16: =IFERROR(IF(OR($A16="",$A16="Model",LEFT($A16,5)="Markt"),"",IF(AND($C16<=V$3+6,$D16>=V$3),"■","")),"") -> ■
A17: Cayenne E4 | B17: Paid Social | C17: 46204 | D17: 46264 | E17: =IFERROR(IF(OR($A17="",$A17="Model",LEFT($A17,5)="Markt"),"",IF(AND($C17<=E$3+6,$D17>=E$3),"■","")),"") | F17: =IFERROR(IF(OR($A17="",$A17="Model",LEFT($A17,5)="Markt"),"",IF(AND($C17<=F$3+6,$D17>=F$3),"■","")),"") | G17: =IFERROR(IF(OR($A17="",$A17="Model",LEFT($A17,5)="Markt"),"",IF(AND($C17<=G$3+6,$D17>=G$3),"■","")),"") | H17: =IFERROR(IF(OR($A17="",$A17="Model",LEFT($A17,5)="Markt"),"",IF(AND($C17<=H$3+6,$D17>=H$3),"■","")),"") | I17: =IFERROR(IF(OR($A17="",$A17="Model",LEFT($A17,5)="Markt"),"",IF(AND($C17<=I$3+6,$D17>=I$3),"■","")),"") | J17: =IFERROR(IF(OR($A17="",$A17="Model",LEFT($A17,5)="Markt"),"",IF(AND($C17<=J$3+6,$D17>=J$3),"■","")),"") | K17: =IFERROR(IF(OR($A17="",$A17="Model",LEFT($A17,5)="Markt"),"",IF(AND($C17<=K$3+6,$D17>=K$3),"■","")),"") | L17: =IFERROR(IF(OR($A17="",$A17="Model",LEFT($A17,5)="Markt"),"",IF(AND($C17<=L$3+6,$D17>=L$3),"■","")),"") | ... V17: =IFERROR(IF(OR($A17="",$A17="Model",LEFT($A17,5)="Markt"),"",IF(AND($C17<=V$3+6,$D17>=V$3),"■","")),"") -> ■
A18: Markt: PD | X18: Markt: PD (Survey) | AT18: {=_xlfn.LET(_xlpm.mL,A18,_xlpm.aL,B18,_xlpm.mR,X18,_xlpm.aR,Y18,_xlpm.useR,AND(_xlpm.mR<>"",_xlpm.mR<>"Model",LEFT(_xlpm.mR,6)<>"Markt:"),_xlpm.m,IF(_xlpm.useR,_xlpm.mR,_xlpm.mL),_xlpm.a,IF(_xlpm.useR,_xlpm.aR,_xlpm.aL),_xlpm.rng,IF(_xlpm.useR,X$1:X18,A$1:A18),IF(OR(_xlpm.m="",_xlpm.m="Model",LEFT(_xlpm.m,6)="Markt:"),"",_xlfn.LET(_xlpm.mkt,LOOKUP(2,1/(LEFT(_xlpm.rng,6)="Markt:"),_xlpm.rng),_xlpm.mktNameRaw,TRIM(MID(_xlpm.mkt,FIND(":",_xlpm.mkt)+1,99)),_xlpm.mktName,TRIM(SUBSTITUTE(_xlpm.mktNameRaw,"(Survey)","")),_xlfn.XLOOKUP(_xlpm.mktName&"|"&SUBSTITUTE(_xlpm.m," ","")&"|"&_xlpm.a,tblMassnahmen[Key],tblMassnahmen[Kanal],""))))} | AU18: {=_xlfn.LET(_xlpm.mL,A18,_xlpm.aL,B18,_xlpm.mR,X18,_xlpm.aR,Y18,_xlpm.useR,AND(_xlpm.mR<>"",_xlpm.mR<>"Model",LEFT(_xlpm.mR,6)<>"Markt:"),_xlpm.m,IF(_xlpm.useR,_xlpm.mR,_xlpm.mL),_xlpm.a,IF(_xlpm.useR,_xlpm.aR,_xlpm.aL),_xlpm.rng,IF(_xlpm.useR,X$1:X18,A$1:A18),IF(OR(_xlpm.m="",_xlpm.m="Model",LEFT(_xlpm.m,6)="Markt:"),"",_xlfn.LET(_xlpm.mkt,LOOKUP(2,1/(LEFT(_xlpm.rng,6)="Markt:"),_xlpm.rng),_xlpm.mktNameRaw,TRIM(MID(_xlpm.mkt,FIND(":",_xlpm.mkt)+1,99)),_xlpm.mktName,TRIM(SUBSTITUTE(_xlpm.mktNameRaw,"(Survey)","")),_xlfn.XLOOKUP(_xlpm.mktName&"|"&SUBSTITUTE(_xlpm.m," ","")&"|"&_xlpm.a,tblMassnahmen[Key],tblMassnahmen[Budget],""))))} | AV18: {=_xlfn.LET(_xlpm.mL,A18,_xlpm.aL,B18,_xlpm.mR,X18,_xlpm.aR,Y18,_xlpm.useR,AND(_xlpm.mR<>"",_xlpm.mR<>"Model",LEFT(_xlpm.mR,6)<>"Markt:"),_xlpm.m,IF(_xlpm.useR,_xlpm.mR,_xlpm.mL),_xlpm.a,IF(_xlpm.useR,_xlpm.aR,_xlpm.aL),_xlpm.rng,IF(_xlpm.useR,X$1:X18,A$1:A18),IF(OR(_xlpm.m="",_xlpm.m="Model",LEFT(_xlpm.m,6)="Markt:"),"",_xlfn.LET(_xlpm.mkt,LOOKUP(2,1/(LEFT(_xlpm.rng,6)="Markt:"),_xlpm.rng),_xlpm.mktNameRaw,TRIM(MID(_xlpm.mkt,FIND(":",_xlpm.mkt)+1,99)),_xlpm.mktName,TRIM(SUBSTITUTE(_xlpm.mktNameRaw,"(Survey)","")),_xlfn.XLOOKUP(_xlpm.mktName&"|"&SUBSTITUTE(_xlpm.m," ","")&"|"&_xlpm.a,tblMassnahmen[Key],tblMassnahmen[KPI],""))))}
A19: Model | B19: CTG Measure | C19: Start | D19: Ende | E19: CW18 | F19: CW19 | G19: CW20 | H19: CW21 | I19: CW22 | J19: CW23 | K19: CW24 | L19: CW25 | M19: CW26 | N19: CW27 | O19: CW28 | P19: CW29 | Q19: CW30 | R19: CW31 | S19: CW32 | T19: CW33 | U19: CW34 | V19: CW35 | X19: Model | Y19: Local Measure | Z19: Start | AA19: Ende | AB19: CW18 | AC19: CW19 | AD19: CW20 | AE19: CW21 | AF19: CW22 | AG19: CW23 | AH19: CW24 | AI19: CW25 | AJ19: CW26 | AK19: CW27 | AL19: CW28 | AM19: CW29 | AN19: CW30 | AO19: CW31 | AP19: CW32 | AQ19: CW33 | AR19: CW34 | AS19: CW35 | AT19: Channel | AU19: Budget | AV19: KPI | AW19: Audience
A20: Macan BEV | B20: Google Ads | C20: 46143 | D20: 46264 | E20: =IFERROR(IF(OR($A20="",$A20="Model",LEFT($A20,5)="Markt"),"",IF(AND($C20<=E$3+6,$D20>=E$3),"■","")),"") -> ■ | F20: =IFERROR(IF(OR($A20="",$A20="Model",LEFT($A20,5)="Markt"),"",IF(AND($C20<=F$3+6,$D20>=F$3),"■","")),"") -> ■ | G20: =IFERROR(IF(OR($A20="",$A20="Model",LEFT($A20,5)="Markt"),"",IF(AND($C20<=G$3+6,$D20>=G$3),"■","")),"") -> ■ | H20: =IFERROR(IF(OR($A20="",$A20="Model",LEFT($A20,5)="Markt"),"",IF(AND($C20<=H$3+6,$D20>=H$3),"■","")),"") -> ■ | I20: =IFERROR(IF(OR($A20="",$A20="Model",LEFT($A20,5)="Markt"),"",IF(AND($C20<=I$3+6,$D20>=I$3),"■","")),"") -> ■ | J20: =IFERROR(IF(OR($A20="",$A20="Model",LEFT($A20,5)="Markt"),"",IF(AND($C20<=J$3+6,$D20>=J$3),"■","")),"") -> ■ | K20: =IFERROR(IF(OR($A20="",$A20="Model",LEFT($A20,5)="Markt"),"",IF(AND($C20<=K$3+6,$D20>=K$3),"■","")),"") -> ■ | L20: =IFERROR(IF(OR($A20="",$A20="Model",LEFT($A20,5)="Markt"),"",IF(AND($C20<=L$3+6,$D20>=L$3),"■","")),"") -> ■ | ... V20: =IFERROR(IF(OR($A20="",$A20="Model",LEFT($A20,5)="Markt"),"",IF(AND($C20<=V$3+6,$D20>=V$3),"■","")),"") -> ■ | X20: Macan H2 | Y20: 20056448_20056448_POR_RNG_RNG_DEU_T1_NU_EUR_2025-12-31_2026-12-30_LOCAL-SEANATIONAL2026 | Z20: 46026 | AA20: 46386 | AB20: =IF(AND($Z20<=(AB$3+6),$AA20>=AB$3),"■","") -> ■ | AC20: =IF(AND($Z20<=(AC$3+6),$AA20>=AC$3),"■","") -> ■ | AD20: =IF(AND($Z20<=(AD$3+6),$AA20>=AD$3),"■","") -> ■ | AE20: =IF(AND($Z20<=(AE$3+6),$AA20>=AE$3),"■","") -> ■ | AF20: =IF(AND($Z20<=(AF$3+6),$AA20>=AF$3),"■","") -> ■ | AG20: =IF(AND($Z20<=(AG$3+6),$AA20>=AG$3),"■","") -> ■ | AH20: =IF(AND($Z20<=(AH$3+6),$AA20>=AH$3),"■","") -> ■ | AI20: =IF(AND($Z20<=(AI$3+6),$AA20>=AI$3),"■","") -> ■ | ... AS20: =IF(AND($Z20<=(AS$3+6),$AA20>=AS$3),"■","") -> ■ | AT20: Search | AU20: 182500 | AV20: Dealer contact form submitted (DCFS) | AW20: Keyword Targeting / see above
A21: Macan BEV | B21: META Inventory Ads | C21: 46143 | D21: 46264 | E21: =IFERROR(IF(OR($A21="",$A21="Model",LEFT($A21,5)="Markt"),"",IF(AND($C21<=E$3+6,$D21>=E$3),"■","")),"") -> ■ | F21: =IFERROR(IF(OR($A21="",$A21="Model",LEFT($A21,5)="Markt"),"",IF(AND($C21<=F$3+6,$D21>=F$3),"■","")),"") -> ■ | G21: =IFERROR(IF(OR($A21="",$A21="Model",LEFT($A21,5)="Markt"),"",IF(AND($C21<=G$3+6,$D21>=G$3),"■","")),"") -> ■ | H21: =IFERROR(IF(OR($A21="",$A21="Model",LEFT($A21,5)="Markt"),"",IF(AND($C21<=H$3+6,$D21>=H$3),"■","")),"") -> ■ | I21: =IFERROR(IF(OR($A21="",$A21="Model",LEFT($A21,5)="Markt"),"",IF(AND($C21<=I$3+6,$D21>=I$3),"■","")),"") -> ■ | J21: =IFERROR(IF(OR($A21="",$A21="Model",LEFT($A21,5)="Markt"),"",IF(AND($C21<=J$3+6,$D21>=J$3),"■","")),"") -> ■ | K21: =IFERROR(IF(OR($A21="",$A21="Model",LEFT($A21,5)="Markt"),"",IF(AND($C21<=K$3+6,$D21>=K$3),"■","")),"") -> ■ | L21: =IFERROR(IF(OR($A21="",$A21="Model",LEFT($A21,5)="Markt"),"",IF(AND($C21<=L$3+6,$D21>=L$3),"■","")),"") -> ■ | ... V21: =IFERROR(IF(OR($A21="",$A21="Model",LEFT($A21,5)="Markt"),"",IF(AND($C21<=V$3+6,$D21>=V$3),"■","")),"") -> ■ | X21: Macan H2 | Y21: 20130912_20130912_POR_RNG_RNG_DEU_T1_NU_EUR_2026-02-22_2026-12-30_LOCAL-AOPROGRAMMATICPERFORMANCE2026 | Z21: 46075 | AA21: 46325 | AB21: =IF(AND($Z21<=(AB$3+6),$AA21>=AB$3),"■","") -> ■ | AC21: =IF(AND($Z21<=(AC$3+6),$AA21>=AC$3),"■","") -> ■ | AD21: =IF(AND($Z21<=(AD$3+6),$AA21>=AD$3),"■","") -> ■ | AE21: =IF(AND($Z21<=(AE$3+6),$AA21>=AE$3),"■","") -> ■ | AF21: =IF(AND($Z21<=(AF$3+6),$AA21>=AF$3),"■","") -> ■ | AG21: =IF(AND($Z21<=(AG$3+6),$AA21>=AG$3),"■","") -> ■ | AH21: =IF(AND($Z21<=(AH$3+6),$AA21>=AH$3),"■","") -> ■ | AI21: =IF(AND($Z21<=(AI$3+6),$AA21>=AI$3),"■","") -> ■ | ... AS21: =IF(AND($Z21<=(AS$3+6),$AA21>=AS$3),"■","") -> ■ | AT21: Programmatic | AU21: 190000 | AV21: Dealer contact form submitted (DCFS) | AW21: Complex Audience Setup including Prospecting LAL and Retargeting Audiences / see above
A22: Macan BEV | B22: Paid Social | C22: 46204 | D22: 46264 | E22: =IFERROR(IF(OR($A22="",$A22="Model",LEFT($A22,5)="Markt"),"",IF(AND($C22<=E$3+6,$D22>=E$3),"■","")),"") | F22: =IFERROR(IF(OR($A22="",$A22="Model",LEFT($A22,5)="Markt"),"",IF(AND($C22<=F$3+6,$D22>=F$3),"■","")),"") | G22: =IFERROR(IF(OR($A22="",$A22="Model",LEFT($A22,5)="Markt"),"",IF(AND($C22<=G$3+6,$D22>=G$3),"■","")),"") | H22: =IFERROR(IF(OR($A22="",$A22="Model",LEFT($A22,5)="Markt"),"",IF(AND($C22<=H$3+6,$D22>=H$3),"■","")),"") | I22: =IFERROR(IF(OR($A22="",$A22="Model",LEFT($A22,5)="Markt"),"",IF(AND($C22<=I$3+6,$D22>=I$3),"■","")),"") | J22: =IFERROR(IF(OR($A22="",$A22="Model",LEFT($A22,5)="Markt"),"",IF(AND($C22<=J$3+6,$D22>=J$3),"■","")),"") | K22: =IFERROR(IF(OR($A22="",$A22="Model",LEFT($A22,5)="Markt"),"",IF(AND($C22<=K$3+6,$D22>=K$3),"■","")),"") | L22: =IFERROR(IF(OR($A22="",$A22="Model",LEFT($A22,5)="Markt"),"",IF(AND($C22<=L$3+6,$D22>=L$3),"■","")),"") | ... V22: =IFERROR(IF(OR($A22="",$A22="Model",LEFT($A22,5)="Markt"),"",IF(AND($C22<=V$3+6,$D22>=V$3),"■","")),"") -> ■ | X22: Macan H2 | Y22: 20172604_20172604_POR_MAC_SUV_DEU_T1_NU_EUR_2026-02-20_2026-10-31_LOCAL-MACANDIENSTWAGENPUSH2026 | Z22: 46118 | AA22: 46249 | AB22: =IF(AND($Z22<=(AB$3+6),$AA22>=AB$3),"■","") -> ■ | AC22: =IF(AND($Z22<=(AC$3+6),$AA22>=AC$3),"■","") -> ■ | AD22: =IF(AND($Z22<=(AD$3+6),$AA22>=AD$3),"■","") -> ■ | AE22: =IF(AND($Z22<=(AE$3+6),$AA22>=AE$3),"■","") -> ■ | AF22: =IF(AND($Z22<=(AF$3+6),$AA22>=AF$3),"■","") -> ■ | AG22: =IF(AND($Z22<=(AG$3+6),$AA22>=AG$3),"■","") -> ■ | AH22: =IF(AND($Z22<=(AH$3+6),$AA22>=AH$3),"■","") -> ■ | AI22: =IF(AND($Z22<=(AI$3+6),$AA22>=AI$3),"■","") -> ■ | ... AS22: =IF(AND($Z22<=(AS$3+6),$AA22>=AS$3),"■","") | AT22: Social,Programmatic | AU22: 170000 | AV22: Model page visit,Dealer contact form submitted (DCFS) | AW22: Business People with high income who look for a luxury company car / Retargeting on Macan Interest like Page Visitors or Dealer Contact Starters for a Macan
A23: Cayenne E3 II | B23: Google Ads | C23: 46143 | D23: 46264 | E23: =IFERROR(IF(OR($A23="",$A23="Model",LEFT($A23,5)="Markt"),"",IF(AND($C23<=E$3+6,$D23>=E$3),"■","")),"") -> ■ | F23: =IFERROR(IF(OR($A23="",$A23="Model",LEFT($A23,5)="Markt"),"",IF(AND($C23<=F$3+6,$D23>=F$3),"■","")),"") -> ■ | G23: =IFERROR(IF(OR($A23="",$A23="Model",LEFT($A23,5)="Markt"),"",IF(AND($C23<=G$3+6,$D23>=G$3),"■","")),"") -> ■ | H23: =IFERROR(IF(OR($A23="",$A23="Model",LEFT($A23,5)="Markt"),"",IF(AND($C23<=H$3+6,$D23>=H$3),"■","")),"") -> ■ | I23: =IFERROR(IF(OR($A23="",$A23="Model",LEFT($A23,5)="Markt"),"",IF(AND($C23<=I$3+6,$D23>=I$3),"■","")),"") -> ■ | J23: =IFERROR(IF(OR($A23="",$A23="Model",LEFT($A23,5)="Markt"),"",IF(AND($C23<=J$3+6,$D23>=J$3),"■","")),"") -> ■ | K23: =IFERROR(IF(OR($A23="",$A23="Model",LEFT($A23,5)="Markt"),"",IF(AND($C23<=K$3+6,$D23>=K$3),"■","")),"") -> ■ | L23: =IFERROR(IF(OR($A23="",$A23="Model",LEFT($A23,5)="Markt"),"",IF(AND($C23<=L$3+6,$D23>=L$3),"■","")),"") -> ■ | ... V23: =IFERROR(IF(OR($A23="",$A23="Model",LEFT($A23,5)="Markt"),"",IF(AND($C23<=V$3+6,$D23>=V$3),"■","")),"") -> ■ | X23: Cayenne E3 II | Y23: 20056448_20056448_POR_RNG_RNG_DEU_T1_NU_EUR_2025-12-31_2026-12-30_LOCAL-SEANATIONAL2026 | Z23: 46026 | AA23: 46386 | AB23: =IF(AND($Z23<=(AB$3+6),$AA23>=AB$3),"■","") -> ■ | AC23: =IF(AND($Z23<=(AC$3+6),$AA23>=AC$3),"■","") -> ■ | AD23: =IF(AND($Z23<=(AD$3+6),$AA23>=AD$3),"■","") -> ■ | AE23: =IF(AND($Z23<=(AE$3+6),$AA23>=AE$3),"■","") -> ■ | AF23: =IF(AND($Z23<=(AF$3+6),$AA23>=AF$3),"■","") -> ■ | AG23: =IF(AND($Z23<=(AG$3+6),$AA23>=AG$3),"■","") -> ■ | AH23: =IF(AND($Z23<=(AH$3+6),$AA23>=AH$3),"■","") -> ■ | AI23: =IF(AND($Z23<=(AI$3+6),$AA23>=AI$3),"■","") -> ■ | ... AS23: =IF(AND($Z23<=(AS$3+6),$AA23>=AS$3),"■","") -> ■ | AT23: Search | AU23: 182500 | AV23: Dealer contact form submitted (DCFS) | AW23: Keyword Targeting / see above
A24: Cayenne E3 II | B24: META Inventory Ads | C24: 46143 | D24: 46264 | E24: =IFERROR(IF(OR($A24="",$A24="Model",LEFT($A24,5)="Markt"),"",IF(AND($C24<=E$3+6,$D24>=E$3),"■","")),"") -> ■ | F24: =IFERROR(IF(OR($A24="",$A24="Model",LEFT($A24,5)="Markt"),"",IF(AND($C24<=F$3+6,$D24>=F$3),"■","")),"") -> ■ | G24: =IFERROR(IF(OR($A24="",$A24="Model",LEFT($A24,5)="Markt"),"",IF(AND($C24<=G$3+6,$D24>=G$3),"■","")),"") -> ■ | H24: =IFERROR(IF(OR($A24="",$A24="Model",LEFT($A24,5)="Markt"),"",IF(AND($C24<=H$3+6,$D24>=H$3),"■","")),"") -> ■ | I24: =IFERROR(IF(OR($A24="",$A24="Model",LEFT($A24,5)="Markt"),"",IF(AND($C24<=I$3+6,$D24>=I$3),"■","")),"") -> ■ | J24: =IFERROR(IF(OR($A24="",$A24="Model",LEFT($A24,5)="Markt"),"",IF(AND($C24<=J$3+6,$D24>=J$3),"■","")),"") -> ■ | K24: =IFERROR(IF(OR($A24="",$A24="Model",LEFT($A24,5)="Markt"),"",IF(AND($C24<=K$3+6,$D24>=K$3),"■","")),"") -> ■ | L24: =IFERROR(IF(OR($A24="",$A24="Model",LEFT($A24,5)="Markt"),"",IF(AND($C24<=L$3+6,$D24>=L$3),"■","")),"") -> ■ | ... V24: =IFERROR(IF(OR($A24="",$A24="Model",LEFT($A24,5)="Markt"),"",IF(AND($C24<=V$3+6,$D24>=V$3),"■","")),"") -> ■ | X24: Cayenne E3 II | Y24: 20130912_20130912_POR_RNG_RNG_DEU_T1_NU_EUR_2026-02-22_2026-12-30_LOCAL-AOPROGRAMMATICPERFORMANCE2026 | Z24: 46075 | AA24: 46202 | AB24: =IF(AND($Z24<=(AB$3+6),$AA24>=AB$3),"■","") -> ■ | AC24: =IF(AND($Z24<=(AC$3+6),$AA24>=AC$3),"■","") -> ■ | AD24: =IF(AND($Z24<=(AD$3+6),$AA24>=AD$3),"■","") -> ■ | AE24: =IF(AND($Z24<=(AE$3+6),$AA24>=AE$3),"■","") -> ■ | AF24: =IF(AND($Z24<=(AF$3+6),$AA24>=AF$3),"■","") -> ■ | AG24: =IF(AND($Z24<=(AG$3+6),$AA24>=AG$3),"■","") -> ■ | AH24: =IF(AND($Z24<=(AH$3+6),$AA24>=AH$3),"■","") -> ■ | AI24: =IF(AND($Z24<=(AI$3+6),$AA24>=AI$3),"■","") -> ■ | ... AS24: =IF(AND($Z24<=(AS$3+6),$AA24>=AS$3),"■","") | AT24: Programmatic | AU24: 185000 € (HY2 is not yet planned out but a separate budget is allocated for it) | AV24: Dealer contact form submitted (DCFS) | AW24: Complex Audience Setup including Prospecting and LAL and Retargeting Audiences / see above
A25: Cayenne E3 II | B25: Paid Social | C25: 46204 | D25: 46264 | E25: =IFERROR(IF(OR($A25="",$A25="Model",LEFT($A25,5)="Markt"),"",IF(AND($C25<=E$3+6,$D25>=E$3),"■","")),"") | F25: =IFERROR(IF(OR($A25="",$A25="Model",LEFT($A25,5)="Markt"),"",IF(AND($C25<=F$3+6,$D25>=F$3),"■","")),"") | G25: =IFERROR(IF(OR($A25="",$A25="Model",LEFT($A25,5)="Markt"),"",IF(AND($C25<=G$3+6,$D25>=G$3),"■","")),"") | H25: =IFERROR(IF(OR($A25="",$A25="Model",LEFT($A25,5)="Markt"),"",IF(AND($C25<=H$3+6,$D25>=H$3),"■","")),"") | I25: =IFERROR(IF(OR($A25="",$A25="Model",LEFT($A25,5)="Markt"),"",IF(AND($C25<=I$3+6,$D25>=I$3),"■","")),"") | J25: =IFERROR(IF(OR($A25="",$A25="Model",LEFT($A25,5)="Markt"),"",IF(AND($C25<=J$3+6,$D25>=J$3),"■","")),"") | K25: =IFERROR(IF(OR($A25="",$A25="Model",LEFT($A25,5)="Markt"),"",IF(AND($C25<=K$3+6,$D25>=K$3),"■","")),"") | L25: =IFERROR(IF(OR($A25="",$A25="Model",LEFT($A25,5)="Markt"),"",IF(AND($C25<=L$3+6,$D25>=L$3),"■","")),"") | ... V25: =IFERROR(IF(OR($A25="",$A25="Model",LEFT($A25,5)="Markt"),"",IF(AND($C25<=V$3+6,$D25>=V$3),"■","")),"") -> ■ | X25: Cayenne E3 II | Y25: 20205848_20205848_POR_CAY_SUV_DEU_T1_NU_EUR_2025-12-31_2026-12-30_LOCAL-CAYENNEE4CAYENNEFAMILY | Z25: 46159 | AA25: 46200 | AB25: =IF(AND($Z25<=(AB$3+6),$AA25>=AB$3),"■","") | AC25: =IF(AND($Z25<=(AC$3+6),$AA25>=AC$3),"■","") | AD25: =IF(AND($Z25<=(AD$3+6),$AA25>=AD$3),"■","") -> ■ | AE25: =IF(AND($Z25<=(AE$3+6),$AA25>=AE$3),"■","") -> ■ | AF25: =IF(AND($Z25<=(AF$3+6),$AA25>=AF$3),"■","") -> ■ | AG25: =IF(AND($Z25<=(AG$3+6),$AA25>=AG$3),"■","") -> ■ | AH25: =IF(AND($Z25<=(AH$3+6),$AA25>=AH$3),"■","") -> ■ | AI25: =IF(AND($Z25<=(AI$3+6),$AA25>=AI$3),"■","") -> ■ | ... AS25: =IF(AND($Z25<=(AS$3+6),$AA25>=AS$3),"■","") | AT25: Programmatic | AU25: 70000 | AV25: Configuration | AW25: tbd / tbd
A26: Cayenne E4 | B26: Google Ads | C26: 46143 | D26: 46264 | E26: =IFERROR(IF(OR($A26="",$A26="Model",LEFT($A26,5)="Markt"),"",IF(AND($C26<=E$3+6,$D26>=E$3),"■","")),"") -> ■ | F26: =IFERROR(IF(OR($A26="",$A26="Model",LEFT($A26,5)="Markt"),"",IF(AND($C26<=F$3+6,$D26>=F$3),"■","")),"") -> ■ | G26: =IFERROR(IF(OR($A26="",$A26="Model",LEFT($A26,5)="Markt"),"",IF(AND($C26<=G$3+6,$D26>=G$3),"■","")),"") -> ■ | H26: =IFERROR(IF(OR($A26="",$A26="Model",LEFT($A26,5)="Markt"),"",IF(AND($C26<=H$3+6,$D26>=H$3),"■","")),"") -> ■ | I26: =IFERROR(IF(OR($A26="",$A26="Model",LEFT($A26,5)="Markt"),"",IF(AND($C26<=I$3+6,$D26>=I$3),"■","")),"") -> ■ | J26: =IFERROR(IF(OR($A26="",$A26="Model",LEFT($A26,5)="Markt"),"",IF(AND($C26<=J$3+6,$D26>=J$3),"■","")),"") -> ■ | K26: =IFERROR(IF(OR($A26="",$A26="Model",LEFT($A26,5)="Markt"),"",IF(AND($C26<=K$3+6,$D26>=K$3),"■","")),"") -> ■ | L26: =IFERROR(IF(OR($A26="",$A26="Model",LEFT($A26,5)="Markt"),"",IF(AND($C26<=L$3+6,$D26>=L$3),"■","")),"") -> ■ | ... V26: =IFERROR(IF(OR($A26="",$A26="Model",LEFT($A26,5)="Markt"),"",IF(AND($C26<=V$3+6,$D26>=V$3),"■","")),"") -> ■ | X26: Cayenne E4 | Y26: 20056448_20056448_POR_RNG_RNG_DEU_T1_NU_EUR_2025-12-31_2026-12-30_LOCAL-SEANATIONAL2026 | Z26: 46026 | AA26: 46386 | AB26: =IF(AND($Z26<=(AB$3+6),$AA26>=AB$3),"■","") -> ■ | AC26: =IF(AND($Z26<=(AC$3+6),$AA26>=AC$3),"■","") -> ■ | AD26: =IF(AND($Z26<=(AD$3+6),$AA26>=AD$3),"■","") -> ■ | AE26: =IF(AND($Z26<=(AE$3+6),$AA26>=AE$3),"■","") -> ■ | AF26: =IF(AND($Z26<=(AF$3+6),$AA26>=AF$3),"■","") -> ■ | AG26: =IF(AND($Z26<=(AG$3+6),$AA26>=AG$3),"■","") -> ■ | AH26: =IF(AND($Z26<=(AH$3+6),$AA26>=AH$3),"■","") -> ■ | AI26: =IF(AND($Z26<=(AI$3+6),$AA26>=AI$3),"■","") -> ■ | ... AS26: =IF(AND($Z26<=(AS$3+6),$AA26>=AS$3),"■","") -> ■ | AT26: Search | AU26: 146000 | AV26: Dealer contact form submitted (DCFS) | AW26: Keyword Targeting / see above
A27: Cayenne E4 | B27: META Inventory Ads | C27: 46204 | D27: 46264 | E27: =IFERROR(IF(OR($A27="",$A27="Model",LEFT($A27,5)="Markt"),"",IF(AND($C27<=E$3+6,$D27>=E$3),"■","")),"") | F27: =IFERROR(IF(OR($A27="",$A27="Model",LEFT($A27,5)="Markt"),"",IF(AND($C27<=F$3+6,$D27>=F$3),"■","")),"") | G27: =IFERROR(IF(OR($A27="",$A27="Model",LEFT($A27,5)="Markt"),"",IF(AND($C27<=G$3+6,$D27>=G$3),"■","")),"") | H27: =IFERROR(IF(OR($A27="",$A27="Model",LEFT($A27,5)="Markt"),"",IF(AND($C27<=H$3+6,$D27>=H$3),"■","")),"") | I27: =IFERROR(IF(OR($A27="",$A27="Model",LEFT($A27,5)="Markt"),"",IF(AND($C27<=I$3+6,$D27>=I$3),"■","")),"") | J27: =IFERROR(IF(OR($A27="",$A27="Model",LEFT($A27,5)="Markt"),"",IF(AND($C27<=J$3+6,$D27>=J$3),"■","")),"") | K27: =IFERROR(IF(OR($A27="",$A27="Model",LEFT($A27,5)="Markt"),"",IF(AND($C27<=K$3+6,$D27>=K$3),"■","")),"") | L27: =IFERROR(IF(OR($A27="",$A27="Model",LEFT($A27,5)="Markt"),"",IF(AND($C27<=L$3+6,$D27>=L$3),"■","")),"") | ... V27: =IFERROR(IF(OR($A27="",$A27="Model",LEFT($A27,5)="Markt"),"",IF(AND($C27<=V$3+6,$D27>=V$3),"■","")),"") -> ■ | X27: Cayenne E4 | Y27: 20130912_20130912_POR_RNG_RNG_DEU_T1_NU_EUR_2026-02-22_2026-12-30_LOCAL-AOPROGRAMMATICPERFORMANCE2026 | Z27: 46075 | AA27: 46325 | AB27: =IF(AND($Z27<=(AB$3+6),$AA27>=AB$3),"■","") -> ■ | AC27: =IF(AND($Z27<=(AC$3+6),$AA27>=AC$3),"■","") -> ■ | AD27: =IF(AND($Z27<=(AD$3+6),$AA27>=AD$3),"■","") -> ■ | AE27: =IF(AND($Z27<=(AE$3+6),$AA27>=AE$3),"■","") -> ■ | AF27: =IF(AND($Z27<=(AF$3+6),$AA27>=AF$3),"■","") -> ■ | AG27: =IF(AND($Z27<=(AG$3+6),$AA27>=AG$3),"■","") -> ■ | AH27: =IF(AND($Z27<=(AH$3+6),$AA27>=AH$3),"■","") -> ■ | AI27: =IF(AND($Z27<=(AI$3+6),$AA27>=AI$3),"■","") -> ■ | ... AS27: =IF(AND($Z27<=(AS$3+6),$AA27>=AS$3),"■","") -> ■ | AT27: Programmatic | AU27: 190000 | AV27: Dealer contact form submitted (DCFS) | AW27: Complex Audience Setup including Prosecting LAL and Retargeting Audiences / see above
A28: Cayenne E4 | B28: Paid Social | C28: 46204 | D28: 46264 | E28: =IFERROR(IF(OR($A28="",$A28="Model",LEFT($A28,5)="Markt"),"",IF(AND($C28<=E$3+6,$D28>=E$3),"■","")),"") | F28: =IFERROR(IF(OR($A28="",$A28="Model",LEFT($A28,5)="Markt"),"",IF(AND($C28<=F$3+6,$D28>=F$3),"■","")),"") | G28: =IFERROR(IF(OR($A28="",$A28="Model",LEFT($A28,5)="Markt"),"",IF(AND($C28<=G$3+6,$D28>=G$3),"■","")),"") | H28: =IFERROR(IF(OR($A28="",$A28="Model",LEFT($A28,5)="Markt"),"",IF(AND($C28<=H$3+6,$D28>=H$3),"■","")),"") | I28: =IFERROR(IF(OR($A28="",$A28="Model",LEFT($A28,5)="Markt"),"",IF(AND($C28<=I$3+6,$D28>=I$3),"■","")),"") | J28: =IFERROR(IF(OR($A28="",$A28="Model",LEFT($A28,5)="Markt"),"",IF(AND($C28<=J$3+6,$D28>=J$3),"■","")),"") | K28: =IFERROR(IF(OR($A28="",$A28="Model",LEFT($A28,5)="Markt"),"",IF(AND($C28<=K$3+6,$D28>=K$3),"■","")),"") | L28: =IFERROR(IF(OR($A28="",$A28="Model",LEFT($A28,5)="Markt"),"",IF(AND($C28<=L$3+6,$D28>=L$3),"■","")),"") | ... V28: =IFERROR(IF(OR($A28="",$A28="Model",LEFT($A28,5)="Markt"),"",IF(AND($C28<=V$3+6,$D28>=V$3),"■","")),"") -> ■ | X28: Cayenne E4 | Y28: 20205848_20205848_POR_CAY_SUV_DEU_T1_NU_EUR_2025-12-31_2026-12-30_LOCAL-CAYENNEE4CAYENNEFAMILY | Z28: 46159 | AA28: 46200 | AB28: =IF(AND($Z28<=(AB$3+6),$AA28>=AB$3),"■","") | AC28: =IF(AND($Z28<=(AC$3+6),$AA28>=AC$3),"■","") | AD28: =IF(AND($Z28<=(AD$3+6),$AA28>=AD$3),"■","") -> ■ | AE28: =IF(AND($Z28<=(AE$3+6),$AA28>=AE$3),"■","") -> ■ | AF28: =IF(AND($Z28<=(AF$3+6),$AA28>=AF$3),"■","") -> ■ | AG28: =IF(AND($Z28<=(AG$3+6),$AA28>=AG$3),"■","") -> ■ | AH28: =IF(AND($Z28<=(AH$3+6),$AA28>=AH$3),"■","") -> ■ | AI28: =IF(AND($Z28<=(AI$3+6),$AA28>=AI$3),"■","") -> ■ | ... AS28: =IF(AND($Z28<=(AS$3+6),$AA28>=AS$3),"■","") | AT28: Programmatic | AU28: 70000 | AV28: Configuration | AW28: tbd / tbd
A29: Markt: PKO | X29: Markt: PKO (Survey)
A30: Model | B30: CTG Measure | C30: Start | D30: Ende | E30: CW18 | F30: CW19 | G30: CW20 | H30: CW21 | I30: CW22 | J30: CW23 | K30: CW24 | L30: CW25 | M30: CW26 | N30: CW27 | O30: CW28 | P30: CW29 | Q30: CW30 | R30: CW31 | S30: CW32 | T30: CW33 | U30: CW34 | V30: CW35 | X30: Model | Y30: Local Measure | Z30: Start | AA30: Ende | AB30: CW18 | AC30: CW19 | AD30: CW20 | AE30: CW21 | AF30: CW22 | AG30: CW23 | AH30: CW24 | AI30: CW25 | AJ30: CW26 | AK30: CW27 | AL30: CW28 | AM30: CW29 | AN30: CW30 | AO30: CW31 | AP30: CW32 | AQ30: CW33 | AR30: CW34 | AS30: CW35 | AT30: Channel | AU30: Budget | AV30: KPI | AW30: Audience
A31: Macan BEV | B31: Google Ads | C31: 46143 | D31: 46264 | E31: =IFERROR(IF(OR($A31="",$A31="Model",LEFT($A31,5)="Markt"),"",IF(AND($C31<=E$3+6,$D31>=E$3),"■","")),"") -> ■ | F31: =IFERROR(IF(OR($A31="",$A31="Model",LEFT($A31,5)="Markt"),"",IF(AND($C31<=F$3+6,$D31>=F$3),"■","")),"") -> ■ | G31: =IFERROR(IF(OR($A31="",$A31="Model",LEFT($A31,5)="Markt"),"",IF(AND($C31<=G$3+6,$D31>=G$3),"■","")),"") -> ■ | H31: =IFERROR(IF(OR($A31="",$A31="Model",LEFT($A31,5)="Markt"),"",IF(AND($C31<=H$3+6,$D31>=H$3),"■","")),"") -> ■ | I31: =IFERROR(IF(OR($A31="",$A31="Model",LEFT($A31,5)="Markt"),"",IF(AND($C31<=I$3+6,$D31>=I$3),"■","")),"") -> ■ | J31: =IFERROR(IF(OR($A31="",$A31="Model",LEFT($A31,5)="Markt"),"",IF(AND($C31<=J$3+6,$D31>=J$3),"■","")),"") -> ■ | K31: =IFERROR(IF(OR($A31="",$A31="Model",LEFT($A31,5)="Markt"),"",IF(AND($C31<=K$3+6,$D31>=K$3),"■","")),"") -> ■ | L31: =IFERROR(IF(OR($A31="",$A31="Model",LEFT($A31,5)="Markt"),"",IF(AND($C31<=L$3+6,$D31>=L$3),"■","")),"") -> ■ | ... V31: =IFERROR(IF(OR($A31="",$A31="Model",LEFT($A31,5)="Markt"),"",IF(AND($C31<=V$3+6,$D31>=V$3),"■","")),"") -> ■ | X31: Macan H2 | Y31: H2 GTS | Z31: 46165.917 | AA31: 46202.917 | AB31: =IF(AND($Z31<=(AB$3+6),$AA31>=AB$3),"■","") | AC31: =IF(AND($Z31<=(AC$3+6),$AA31>=AC$3),"■","") | AD31: =IF(AND($Z31<=(AD$3+6),$AA31>=AD$3),"■","") | AE31: =IF(AND($Z31<=(AE$3+6),$AA31>=AE$3),"■","") -> ■ | AF31: =IF(AND($Z31<=(AF$3+6),$AA31>=AF$3),"■","") -> ■ | AG31: =IF(AND($Z31<=(AG$3+6),$AA31>=AG$3),"■","") -> ■ | AH31: =IF(AND($Z31<=(AH$3+6),$AA31>=AH$3),"■","") -> ■ | AI31: =IF(AND($Z31<=(AI$3+6),$AA31>=AI$3),"■","") -> ■ | ... AS31: =IF(AND($Z31<=(AS$3+6),$AA31>=AS$3),"■","") | AT31: Social,Search,Programmatic,Other Online Channel | AU31: 350,000,000KRW | AV31: Configuration,Dealer contact form submitted (DCFS) | AW31: Existing Buyers / All Strategic Target Groups
A32: Macan BEV | B32: Google Inventory Ads | C32: 46143 | D32: 46264 | E32: =IFERROR(IF(OR($A32="",$A32="Model",LEFT($A32,5)="Markt"),"",IF(AND($C32<=E$3+6,$D32>=E$3),"■","")),"") -> ■ | F32: =IFERROR(IF(OR($A32="",$A32="Model",LEFT($A32,5)="Markt"),"",IF(AND($C32<=F$3+6,$D32>=F$3),"■","")),"") -> ■ | G32: =IFERROR(IF(OR($A32="",$A32="Model",LEFT($A32,5)="Markt"),"",IF(AND($C32<=G$3+6,$D32>=G$3),"■","")),"") -> ■ | H32: =IFERROR(IF(OR($A32="",$A32="Model",LEFT($A32,5)="Markt"),"",IF(AND($C32<=H$3+6,$D32>=H$3),"■","")),"") -> ■ | I32: =IFERROR(IF(OR($A32="",$A32="Model",LEFT($A32,5)="Markt"),"",IF(AND($C32<=I$3+6,$D32>=I$3),"■","")),"") -> ■ | J32: =IFERROR(IF(OR($A32="",$A32="Model",LEFT($A32,5)="Markt"),"",IF(AND($C32<=J$3+6,$D32>=J$3),"■","")),"") -> ■ | K32: =IFERROR(IF(OR($A32="",$A32="Model",LEFT($A32,5)="Markt"),"",IF(AND($C32<=K$3+6,$D32>=K$3),"■","")),"") -> ■ | L32: =IFERROR(IF(OR($A32="",$A32="Model",LEFT($A32,5)="Markt"),"",IF(AND($C32<=L$3+6,$D32>=L$3),"■","")),"") -> ■ | ... V32: =IFERROR(IF(OR($A32="",$A32="Model",LEFT($A32,5)="Markt"),"",IF(AND($C32<=V$3+6,$D32>=V$3),"■","")),"") -> ■ | X32: Cayenne E4 | Y32: E4 Pre Launch | Z32: 46100.958 | AA32: 46145.917 | AB32: =IF(AND($Z32<=(AB$3+6),$AA32>=AB$3),"■","") -> ■ | AC32: =IF(AND($Z32<=(AC$3+6),$AA32>=AC$3),"■","") | AD32: =IF(AND($Z32<=(AD$3+6),$AA32>=AD$3),"■","") | AE32: =IF(AND($Z32<=(AE$3+6),$AA32>=AE$3),"■","") | AF32: =IF(AND($Z32<=(AF$3+6),$AA32>=AF$3),"■","") | AG32: =IF(AND($Z32<=(AG$3+6),$AA32>=AG$3),"■","") | AH32: =IF(AND($Z32<=(AH$3+6),$AA32>=AH$3),"■","") | AI32: =IF(AND($Z32<=(AI$3+6),$AA32>=AI$3),"■","") | ... AS32: =IF(AND($Z32<=(AS$3+6),$AA32>=AS$3),"■","") | AT32: Social,Search,Programmatic,Other Online Channel | AU32: 1,480,000,000KRW | AV32: Impressions | AW32: Existing Buyers / All strategic target groups
A33: Macan BEV | B33: META Inventory Ads | C33: 46143 | D33: 46264 | E33: =IFERROR(IF(OR($A33="",$A33="Model",LEFT($A33,5)="Markt"),"",IF(AND($C33<=E$3+6,$D33>=E$3),"■","")),"") -> ■ | F33: =IFERROR(IF(OR($A33="",$A33="Model",LEFT($A33,5)="Markt"),"",IF(AND($C33<=F$3+6,$D33>=F$3),"■","")),"") -> ■ | G33: =IFERROR(IF(OR($A33="",$A33="Model",LEFT($A33,5)="Markt"),"",IF(AND($C33<=G$3+6,$D33>=G$3),"■","")),"") -> ■ | H33: =IFERROR(IF(OR($A33="",$A33="Model",LEFT($A33,5)="Markt"),"",IF(AND($C33<=H$3+6,$D33>=H$3),"■","")),"") -> ■ | I33: =IFERROR(IF(OR($A33="",$A33="Model",LEFT($A33,5)="Markt"),"",IF(AND($C33<=I$3+6,$D33>=I$3),"■","")),"") -> ■ | J33: =IFERROR(IF(OR($A33="",$A33="Model",LEFT($A33,5)="Markt"),"",IF(AND($C33<=J$3+6,$D33>=J$3),"■","")),"") -> ■ | K33: =IFERROR(IF(OR($A33="",$A33="Model",LEFT($A33,5)="Markt"),"",IF(AND($C33<=K$3+6,$D33>=K$3),"■","")),"") -> ■ | L33: =IFERROR(IF(OR($A33="",$A33="Model",LEFT($A33,5)="Markt"),"",IF(AND($C33<=L$3+6,$D33>=L$3),"■","")),"") -> ■ | ... V33: =IFERROR(IF(OR($A33="",$A33="Model",LEFT($A33,5)="Markt"),"",IF(AND($C33<=V$3+6,$D33>=V$3),"■","")),"") -> ■ | X33: Cayenne E4 | Y33: E4 Coupe Launch | Z33: 46165.917 | AA33: 46202.917 | AB33: =IF(AND($Z33<=(AB$3+6),$AA33>=AB$3),"■","") | AC33: =IF(AND($Z33<=(AC$3+6),$AA33>=AC$3),"■","") | AD33: =IF(AND($Z33<=(AD$3+6),$AA33>=AD$3),"■","") | AE33: =IF(AND($Z33<=(AE$3+6),$AA33>=AE$3),"■","") -> ■ | AF33: =IF(AND($Z33<=(AF$3+6),$AA33>=AF$3),"■","") -> ■ | AG33: =IF(AND($Z33<=(AG$3+6),$AA33>=AG$3),"■","") -> ■ | AH33: =IF(AND($Z33<=(AH$3+6),$AA33>=AH$3),"■","") -> ■ | AI33: =IF(AND($Z33<=(AI$3+6),$AA33>=AI$3),"■","") -> ■ | ... AS33: =IF(AND($Z33<=(AS$3+6),$AA33>=AS$3),"■","") | AT33: Social,Search,Programmatic,Other Online Channel | AU33: 500,000,000 KRW | AV33: Configuration,Dealer contact form submitted (DCFS) | AW33: Existing Buyers / All Strategic Target Groups
A34: Macan BEV | B34: Paid Social | C34: 46204 | D34: 46264 | E34: =IFERROR(IF(OR($A34="",$A34="Model",LEFT($A34,5)="Markt"),"",IF(AND($C34<=E$3+6,$D34>=E$3),"■","")),"") | F34: =IFERROR(IF(OR($A34="",$A34="Model",LEFT($A34,5)="Markt"),"",IF(AND($C34<=F$3+6,$D34>=F$3),"■","")),"") | G34: =IFERROR(IF(OR($A34="",$A34="Model",LEFT($A34,5)="Markt"),"",IF(AND($C34<=G$3+6,$D34>=G$3),"■","")),"") | H34: =IFERROR(IF(OR($A34="",$A34="Model",LEFT($A34,5)="Markt"),"",IF(AND($C34<=H$3+6,$D34>=H$3),"■","")),"") | I34: =IFERROR(IF(OR($A34="",$A34="Model",LEFT($A34,5)="Markt"),"",IF(AND($C34<=I$3+6,$D34>=I$3),"■","")),"") | J34: =IFERROR(IF(OR($A34="",$A34="Model",LEFT($A34,5)="Markt"),"",IF(AND($C34<=J$3+6,$D34>=J$3),"■","")),"") | K34: =IFERROR(IF(OR($A34="",$A34="Model",LEFT($A34,5)="Markt"),"",IF(AND($C34<=K$3+6,$D34>=K$3),"■","")),"") | L34: =IFERROR(IF(OR($A34="",$A34="Model",LEFT($A34,5)="Markt"),"",IF(AND($C34<=L$3+6,$D34>=L$3),"■","")),"") | ... V34: =IFERROR(IF(OR($A34="",$A34="Model",LEFT($A34,5)="Markt"),"",IF(AND($C34<=V$3+6,$D34>=V$3),"■","")),"") -> ■
A35: Cayenne E3 II | B35: Google Ads | C35: 46143 | D35: 46264 | E35: =IFERROR(IF(OR($A35="",$A35="Model",LEFT($A35,5)="Markt"),"",IF(AND($C35<=E$3+6,$D35>=E$3),"■","")),"") -> ■ | F35: =IFERROR(IF(OR($A35="",$A35="Model",LEFT($A35,5)="Markt"),"",IF(AND($C35<=F$3+6,$D35>=F$3),"■","")),"") -> ■ | G35: =IFERROR(IF(OR($A35="",$A35="Model",LEFT($A35,5)="Markt"),"",IF(AND($C35<=G$3+6,$D35>=G$3),"■","")),"") -> ■ | H35: =IFERROR(IF(OR($A35="",$A35="Model",LEFT($A35,5)="Markt"),"",IF(AND($C35<=H$3+6,$D35>=H$3),"■","")),"") -> ■ | I35: =IFERROR(IF(OR($A35="",$A35="Model",LEFT($A35,5)="Markt"),"",IF(AND($C35<=I$3+6,$D35>=I$3),"■","")),"") -> ■ | J35: =IFERROR(IF(OR($A35="",$A35="Model",LEFT($A35,5)="Markt"),"",IF(AND($C35<=J$3+6,$D35>=J$3),"■","")),"") -> ■ | K35: =IFERROR(IF(OR($A35="",$A35="Model",LEFT($A35,5)="Markt"),"",IF(AND($C35<=K$3+6,$D35>=K$3),"■","")),"") -> ■ | L35: =IFERROR(IF(OR($A35="",$A35="Model",LEFT($A35,5)="Markt"),"",IF(AND($C35<=L$3+6,$D35>=L$3),"■","")),"") -> ■ | ... V35: =IFERROR(IF(OR($A35="",$A35="Model",LEFT($A35,5)="Markt"),"",IF(AND($C35<=V$3+6,$D35>=V$3),"■","")),"") -> ■
A36: Cayenne E3 II | B36: Google Inventory Ads | C36: 46143 | D36: 46264 | E36: =IFERROR(IF(OR($A36="",$A36="Model",LEFT($A36,5)="Markt"),"",IF(AND($C36<=E$3+6,$D36>=E$3),"■","")),"") -> ■ | F36: =IFERROR(IF(OR($A36="",$A36="Model",LEFT($A36,5)="Markt"),"",IF(AND($C36<=F$3+6,$D36>=F$3),"■","")),"") -> ■ | G36: =IFERROR(IF(OR($A36="",$A36="Model",LEFT($A36,5)="Markt"),"",IF(AND($C36<=G$3+6,$D36>=G$3),"■","")),"") -> ■ | H36: =IFERROR(IF(OR($A36="",$A36="Model",LEFT($A36,5)="Markt"),"",IF(AND($C36<=H$3+6,$D36>=H$3),"■","")),"") -> ■ | I36: =IFERROR(IF(OR($A36="",$A36="Model",LEFT($A36,5)="Markt"),"",IF(AND($C36<=I$3+6,$D36>=I$3),"■","")),"") -> ■ | J36: =IFERROR(IF(OR($A36="",$A36="Model",LEFT($A36,5)="Markt"),"",IF(AND($C36<=J$3+6,$D36>=J$3),"■","")),"") -> ■ | K36: =IFERROR(IF(OR($A36="",$A36="Model",LEFT($A36,5)="Markt"),"",IF(AND($C36<=K$3+6,$D36>=K$3),"■","")),"") -> ■ | L36: =IFERROR(IF(OR($A36="",$A36="Model",LEFT($A36,5)="Markt"),"",IF(AND($C36<=L$3+6,$D36>=L$3),"■","")),"") -> ■ | ... V36: =IFERROR(IF(OR($A36="",$A36="Model",LEFT($A36,5)="Markt"),"",IF(AND($C36<=V$3+6,$D36>=V$3),"■","")),"") -> ■
A37: Cayenne E3 II | B37: META Inventory Ads | C37: 46143 | D37: 46264 | E37: =IFERROR(IF(OR($A37="",$A37="Model",LEFT($A37,5)="Markt"),"",IF(AND($C37<=E$3+6,$D37>=E$3),"■","")),"") -> ■ | F37: =IFERROR(IF(OR($A37="",$A37="Model",LEFT($A37,5)="Markt"),"",IF(AND($C37<=F$3+6,$D37>=F$3),"■","")),"") -> ■ | G37: =IFERROR(IF(OR($A37="",$A37="Model",LEFT($A37,5)="Markt"),"",IF(AND($C37<=G$3+6,$D37>=G$3),"■","")),"") -> ■ | H37: =IFERROR(IF(OR($A37="",$A37="Model",LEFT($A37,5)="Markt"),"",IF(AND($C37<=H$3+6,$D37>=H$3),"■","")),"") -> ■ | I37: =IFERROR(IF(OR($A37="",$A37="Model",LEFT($A37,5)="Markt"),"",IF(AND($C37<=I$3+6,$D37>=I$3),"■","")),"") -> ■ | J37: =IFERROR(IF(OR($A37="",$A37="Model",LEFT($A37,5)="Markt"),"",IF(AND($C37<=J$3+6,$D37>=J$3),"■","")),"") -> ■ | K37: =IFERROR(IF(OR($A37="",$A37="Model",LEFT($A37,5)="Markt"),"",IF(AND($C37<=K$3+6,$D37>=K$3),"■","")),"") -> ■ | L37: =IFERROR(IF(OR($A37="",$A37="Model",LEFT($A37,5)="Markt"),"",IF(AND($C37<=L$3+6,$D37>=L$3),"■","")),"") -> ■ | ... V37: =IFERROR(IF(OR($A37="",$A37="Model",LEFT($A37,5)="Markt"),"",IF(AND($C37<=V$3+6,$D37>=V$3),"■","")),"") -> ■
A38: Cayenne E3 II | B38: Paid Social | C38: 46204 | D38: 46264 | E38: =IFERROR(IF(OR($A38="",$A38="Model",LEFT($A38,5)="Markt"),"",IF(AND($C38<=E$3+6,$D38>=E$3),"■","")),"") | F38: =IFERROR(IF(OR($A38="",$A38="Model",LEFT($A38,5)="Markt"),"",IF(AND($C38<=F$3+6,$D38>=F$3),"■","")),"") | G38: =IFERROR(IF(OR($A38="",$A38="Model",LEFT($A38,5)="Markt"),"",IF(AND($C38<=G$3+6,$D38>=G$3),"■","")),"") | H38: =IFERROR(IF(OR($A38="",$A38="Model",LEFT($A38,5)="Markt"),"",IF(AND($C38<=H$3+6,$D38>=H$3),"■","")),"") | I38: =IFERROR(IF(OR($A38="",$A38="Model",LEFT($A38,5)="Markt"),"",IF(AND($C38<=I$3+6,$D38>=I$3),"■","")),"") | J38: =IFERROR(IF(OR($A38="",$A38="Model",LEFT($A38,5)="Markt"),"",IF(AND($C38<=J$3+6,$D38>=J$3),"■","")),"") | K38: =IFERROR(IF(OR($A38="",$A38="Model",LEFT($A38,5)="Markt"),"",IF(AND($C38<=K$3+6,$D38>=K$3),"■","")),"") | L38: =IFERROR(IF(OR($A38="",$A38="Model",LEFT($A38,5)="Markt"),"",IF(AND($C38<=L$3+6,$D38>=L$3),"■","")),"") | ... V38: =IFERROR(IF(OR($A38="",$A38="Model",LEFT($A38,5)="Markt"),"",IF(AND($C38<=V$3+6,$D38>=V$3),"■","")),"") -> ■
A39: Cayenne E4 | B39: Google Ads | C39: 46143 | D39: 46264 | E39: =IFERROR(IF(OR($A39="",$A39="Model",LEFT($A39,5)="Markt"),"",IF(AND($C39<=E$3+6,$D39>=E$3),"■","")),"") -> ■ | F39: =IFERROR(IF(OR($A39="",$A39="Model",LEFT($A39,5)="Markt"),"",IF(AND($C39<=F$3+6,$D39>=F$3),"■","")),"") -> ■ | G39: =IFERROR(IF(OR($A39="",$A39="Model",LEFT($A39,5)="Markt"),"",IF(AND($C39<=G$3+6,$D39>=G$3),"■","")),"") -> ■ | H39: =IFERROR(IF(OR($A39="",$A39="Model",LEFT($A39,5)="Markt"),"",IF(AND($C39<=H$3+6,$D39>=H$3),"■","")),"") -> ■ | I39: =IFERROR(IF(OR($A39="",$A39="Model",LEFT($A39,5)="Markt"),"",IF(AND($C39<=I$3+6,$D39>=I$3),"■","")),"") -> ■ | J39: =IFERROR(IF(OR($A39="",$A39="Model",LEFT($A39,5)="Markt"),"",IF(AND($C39<=J$3+6,$D39>=J$3),"■","")),"") -> ■ | K39: =IFERROR(IF(OR($A39="",$A39="Model",LEFT($A39,5)="Markt"),"",IF(AND($C39<=K$3+6,$D39>=K$3),"■","")),"") -> ■ | L39: =IFERROR(IF(OR($A39="",$A39="Model",LEFT($A39,5)="Markt"),"",IF(AND($C39<=L$3+6,$D39>=L$3),"■","")),"") -> ■ | ... V39: =IFERROR(IF(OR($A39="",$A39="Model",LEFT($A39,5)="Markt"),"",IF(AND($C39<=V$3+6,$D39>=V$3),"■","")),"") -> ■
A40: Cayenne E4 | B40: Google Inventory Ads | C40: 46204 | D40: 46264 | E40: =IFERROR(IF(OR($A40="",$A40="Model",LEFT($A40,5)="Markt"),"",IF(AND($C40<=E$3+6,$D40>=E$3),"■","")),"") | F40: =IFERROR(IF(OR($A40="",$A40="Model",LEFT($A40,5)="Markt"),"",IF(AND($C40<=F$3+6,$D40>=F$3),"■","")),"") | G40: =IFERROR(IF(OR($A40="",$A40="Model",LEFT($A40,5)="Markt"),"",IF(AND($C40<=G$3+6,$D40>=G$3),"■","")),"") | H40: =IFERROR(IF(OR($A40="",$A40="Model",LEFT($A40,5)="Markt"),"",IF(AND($C40<=H$3+6,$D40>=H$3),"■","")),"") | I40: =IFERROR(IF(OR($A40="",$A40="Model",LEFT($A40,5)="Markt"),"",IF(AND($C40<=I$3+6,$D40>=I$3),"■","")),"") | J40: =IFERROR(IF(OR($A40="",$A40="Model",LEFT($A40,5)="Markt"),"",IF(AND($C40<=J$3+6,$D40>=J$3),"■","")),"") | K40: =IFERROR(IF(OR($A40="",$A40="Model",LEFT($A40,5)="Markt"),"",IF(AND($C40<=K$3+6,$D40>=K$3),"■","")),"") | L40: =IFERROR(IF(OR($A40="",$A40="Model",LEFT($A40,5)="Markt"),"",IF(AND($C40<=L$3+6,$D40>=L$3),"■","")),"") | ... V40: =IFERROR(IF(OR($A40="",$A40="Model",LEFT($A40,5)="Markt"),"",IF(AND($C40<=V$3+6,$D40>=V$3),"■","")),"") -> ■
A41: Cayenne E4 | B41: META Inventory Ads | C41: 46204 | D41: 46264 | E41: =IFERROR(IF(OR($A41="",$A41="Model",LEFT($A41,5)="Markt"),"",IF(AND($C41<=E$3+6,$D41>=E$3),"■","")),"") | F41: =IFERROR(IF(OR($A41="",$A41="Model",LEFT($A41,5)="Markt"),"",IF(AND($C41<=F$3+6,$D41>=F$3),"■","")),"") | G41: =IFERROR(IF(OR($A41="",$A41="Model",LEFT($A41,5)="Markt"),"",IF(AND($C41<=G$3+6,$D41>=G$3),"■","")),"") | H41: =IFERROR(IF(OR($A41="",$A41="Model",LEFT($A41,5)="Markt"),"",IF(AND($C41<=H$3+6,$D41>=H$3),"■","")),"") | I41: =IFERROR(IF(OR($A41="",$A41="Model",LEFT($A41,5)="Markt"),"",IF(AND($C41<=I$3+6,$D41>=I$3),"■","")),"") | J41: =IFERROR(IF(OR($A41="",$A41="Model",LEFT($A41,5)="Markt"),"",IF(AND($C41<=J$3+6,$D41>=J$3),"■","")),"") | K41: =IFERROR(IF(OR($A41="",$A41="Model",LEFT($A41,5)="Markt"),"",IF(AND($C41<=K$3+6,$D41>=K$3),"■","")),"") | L41: =IFERROR(IF(OR($A41="",$A41="Model",LEFT($A41,5)="Markt"),"",IF(AND($C41<=L$3+6,$D41>=L$3),"■","")),"") | ... V41: =IFERROR(IF(OR($A41="",$A41="Model",LEFT($A41,5)="Markt"),"",IF(AND($C41<=V$3+6,$D41>=V$3),"■","")),"") -> ■
A42: Cayenne E4 | B42: Paid Social | C42: 46204 | D42: 46264 | E42: =IFERROR(IF(OR($A42="",$A42="Model",LEFT($A42,5)="Markt"),"",IF(AND($C42<=E$3+6,$D42>=E$3),"■","")),"") | F42: =IFERROR(IF(OR($A42="",$A42="Model",LEFT($A42,5)="Markt"),"",IF(AND($C42<=F$3+6,$D42>=F$3),"■","")),"") | G42: =IFERROR(IF(OR($A42="",$A42="Model",LEFT($A42,5)="Markt"),"",IF(AND($C42<=G$3+6,$D42>=G$3),"■","")),"") | H42: =IFERROR(IF(OR($A42="",$A42="Model",LEFT($A42,5)="Markt"),"",IF(AND($C42<=H$3+6,$D42>=H$3),"■","")),"") | I42: =IFERROR(IF(OR($A42="",$A42="Model",LEFT($A42,5)="Markt"),"",IF(AND($C42<=I$3+6,$D42>=I$3),"■","")),"") | J42: =IFERROR(IF(OR($A42="",$A42="Model",LEFT($A42,5)="Markt"),"",IF(AND($C42<=J$3+6,$D42>=J$3),"■","")),"") | K42: =IFERROR(IF(OR($A42="",$A42="Model",LEFT($A42,5)="Markt"),"",IF(AND($C42<=K$3+6,$D42>=K$3),"■","")),"") | L42: =IFERROR(IF(OR($A42="",$A42="Model",LEFT($A42,5)="Markt"),"",IF(AND($C42<=L$3+6,$D42>=L$3),"■","")),"") | ... V42: =IFERROR(IF(OR($A42="",$A42="Model",LEFT($A42,5)="Markt"),"",IF(AND($C42<=V$3+6,$D42>=V$3),"■","")),"") -> ■
A43: Markt: POF | X43: Markt: POF (Survey)
A44: Model | B44: CTG Measure | C44: Start | D44: Ende | E44: CW18 | F44: CW19 | G44: CW20 | H44: CW21 | I44: CW22 | J44: CW23 | K44: CW24 | L44: CW25 | M44: CW26 | N44: CW27 | O44: CW28 | P44: CW29 | Q44: CW30 | R44: CW31 | S44: CW32 | T44: CW33 | U44: CW34 | V44: CW35 | X44: Model | Y44: Local Measure | Z44: Start | AA44: Ende | AB44: CW18 | AC44: CW19 | AD44: CW20 | AE44: CW21 | AF44: CW22 | AG44: CW23 | AH44: CW24 | AI44: CW25 | AJ44: CW26 | AK44: CW27 | AL44: CW28 | AM44: CW29 | AN44: CW30 | AO44: CW31 | AP44: CW32 | AQ44: CW33 | AR44: CW34 | AS44: CW35 | AT44: Channel | AU44: Budget | AV44: KPI | AW44: Audience
A45: Macan BEV | B45: Google Ads | C45: 46143 | D45: 46264 | E45: =IFERROR(IF(OR($A45="",$A45="Model",LEFT($A45,5)="Markt"),"",IF(AND($C45<=E$3+6,$D45>=E$3),"■","")),"") -> ■ | F45: =IFERROR(IF(OR($A45="",$A45="Model",LEFT($A45,5)="Markt"),"",IF(AND($C45<=F$3+6,$D45>=F$3),"■","")),"") -> ■ | G45: =IFERROR(IF(OR($A45="",$A45="Model",LEFT($A45,5)="Markt"),"",IF(AND($C45<=G$3+6,$D45>=G$3),"■","")),"") -> ■ | H45: =IFERROR(IF(OR($A45="",$A45="Model",LEFT($A45,5)="Markt"),"",IF(AND($C45<=H$3+6,$D45>=H$3),"■","")),"") -> ■ | I45: =IFERROR(IF(OR($A45="",$A45="Model",LEFT($A45,5)="Markt"),"",IF(AND($C45<=I$3+6,$D45>=I$3),"■","")),"") -> ■ | J45: =IFERROR(IF(OR($A45="",$A45="Model",LEFT($A45,5)="Markt"),"",IF(AND($C45<=J$3+6,$D45>=J$3),"■","")),"") -> ■ | K45: =IFERROR(IF(OR($A45="",$A45="Model",LEFT($A45,5)="Markt"),"",IF(AND($C45<=K$3+6,$D45>=K$3),"■","")),"") -> ■ | L45: =IFERROR(IF(OR($A45="",$A45="Model",LEFT($A45,5)="Markt"),"",IF(AND($C45<=L$3+6,$D45>=L$3),"■","")),"") -> ■ | ... V45: =IFERROR(IF(OR($A45="",$A45="Model",LEFT($A45,5)="Markt"),"",IF(AND($C45<=V$3+6,$D45>=V$3),"■","")),"") -> ■ | X45: Macan H2 | Y45: Always on META (traffic and lead ad) | Z45: 46022 | AA45: 46386 | AB45: =IF(AND($Z45<=(AB$3+6),$AA45>=AB$3),"■","") -> ■ | AC45: =IF(AND($Z45<=(AC$3+6),$AA45>=AC$3),"■","") -> ■ | AD45: =IF(AND($Z45<=(AD$3+6),$AA45>=AD$3),"■","") -> ■ | AE45: =IF(AND($Z45<=(AE$3+6),$AA45>=AE$3),"■","") -> ■ | AF45: =IF(AND($Z45<=(AF$3+6),$AA45>=AF$3),"■","") -> ■ | AG45: =IF(AND($Z45<=(AG$3+6),$AA45>=AG$3),"■","") -> ■ | AH45: =IF(AND($Z45<=(AH$3+6),$AA45>=AH$3),"■","") -> ■ | AI45: =IF(AND($Z45<=(AI$3+6),$AA45>=AI$3),"■","") -> ■ | ... AS45: =IF(AND($Z45<=(AS$3+6),$AA45>=AS$3),"■","") -> ■ | AT45: Social | AU45: 40K€ | AV45: Impressions,Cost per Million (CPM),Click Through Rate (CTR),Model page visit,Configuration,Dealer contact form submitted (DCFS),Cost per Lead (CPL) | AW45: LAL CAP database / RTG other campaigns and PCOM
A46: Macan BEV | B46: Google Inventory Ads | C46: 46143 | D46: 46264 | E46: =IFERROR(IF(OR($A46="",$A46="Model",LEFT($A46,5)="Markt"),"",IF(AND($C46<=E$3+6,$D46>=E$3),"■","")),"") -> ■ | F46: =IFERROR(IF(OR($A46="",$A46="Model",LEFT($A46,5)="Markt"),"",IF(AND($C46<=F$3+6,$D46>=F$3),"■","")),"") -> ■ | G46: =IFERROR(IF(OR($A46="",$A46="Model",LEFT($A46,5)="Markt"),"",IF(AND($C46<=G$3+6,$D46>=G$3),"■","")),"") -> ■ | H46: =IFERROR(IF(OR($A46="",$A46="Model",LEFT($A46,5)="Markt"),"",IF(AND($C46<=H$3+6,$D46>=H$3),"■","")),"") -> ■ | I46: =IFERROR(IF(OR($A46="",$A46="Model",LEFT($A46,5)="Markt"),"",IF(AND($C46<=I$3+6,$D46>=I$3),"■","")),"") -> ■ | J46: =IFERROR(IF(OR($A46="",$A46="Model",LEFT($A46,5)="Markt"),"",IF(AND($C46<=J$3+6,$D46>=J$3),"■","")),"") -> ■ | K46: =IFERROR(IF(OR($A46="",$A46="Model",LEFT($A46,5)="Markt"),"",IF(AND($C46<=K$3+6,$D46>=K$3),"■","")),"") -> ■ | L46: =IFERROR(IF(OR($A46="",$A46="Model",LEFT($A46,5)="Markt"),"",IF(AND($C46<=L$3+6,$D46>=L$3),"■","")),"") -> ■ | ... V46: =IFERROR(IF(OR($A46="",$A46="Model",LEFT($A46,5)="Markt"),"",IF(AND($C46<=V$3+6,$D46>=V$3),"■","")),"") -> ■ | X46: Macan H2 | Y46: Always-on SEA | Z46: 46022 | AA46: 46386 | AB46: =IF(AND($Z46<=(AB$3+6),$AA46>=AB$3),"■","") -> ■ | AC46: =IF(AND($Z46<=(AC$3+6),$AA46>=AC$3),"■","") -> ■ | AD46: =IF(AND($Z46<=(AD$3+6),$AA46>=AD$3),"■","") -> ■ | AE46: =IF(AND($Z46<=(AE$3+6),$AA46>=AE$3),"■","") -> ■ | AF46: =IF(AND($Z46<=(AF$3+6),$AA46>=AF$3),"■","") -> ■ | AG46: =IF(AND($Z46<=(AG$3+6),$AA46>=AG$3),"■","") -> ■ | AH46: =IF(AND($Z46<=(AH$3+6),$AA46>=AH$3),"■","") -> ■ | AI46: =IF(AND($Z46<=(AI$3+6),$AA46>=AI$3),"■","") -> ■ | ... AS46: =IF(AND($Z46<=(AS$3+6),$AA46>=AS$3),"■","") -> ■ | AT46: Search | AU46: 81K€ | AV46: Model page visit,Configuration,Dealer contact form submitted (DCFS),Cost per Lead (CPL) | AW46: NA / NA
A47: Macan BEV | B47: META Inventory Ads | C47: 46143 | D47: 46264 | E47: =IFERROR(IF(OR($A47="",$A47="Model",LEFT($A47,5)="Markt"),"",IF(AND($C47<=E$3+6,$D47>=E$3),"■","")),"") -> ■ | F47: =IFERROR(IF(OR($A47="",$A47="Model",LEFT($A47,5)="Markt"),"",IF(AND($C47<=F$3+6,$D47>=F$3),"■","")),"") -> ■ | G47: =IFERROR(IF(OR($A47="",$A47="Model",LEFT($A47,5)="Markt"),"",IF(AND($C47<=G$3+6,$D47>=G$3),"■","")),"") -> ■ | H47: =IFERROR(IF(OR($A47="",$A47="Model",LEFT($A47,5)="Markt"),"",IF(AND($C47<=H$3+6,$D47>=H$3),"■","")),"") -> ■ | I47: =IFERROR(IF(OR($A47="",$A47="Model",LEFT($A47,5)="Markt"),"",IF(AND($C47<=I$3+6,$D47>=I$3),"■","")),"") -> ■ | J47: =IFERROR(IF(OR($A47="",$A47="Model",LEFT($A47,5)="Markt"),"",IF(AND($C47<=J$3+6,$D47>=J$3),"■","")),"") -> ■ | K47: =IFERROR(IF(OR($A47="",$A47="Model",LEFT($A47,5)="Markt"),"",IF(AND($C47<=K$3+6,$D47>=K$3),"■","")),"") -> ■ | L47: =IFERROR(IF(OR($A47="",$A47="Model",LEFT($A47,5)="Markt"),"",IF(AND($C47<=L$3+6,$D47>=L$3),"■","")),"") -> ■ | ... V47: =IFERROR(IF(OR($A47="",$A47="Model",LEFT($A47,5)="Markt"),"",IF(AND($C47<=V$3+6,$D47>=V$3),"■","")),"") -> ■ | X47: Cayenne E3 II | Y47: Always-on META (trafic and lead ad) | Z47: 46022 | AA47: 46386 | AB47: =IF(AND($Z47<=(AB$3+6),$AA47>=AB$3),"■","") -> ■ | AC47: =IF(AND($Z47<=(AC$3+6),$AA47>=AC$3),"■","") -> ■ | AD47: =IF(AND($Z47<=(AD$3+6),$AA47>=AD$3),"■","") -> ■ | AE47: =IF(AND($Z47<=(AE$3+6),$AA47>=AE$3),"■","") -> ■ | AF47: =IF(AND($Z47<=(AF$3+6),$AA47>=AF$3),"■","") -> ■ | AG47: =IF(AND($Z47<=(AG$3+6),$AA47>=AG$3),"■","") -> ■ | AH47: =IF(AND($Z47<=(AH$3+6),$AA47>=AH$3),"■","") -> ■ | AI47: =IF(AND($Z47<=(AI$3+6),$AA47>=AI$3),"■","") -> ■ | ... AS47: =IF(AND($Z47<=(AS$3+6),$AA47>=AS$3),"■","") -> ■ | AT47: Social | AU47: 40€ (same campaign (trafic and lead ad) for E3 II and E4 - we let the algorythm decide which creative asset to push depending on the audience) | AV47: Dealer contact form submitted (DCFS),Cost Per Lead (CPL) | AW47: LAL CAP database / RTG other campaigns and PCOM
A48: Macan BEV | B48: Paid Social | C48: 46204 | D48: 46264 | E48: =IFERROR(IF(OR($A48="",$A48="Model",LEFT($A48,5)="Markt"),"",IF(AND($C48<=E$3+6,$D48>=E$3),"■","")),"") | F48: =IFERROR(IF(OR($A48="",$A48="Model",LEFT($A48,5)="Markt"),"",IF(AND($C48<=F$3+6,$D48>=F$3),"■","")),"") | G48: =IFERROR(IF(OR($A48="",$A48="Model",LEFT($A48,5)="Markt"),"",IF(AND($C48<=G$3+6,$D48>=G$3),"■","")),"") | H48: =IFERROR(IF(OR($A48="",$A48="Model",LEFT($A48,5)="Markt"),"",IF(AND($C48<=H$3+6,$D48>=H$3),"■","")),"") | I48: =IFERROR(IF(OR($A48="",$A48="Model",LEFT($A48,5)="Markt"),"",IF(AND($C48<=I$3+6,$D48>=I$3),"■","")),"") | J48: =IFERROR(IF(OR($A48="",$A48="Model",LEFT($A48,5)="Markt"),"",IF(AND($C48<=J$3+6,$D48>=J$3),"■","")),"") | K48: =IFERROR(IF(OR($A48="",$A48="Model",LEFT($A48,5)="Markt"),"",IF(AND($C48<=K$3+6,$D48>=K$3),"■","")),"") | L48: =IFERROR(IF(OR($A48="",$A48="Model",LEFT($A48,5)="Markt"),"",IF(AND($C48<=L$3+6,$D48>=L$3),"■","")),"") | ... V48: =IFERROR(IF(OR($A48="",$A48="Model",LEFT($A48,5)="Markt"),"",IF(AND($C48<=V$3+6,$D48>=V$3),"■","")),"") -> ■ | X48: Cayenne E3 II | Y48: Always-on SEA | Z48: 46022 | AA48: 46386 | AB48: =IF(AND($Z48<=(AB$3+6),$AA48>=AB$3),"■","") -> ■ | AC48: =IF(AND($Z48<=(AC$3+6),$AA48>=AC$3),"■","") -> ■ | AD48: =IF(AND($Z48<=(AD$3+6),$AA48>=AD$3),"■","") -> ■ | AE48: =IF(AND($Z48<=(AE$3+6),$AA48>=AE$3),"■","") -> ■ | AF48: =IF(AND($Z48<=(AF$3+6),$AA48>=AF$3),"■","") -> ■ | AG48: =IF(AND($Z48<=(AG$3+6),$AA48>=AG$3),"■","") -> ■ | AH48: =IF(AND($Z48<=(AH$3+6),$AA48>=AH$3),"■","") -> ■ | AI48: =IF(AND($Z48<=(AI$3+6),$AA48>=AI$3),"■","") -> ■ | ... AS48: =IF(AND($Z48<=(AS$3+6),$AA48>=AS$3),"■","") -> ■ | AT48: Search | AU48: 40K€ budget for PHEV models (including E3II and Panamera) | AV48: Model page visit,Configuration,Dealer contact form submitted (DCFS),Cost per Lead (CPL) | AW48: NA / NA
A49: Cayenne E3 II | B49: Google Ads | C49: 46143 | D49: 46264 | E49: =IFERROR(IF(OR($A49="",$A49="Model",LEFT($A49,5)="Markt"),"",IF(AND($C49<=E$3+6,$D49>=E$3),"■","")),"") -> ■ | F49: =IFERROR(IF(OR($A49="",$A49="Model",LEFT($A49,5)="Markt"),"",IF(AND($C49<=F$3+6,$D49>=F$3),"■","")),"") -> ■ | G49: =IFERROR(IF(OR($A49="",$A49="Model",LEFT($A49,5)="Markt"),"",IF(AND($C49<=G$3+6,$D49>=G$3),"■","")),"") -> ■ | H49: =IFERROR(IF(OR($A49="",$A49="Model",LEFT($A49,5)="Markt"),"",IF(AND($C49<=H$3+6,$D49>=H$3),"■","")),"") -> ■ | I49: =IFERROR(IF(OR($A49="",$A49="Model",LEFT($A49,5)="Markt"),"",IF(AND($C49<=I$3+6,$D49>=I$3),"■","")),"") -> ■ | J49: =IFERROR(IF(OR($A49="",$A49="Model",LEFT($A49,5)="Markt"),"",IF(AND($C49<=J$3+6,$D49>=J$3),"■","")),"") -> ■ | K49: =IFERROR(IF(OR($A49="",$A49="Model",LEFT($A49,5)="Markt"),"",IF(AND($C49<=K$3+6,$D49>=K$3),"■","")),"") -> ■ | L49: =IFERROR(IF(OR($A49="",$A49="Model",LEFT($A49,5)="Markt"),"",IF(AND($C49<=L$3+6,$D49>=L$3),"■","")),"") -> ■ | ... V49: =IFERROR(IF(OR($A49="",$A49="Model",LEFT($A49,5)="Markt"),"",IF(AND($C49<=V$3+6,$D49>=V$3),"■","")),"") -> ■ | X49: Cayenne E4 | Y49: Always-on META (traffic and lead ad) & SEA | Z49: 46022 | AA49: 46386 | AB49: =IF(AND($Z49<=(AB$3+6),$AA49>=AB$3),"■","") -> ■ | AC49: =IF(AND($Z49<=(AC$3+6),$AA49>=AC$3),"■","") -> ■ | AD49: =IF(AND($Z49<=(AD$3+6),$AA49>=AD$3),"■","") -> ■ | AE49: =IF(AND($Z49<=(AE$3+6),$AA49>=AE$3),"■","") -> ■ | AF49: =IF(AND($Z49<=(AF$3+6),$AA49>=AF$3),"■","") -> ■ | AG49: =IF(AND($Z49<=(AG$3+6),$AA49>=AG$3),"■","") -> ■ | AH49: =IF(AND($Z49<=(AH$3+6),$AA49>=AH$3),"■","") -> ■ | AI49: =IF(AND($Z49<=(AI$3+6),$AA49>=AI$3),"■","") -> ■ | ... AS49: =IF(AND($Z49<=(AS$3+6),$AA49>=AS$3),"■","") -> ■ | AT49: Social,Search | AU49: 45K€ for SEA and 40K€ for Cayenne META campaign trafic and lead ad (common to E3II and E4) | AV49: Impressions,Cost per Million (CPM),Click Through Rate (CTR),Model page visit,Configuration,Dealer contact form submitted (DCFS),Cost per Lead (CPL) | AW49: LAL CAP database / RTG other campaigns and PCOM
A50: Cayenne E3 II | B50: Google Inventory Ads | C50: 46143 | D50: 46264 | E50: =IFERROR(IF(OR($A50="",$A50="Model",LEFT($A50,5)="Markt"),"",IF(AND($C50<=E$3+6,$D50>=E$3),"■","")),"") -> ■ | F50: =IFERROR(IF(OR($A50="",$A50="Model",LEFT($A50,5)="Markt"),"",IF(AND($C50<=F$3+6,$D50>=F$3),"■","")),"") -> ■ | G50: =IFERROR(IF(OR($A50="",$A50="Model",LEFT($A50,5)="Markt"),"",IF(AND($C50<=G$3+6,$D50>=G$3),"■","")),"") -> ■ | H50: =IFERROR(IF(OR($A50="",$A50="Model",LEFT($A50,5)="Markt"),"",IF(AND($C50<=H$3+6,$D50>=H$3),"■","")),"") -> ■ | I50: =IFERROR(IF(OR($A50="",$A50="Model",LEFT($A50,5)="Markt"),"",IF(AND($C50<=I$3+6,$D50>=I$3),"■","")),"") -> ■ | J50: =IFERROR(IF(OR($A50="",$A50="Model",LEFT($A50,5)="Markt"),"",IF(AND($C50<=J$3+6,$D50>=J$3),"■","")),"") -> ■ | K50: =IFERROR(IF(OR($A50="",$A50="Model",LEFT($A50,5)="Markt"),"",IF(AND($C50<=K$3+6,$D50>=K$3),"■","")),"") -> ■ | L50: =IFERROR(IF(OR($A50="",$A50="Model",LEFT($A50,5)="Markt"),"",IF(AND($C50<=L$3+6,$D50>=L$3),"■","")),"") -> ■ | ... V50: =IFERROR(IF(OR($A50="",$A50="Model",LEFT($A50,5)="Markt"),"",IF(AND($C50<=V$3+6,$D50>=V$3),"■","")),"") -> ■ | X50: Cayenne E4 | Y50: Digital campaign (traffic and lead generation) via programmatic + DOOH | Z50: 46100 | AA50: 46179 | AB50: =IF(AND($Z50<=(AB$3+6),$AA50>=AB$3),"■","") -> ■ | AC50: =IF(AND($Z50<=(AC$3+6),$AA50>=AC$3),"■","") -> ■ | AD50: =IF(AND($Z50<=(AD$3+6),$AA50>=AD$3),"■","") -> ■ | AE50: =IF(AND($Z50<=(AE$3+6),$AA50>=AE$3),"■","") -> ■ | AF50: =IF(AND($Z50<=(AF$3+6),$AA50>=AF$3),"■","") -> ■ | AG50: =IF(AND($Z50<=(AG$3+6),$AA50>=AG$3),"■","") -> ■ | AH50: =IF(AND($Z50<=(AH$3+6),$AA50>=AH$3),"■","") | AI50: =IF(AND($Z50<=(AI$3+6),$AA50>=AI$3),"■","") | ... AS50: =IF(AND($Z50<=(AS$3+6),$AA50>=AS$3),"■","") | AT50: Programmatic,Other Online Channel | AU50: 231K€ | AV50: Impressions,Cost per Million (CPM),Click Through Rate (CTR),Model page visit | AW50: based on interests such as luxury goods travel new tech automotive entrepreneurship / NA
A51: Cayenne E3 II | B51: META Inventory Ads | C51: 46143 | D51: 46264 | E51: =IFERROR(IF(OR($A51="",$A51="Model",LEFT($A51,5)="Markt"),"",IF(AND($C51<=E$3+6,$D51>=E$3),"■","")),"") -> ■ | F51: =IFERROR(IF(OR($A51="",$A51="Model",LEFT($A51,5)="Markt"),"",IF(AND($C51<=F$3+6,$D51>=F$3),"■","")),"") -> ■ | G51: =IFERROR(IF(OR($A51="",$A51="Model",LEFT($A51,5)="Markt"),"",IF(AND($C51<=G$3+6,$D51>=G$3),"■","")),"") -> ■ | H51: =IFERROR(IF(OR($A51="",$A51="Model",LEFT($A51,5)="Markt"),"",IF(AND($C51<=H$3+6,$D51>=H$3),"■","")),"") -> ■ | I51: =IFERROR(IF(OR($A51="",$A51="Model",LEFT($A51,5)="Markt"),"",IF(AND($C51<=I$3+6,$D51>=I$3),"■","")),"") -> ■ | J51: =IFERROR(IF(OR($A51="",$A51="Model",LEFT($A51,5)="Markt"),"",IF(AND($C51<=J$3+6,$D51>=J$3),"■","")),"") -> ■ | K51: =IFERROR(IF(OR($A51="",$A51="Model",LEFT($A51,5)="Markt"),"",IF(AND($C51<=K$3+6,$D51>=K$3),"■","")),"") -> ■ | L51: =IFERROR(IF(OR($A51="",$A51="Model",LEFT($A51,5)="Markt"),"",IF(AND($C51<=L$3+6,$D51>=L$3),"■","")),"") -> ■ | ... V51: =IFERROR(IF(OR($A51="",$A51="Model",LEFT($A51,5)="Markt"),"",IF(AND($C51<=V$3+6,$D51>=V$3),"■","")),"") -> ■ | X51: Cayenne E4 | Y51: Press campaign | Z51: 46081 | AA51: 46202 | AB51: =IF(AND($Z51<=(AB$3+6),$AA51>=AB$3),"■","") -> ■ | AC51: =IF(AND($Z51<=(AC$3+6),$AA51>=AC$3),"■","") -> ■ | AD51: =IF(AND($Z51<=(AD$3+6),$AA51>=AD$3),"■","") -> ■ | AE51: =IF(AND($Z51<=(AE$3+6),$AA51>=AE$3),"■","") -> ■ | AF51: =IF(AND($Z51<=(AF$3+6),$AA51>=AF$3),"■","") -> ■ | AG51: =IF(AND($Z51<=(AG$3+6),$AA51>=AG$3),"■","") -> ■ | AH51: =IF(AND($Z51<=(AH$3+6),$AA51>=AH$3),"■","") -> ■ | AI51: =IF(AND($Z51<=(AI$3+6),$AA51>=AI$3),"■","") -> ■ | ... AS51: =IF(AND($Z51<=(AS$3+6),$AA51>=AS$3),"■","") | AT51: Other Online Channel | AU51: 166 | AV51: Impressions | AW51: NA / NA
A52: Cayenne E3 II | B52: Paid Social | C52: 46204 | D52: 46264 | E52: =IFERROR(IF(OR($A52="",$A52="Model",LEFT($A52,5)="Markt"),"",IF(AND($C52<=E$3+6,$D52>=E$3),"■","")),"") | F52: =IFERROR(IF(OR($A52="",$A52="Model",LEFT($A52,5)="Markt"),"",IF(AND($C52<=F$3+6,$D52>=F$3),"■","")),"") | G52: =IFERROR(IF(OR($A52="",$A52="Model",LEFT($A52,5)="Markt"),"",IF(AND($C52<=G$3+6,$D52>=G$3),"■","")),"") | H52: =IFERROR(IF(OR($A52="",$A52="Model",LEFT($A52,5)="Markt"),"",IF(AND($C52<=H$3+6,$D52>=H$3),"■","")),"") | I52: =IFERROR(IF(OR($A52="",$A52="Model",LEFT($A52,5)="Markt"),"",IF(AND($C52<=I$3+6,$D52>=I$3),"■","")),"") | J52: =IFERROR(IF(OR($A52="",$A52="Model",LEFT($A52,5)="Markt"),"",IF(AND($C52<=J$3+6,$D52>=J$3),"■","")),"") | K52: =IFERROR(IF(OR($A52="",$A52="Model",LEFT($A52,5)="Markt"),"",IF(AND($C52<=K$3+6,$D52>=K$3),"■","")),"") | L52: =IFERROR(IF(OR($A52="",$A52="Model",LEFT($A52,5)="Markt"),"",IF(AND($C52<=L$3+6,$D52>=L$3),"■","")),"") | ... V52: =IFERROR(IF(OR($A52="",$A52="Model",LEFT($A52,5)="Markt"),"",IF(AND($C52<=V$3+6,$D52>=V$3),"■","")),"") -> ■
A53: Cayenne E4 | B53: Google Ads | C53: 46143 | D53: 46264 | E53: =IFERROR(IF(OR($A53="",$A53="Model",LEFT($A53,5)="Markt"),"",IF(AND($C53<=E$3+6,$D53>=E$3),"■","")),"") -> ■ | F53: =IFERROR(IF(OR($A53="",$A53="Model",LEFT($A53,5)="Markt"),"",IF(AND($C53<=F$3+6,$D53>=F$3),"■","")),"") -> ■ | G53: =IFERROR(IF(OR($A53="",$A53="Model",LEFT($A53,5)="Markt"),"",IF(AND($C53<=G$3+6,$D53>=G$3),"■","")),"") -> ■ | H53: =IFERROR(IF(OR($A53="",$A53="Model",LEFT($A53,5)="Markt"),"",IF(AND($C53<=H$3+6,$D53>=H$3),"■","")),"") -> ■ | I53: =IFERROR(IF(OR($A53="",$A53="Model",LEFT($A53,5)="Markt"),"",IF(AND($C53<=I$3+6,$D53>=I$3),"■","")),"") -> ■ | J53: =IFERROR(IF(OR($A53="",$A53="Model",LEFT($A53,5)="Markt"),"",IF(AND($C53<=J$3+6,$D53>=J$3),"■","")),"") -> ■ | K53: =IFERROR(IF(OR($A53="",$A53="Model",LEFT($A53,5)="Markt"),"",IF(AND($C53<=K$3+6,$D53>=K$3),"■","")),"") -> ■ | L53: =IFERROR(IF(OR($A53="",$A53="Model",LEFT($A53,5)="Markt"),"",IF(AND($C53<=L$3+6,$D53>=L$3),"■","")),"") -> ■ | ... V53: =IFERROR(IF(OR($A53="",$A53="Model",LEFT($A53,5)="Markt"),"",IF(AND($C53<=V$3+6,$D53>=V$3),"■","")),"") -> ■
A54: Cayenne E4 | B54: Google Inventory Ads | C54: 46204 | D54: 46264 | E54: =IFERROR(IF(OR($A54="",$A54="Model",LEFT($A54,5)="Markt"),"",IF(AND($C54<=E$3+6,$D54>=E$3),"■","")),"") | F54: =IFERROR(IF(OR($A54="",$A54="Model",LEFT($A54,5)="Markt"),"",IF(AND($C54<=F$3+6,$D54>=F$3),"■","")),"") | G54: =IFERROR(IF(OR($A54="",$A54="Model",LEFT($A54,5)="Markt"),"",IF(AND($C54<=G$3+6,$D54>=G$3),"■","")),"") | H54: =IFERROR(IF(OR($A54="",$A54="Model",LEFT($A54,5)="Markt"),"",IF(AND($C54<=H$3+6,$D54>=H$3),"■","")),"") | I54: =IFERROR(IF(OR($A54="",$A54="Model",LEFT($A54,5)="Markt"),"",IF(AND($C54<=I$3+6,$D54>=I$3),"■","")),"") | J54: =IFERROR(IF(OR($A54="",$A54="Model",LEFT($A54,5)="Markt"),"",IF(AND($C54<=J$3+6,$D54>=J$3),"■","")),"") | K54: =IFERROR(IF(OR($A54="",$A54="Model",LEFT($A54,5)="Markt"),"",IF(AND($C54<=K$3+6,$D54>=K$3),"■","")),"") | L54: =IFERROR(IF(OR($A54="",$A54="Model",LEFT($A54,5)="Markt"),"",IF(AND($C54<=L$3+6,$D54>=L$3),"■","")),"") | ... V54: =IFERROR(IF(OR($A54="",$A54="Model",LEFT($A54,5)="Markt"),"",IF(AND($C54<=V$3+6,$D54>=V$3),"■","")),"") -> ■
A55: Cayenne E4 | B55: META Inventory Ads | C55: 46204 | D55: 46264 | E55: =IFERROR(IF(OR($A55="",$A55="Model",LEFT($A55,5)="Markt"),"",IF(AND($C55<=E$3+6,$D55>=E$3),"■","")),"") | F55: =IFERROR(IF(OR($A55="",$A55="Model",LEFT($A55,5)="Markt"),"",IF(AND($C55<=F$3+6,$D55>=F$3),"■","")),"") | G55: =IFERROR(IF(OR($A55="",$A55="Model",LEFT($A55,5)="Markt"),"",IF(AND($C55<=G$3+6,$D55>=G$3),"■","")),"") | H55: =IFERROR(IF(OR($A55="",$A55="Model",LEFT($A55,5)="Markt"),"",IF(AND($C55<=H$3+6,$D55>=H$3),"■","")),"") | I55: =IFERROR(IF(OR($A55="",$A55="Model",LEFT($A55,5)="Markt"),"",IF(AND($C55<=I$3+6,$D55>=I$3),"■","")),"") | J55: =IFERROR(IF(OR($A55="",$A55="Model",LEFT($A55,5)="Markt"),"",IF(AND($C55<=J$3+6,$D55>=J$3),"■","")),"") | K55: =IFERROR(IF(OR($A55="",$A55="Model",LEFT($A55,5)="Markt"),"",IF(AND($C55<=K$3+6,$D55>=K$3),"■","")),"") | L55: =IFERROR(IF(OR($A55="",$A55="Model",LEFT($A55,5)="Markt"),"",IF(AND($C55<=L$3+6,$D55>=L$3),"■","")),"") | ... V55: =IFERROR(IF(OR($A55="",$A55="Model",LEFT($A55,5)="Markt"),"",IF(AND($C55<=V$3+6,$D55>=V$3),"■","")),"") -> ■
A56: Cayenne E4 | B56: Paid Social | C56: 46204 | D56: 46264 | E56: =IFERROR(IF(OR($A56="",$A56="Model",LEFT($A56,5)="Markt"),"",IF(AND($C56<=E$3+6,$D56>=E$3),"■","")),"") | F56: =IFERROR(IF(OR($A56="",$A56="Model",LEFT($A56,5)="Markt"),"",IF(AND($C56<=F$3+6,$D56>=F$3),"■","")),"") | G56: =IFERROR(IF(OR($A56="",$A56="Model",LEFT($A56,5)="Markt"),"",IF(AND($C56<=G$3+6,$D56>=G$3),"■","")),"") | H56: =IFERROR(IF(OR($A56="",$A56="Model",LEFT($A56,5)="Markt"),"",IF(AND($C56<=H$3+6,$D56>=H$3),"■","")),"") | I56: =IFERROR(IF(OR($A56="",$A56="Model",LEFT($A56,5)="Markt"),"",IF(AND($C56<=I$3+6,$D56>=I$3),"■","")),"") | J56: =IFERROR(IF(OR($A56="",$A56="Model",LEFT($A56,5)="Markt"),"",IF(AND($C56<=J$3+6,$D56>=J$3),"■","")),"") | K56: =IFERROR(IF(OR($A56="",$A56="Model",LEFT($A56,5)="Markt"),"",IF(AND($C56<=K$3+6,$D56>=K$3),"■","")),"") | L56: =IFERROR(IF(OR($A56="",$A56="Model",LEFT($A56,5)="Markt"),"",IF(AND($C56<=L$3+6,$D56>=L$3),"■","")),"") | ... V56: =IFERROR(IF(OR($A56="",$A56="Model",LEFT($A56,5)="Markt"),"",IF(AND($C56<=V$3+6,$D56>=V$3),"■","")),"") -> ■
A57: Markt: PIT | X57: Markt: PIT (Survey) | AT57: {=_xlfn.LET(_xlpm.mL,A57,_xlpm.aL,B57,_xlpm.mR,X57,_xlpm.aR,Y57,_xlpm.useR,AND(_xlpm.mR<>"",_xlpm.mR<>"Model",LEFT(_xlpm.mR,6)<>"Markt:"),_xlpm.m,IF(_xlpm.useR,_xlpm.mR,_xlpm.mL),_xlpm.a,IF(_xlpm.useR,_xlpm.aR,_xlpm.aL),_xlpm.rng,IF(_xlpm.useR,X$1:X57,A$1:A57),IF(OR(_xlpm.m="",_xlpm.m="Model",LEFT(_xlpm.m,6)="Markt:"),"",_xlfn.LET(_xlpm.mkt,LOOKUP(2,1/(LEFT(_xlpm.rng,6)="Markt:"),_xlpm.rng),_xlpm.mktNameRaw,TRIM(MID(_xlpm.mkt,FIND(":",_xlpm.mkt)+1,99)),_xlpm.mktName,TRIM(SUBSTITUTE(_xlpm.mktNameRaw,"(Survey)","")),_xlfn.XLOOKUP(_xlpm.mktName&"|"&SUBSTITUTE(_xlpm.m," ","")&"|"&_xlpm.a,tblMassnahmen[Key],tblMassnahmen[Kanal],""))))} | AU57: {=_xlfn.LET(_xlpm.mL,A57,_xlpm.aL,B57,_xlpm.mR,X57,_xlpm.aR,Y57,_xlpm.useR,AND(_xlpm.mR<>"",_xlpm.mR<>"Model",LEFT(_xlpm.mR,6)<>"Markt:"),_xlpm.m,IF(_xlpm.useR,_xlpm.mR,_xlpm.mL),_xlpm.a,IF(_xlpm.useR,_xlpm.aR,_xlpm.aL),_xlpm.rng,IF(_xlpm.useR,X$1:X57,A$1:A57),IF(OR(_xlpm.m="",_xlpm.m="Model",LEFT(_xlpm.m,6)="Markt:"),"",_xlfn.LET(_xlpm.mkt,LOOKUP(2,1/(LEFT(_xlpm.rng,6)="Markt:"),_xlpm.rng),_xlpm.mktNameRaw,TRIM(MID(_xlpm.mkt,FIND(":",_xlpm.mkt)+1,99)),_xlpm.mktName,TRIM(SUBSTITUTE(_xlpm.mktNameRaw,"(Survey)","")),_xlfn.XLOOKUP(_xlpm.mktName&"|"&SUBSTITUTE(_xlpm.m," ","")&"|"&_xlpm.a,tblMassnahmen[Key],tblMassnahmen[Budget],""))))} | AV57: {=_xlfn.LET(_xlpm.mL,A57,_xlpm.aL,B57,_xlpm.mR,X57,_xlpm.aR,Y57,_xlpm.useR,AND(_xlpm.mR<>"",_xlpm.mR<>"Model",LEFT(_xlpm.mR,6)<>"Markt:"),_xlpm.m,IF(_xlpm.useR,_xlpm.mR,_xlpm.mL),_xlpm.a,IF(_xlpm.useR,_xlpm.aR,_xlpm.aL),_xlpm.rng,IF(_xlpm.useR,X$1:X57,A$1:A57),IF(OR(_xlpm.m="",_xlpm.m="Model",LEFT(_xlpm.m,6)="Markt:"),"",_xlfn.LET(_xlpm.mkt,LOOKUP(2,1/(LEFT(_xlpm.rng,6)="Markt:"),_xlpm.rng),_xlpm.mktNameRaw,TRIM(MID(_xlpm.mkt,FIND(":",_xlpm.mkt)+1,99)),_xlpm.mktName,TRIM(SUBSTITUTE(_xlpm.mktNameRaw,"(Survey)","")),_xlfn.XLOOKUP(_xlpm.mktName&"|"&SUBSTITUTE(_xlpm.m," ","")&"|"&_xlpm.a,tblMassnahmen[Key],tblMassnahmen[KPI],""))))}
A58: Model | B58: CTG Measure | C58: Start | D58: Ende | E58: CW18 | F58: CW19 | G58: CW20 | H58: CW21 | I58: CW22 | J58: CW23 | K58: CW24 | L58: CW25 | M58: CW26 | N58: CW27 | O58: CW28 | P58: CW29 | Q58: CW30 | R58: CW31 | S58: CW32 | T58: CW33 | U58: CW34 | V58: CW35 | X58: Model | Y58: Local Measure | Z58: Start | AA58: Ende | AB58: CW18 | AC58: CW19 | AD58: CW20 | AE58: CW21 | AF58: CW22 | AG58: CW23 | AH58: CW24 | AI58: CW25 | AJ58: CW26 | AK58: CW27 | AL58: CW28 | AM58: CW29 | AN58: CW30 | AO58: CW31 | AP58: CW32 | AQ58: CW33 | AR58: CW34 | AS58: CW35 | AT58: Channel | AU58: Budget | AV58: KPI | AW58: Audience
A59: Macan BEV | B59: Google Ads | C59: 46143 | D59: 46264 | E59: =IFERROR(IF(OR($A59="",$A59="Model",LEFT($A59,5)="Markt"),"",IF(AND($C59<=E$3+6,$D59>=E$3),"■","")),"") -> ■ | F59: =IFERROR(IF(OR($A59="",$A59="Model",LEFT($A59,5)="Markt"),"",IF(AND($C59<=F$3+6,$D59>=F$3),"■","")),"") -> ■ | G59: =IFERROR(IF(OR($A59="",$A59="Model",LEFT($A59,5)="Markt"),"",IF(AND($C59<=G$3+6,$D59>=G$3),"■","")),"") -> ■ | H59: =IFERROR(IF(OR($A59="",$A59="Model",LEFT($A59,5)="Markt"),"",IF(AND($C59<=H$3+6,$D59>=H$3),"■","")),"") -> ■ | I59: =IFERROR(IF(OR($A59="",$A59="Model",LEFT($A59,5)="Markt"),"",IF(AND($C59<=I$3+6,$D59>=I$3),"■","")),"") -> ■ | J59: =IFERROR(IF(OR($A59="",$A59="Model",LEFT($A59,5)="Markt"),"",IF(AND($C59<=J$3+6,$D59>=J$3),"■","")),"") -> ■ | K59: =IFERROR(IF(OR($A59="",$A59="Model",LEFT($A59,5)="Markt"),"",IF(AND($C59<=K$3+6,$D59>=K$3),"■","")),"") -> ■ | L59: =IFERROR(IF(OR($A59="",$A59="Model",LEFT($A59,5)="Markt"),"",IF(AND($C59<=L$3+6,$D59>=L$3),"■","")),"") -> ■ | ... V59: =IFERROR(IF(OR($A59="",$A59="Model",LEFT($A59,5)="Markt"),"",IF(AND($C59<=V$3+6,$D59>=V$3),"■","")),"") -> ■ | X59: Macan H2 | Y59: Campagna DCO | Z59: 46067 | AA59: 46386 | AB59: =IF(AND($Z59<=(AB$3+6),$AA59>=AB$3),"■","") -> ■ | AC59: =IF(AND($Z59<=(AC$3+6),$AA59>=AC$3),"■","") -> ■ | AD59: =IF(AND($Z59<=(AD$3+6),$AA59>=AD$3),"■","") -> ■ | AE59: =IF(AND($Z59<=(AE$3+6),$AA59>=AE$3),"■","") -> ■ | AF59: =IF(AND($Z59<=(AF$3+6),$AA59>=AF$3),"■","") -> ■ | AG59: =IF(AND($Z59<=(AG$3+6),$AA59>=AG$3),"■","") -> ■ | AH59: =IF(AND($Z59<=(AH$3+6),$AA59>=AH$3),"■","") -> ■ | AI59: =IF(AND($Z59<=(AI$3+6),$AA59>=AI$3),"■","") -> ■ | ... AS59: =IF(AND($Z59<=(AS$3+6),$AA59>=AS$3),"■","") -> ■ | AT59: Social,Programmatic | AU59: 190 | AV59: Impressions,Dealer contact form submitted (DCFS) | AW59: Custom adience / retargeting and cdp
A60: Macan BEV | B60: Google Inventory Ads | C60: 46174 | D60: 46264 | E60: =IFERROR(IF(OR($A60="",$A60="Model",LEFT($A60,5)="Markt"),"",IF(AND($C60<=E$3+6,$D60>=E$3),"■","")),"") | F60: =IFERROR(IF(OR($A60="",$A60="Model",LEFT($A60,5)="Markt"),"",IF(AND($C60<=F$3+6,$D60>=F$3),"■","")),"") | G60: =IFERROR(IF(OR($A60="",$A60="Model",LEFT($A60,5)="Markt"),"",IF(AND($C60<=G$3+6,$D60>=G$3),"■","")),"") | H60: =IFERROR(IF(OR($A60="",$A60="Model",LEFT($A60,5)="Markt"),"",IF(AND($C60<=H$3+6,$D60>=H$3),"■","")),"") | I60: =IFERROR(IF(OR($A60="",$A60="Model",LEFT($A60,5)="Markt"),"",IF(AND($C60<=I$3+6,$D60>=I$3),"■","")),"") | J60: =IFERROR(IF(OR($A60="",$A60="Model",LEFT($A60,5)="Markt"),"",IF(AND($C60<=J$3+6,$D60>=J$3),"■","")),"") -> ■ | K60: =IFERROR(IF(OR($A60="",$A60="Model",LEFT($A60,5)="Markt"),"",IF(AND($C60<=K$3+6,$D60>=K$3),"■","")),"") -> ■ | L60: =IFERROR(IF(OR($A60="",$A60="Model",LEFT($A60,5)="Markt"),"",IF(AND($C60<=L$3+6,$D60>=L$3),"■","")),"") -> ■ | ... V60: =IFERROR(IF(OR($A60="",$A60="Model",LEFT($A60,5)="Markt"),"",IF(AND($C60<=V$3+6,$D60>=V$3),"■","")),"") -> ■ | X60: Cayenne E4 | Y60: Campagna DCO | Z60: 46067 | AA60: 46386 | AB60: =IF(AND($Z60<=(AB$3+6),$AA60>=AB$3),"■","") -> ■ | AC60: =IF(AND($Z60<=(AC$3+6),$AA60>=AC$3),"■","") -> ■ | AD60: =IF(AND($Z60<=(AD$3+6),$AA60>=AD$3),"■","") -> ■ | AE60: =IF(AND($Z60<=(AE$3+6),$AA60>=AE$3),"■","") -> ■ | AF60: =IF(AND($Z60<=(AF$3+6),$AA60>=AF$3),"■","") -> ■ | AG60: =IF(AND($Z60<=(AG$3+6),$AA60>=AG$3),"■","") -> ■ | AH60: =IF(AND($Z60<=(AH$3+6),$AA60>=AH$3),"■","") -> ■ | AI60: =IF(AND($Z60<=(AI$3+6),$AA60>=AI$3),"■","") -> ■ | ... AS60: =IF(AND($Z60<=(AS$3+6),$AA60>=AS$3),"■","") -> ■ | AT60: Programmatic | AU60: 100 | AV60: Dealer contact form submitted (DCFS) | AW60: Custom affinity audience / Retargeting
A61: Macan BEV | B61: META Inventory Ads | C61: 46143 | D61: 46264 | E61: =IFERROR(IF(OR($A61="",$A61="Model",LEFT($A61,5)="Markt"),"",IF(AND($C61<=E$3+6,$D61>=E$3),"■","")),"") -> ■ | F61: =IFERROR(IF(OR($A61="",$A61="Model",LEFT($A61,5)="Markt"),"",IF(AND($C61<=F$3+6,$D61>=F$3),"■","")),"") -> ■ | G61: =IFERROR(IF(OR($A61="",$A61="Model",LEFT($A61,5)="Markt"),"",IF(AND($C61<=G$3+6,$D61>=G$3),"■","")),"") -> ■ | H61: =IFERROR(IF(OR($A61="",$A61="Model",LEFT($A61,5)="Markt"),"",IF(AND($C61<=H$3+6,$D61>=H$3),"■","")),"") -> ■ | I61: =IFERROR(IF(OR($A61="",$A61="Model",LEFT($A61,5)="Markt"),"",IF(AND($C61<=I$3+6,$D61>=I$3),"■","")),"") -> ■ | J61: =IFERROR(IF(OR($A61="",$A61="Model",LEFT($A61,5)="Markt"),"",IF(AND($C61<=J$3+6,$D61>=J$3),"■","")),"") -> ■ | K61: =IFERROR(IF(OR($A61="",$A61="Model",LEFT($A61,5)="Markt"),"",IF(AND($C61<=K$3+6,$D61>=K$3),"■","")),"") -> ■ | L61: =IFERROR(IF(OR($A61="",$A61="Model",LEFT($A61,5)="Markt"),"",IF(AND($C61<=L$3+6,$D61>=L$3),"■","")),"") -> ■ | ... V61: =IFERROR(IF(OR($A61="",$A61="Model",LEFT($A61,5)="Markt"),"",IF(AND($C61<=V$3+6,$D61>=V$3),"■","")),"") -> ■ | X61: Cayenne E4 | Y61: Cayenne E4 | Z61: 46067 | AA61: 46386 | AB61: =IF(AND($Z61<=(AB$3+6),$AA61>=AB$3),"■","") -> ■ | AC61: =IF(AND($Z61<=(AC$3+6),$AA61>=AC$3),"■","") -> ■ | AD61: =IF(AND($Z61<=(AD$3+6),$AA61>=AD$3),"■","") -> ■ | AE61: =IF(AND($Z61<=(AE$3+6),$AA61>=AE$3),"■","") -> ■ | AF61: =IF(AND($Z61<=(AF$3+6),$AA61>=AF$3),"■","") -> ■ | AG61: =IF(AND($Z61<=(AG$3+6),$AA61>=AG$3),"■","") -> ■ | AH61: =IF(AND($Z61<=(AH$3+6),$AA61>=AH$3),"■","") -> ■ | AI61: =IF(AND($Z61<=(AI$3+6),$AA61>=AI$3),"■","") -> ■ | ... AS61: =IF(AND($Z61<=(AS$3+6),$AA61>=AS$3),"■","") -> ■ | AT61: Social,Programmatic | AU61: 100 | AV61: Cost per Million (CPM),Dealer contact form submitted (DCFS) | AW61: Custom affinity audience / Retargeting audience
A62: Macan BEV | B62: Paid Social | C62: 46204 | D62: 46264 | E62: =IFERROR(IF(OR($A62="",$A62="Model",LEFT($A62,5)="Markt"),"",IF(AND($C62<=E$3+6,$D62>=E$3),"■","")),"") | F62: =IFERROR(IF(OR($A62="",$A62="Model",LEFT($A62,5)="Markt"),"",IF(AND($C62<=F$3+6,$D62>=F$3),"■","")),"") | G62: =IFERROR(IF(OR($A62="",$A62="Model",LEFT($A62,5)="Markt"),"",IF(AND($C62<=G$3+6,$D62>=G$3),"■","")),"") | H62: =IFERROR(IF(OR($A62="",$A62="Model",LEFT($A62,5)="Markt"),"",IF(AND($C62<=H$3+6,$D62>=H$3),"■","")),"") | I62: =IFERROR(IF(OR($A62="",$A62="Model",LEFT($A62,5)="Markt"),"",IF(AND($C62<=I$3+6,$D62>=I$3),"■","")),"") | J62: =IFERROR(IF(OR($A62="",$A62="Model",LEFT($A62,5)="Markt"),"",IF(AND($C62<=J$3+6,$D62>=J$3),"■","")),"") | K62: =IFERROR(IF(OR($A62="",$A62="Model",LEFT($A62,5)="Markt"),"",IF(AND($C62<=K$3+6,$D62>=K$3),"■","")),"") | L62: =IFERROR(IF(OR($A62="",$A62="Model",LEFT($A62,5)="Markt"),"",IF(AND($C62<=L$3+6,$D62>=L$3),"■","")),"") | ... V62: =IFERROR(IF(OR($A62="",$A62="Model",LEFT($A62,5)="Markt"),"",IF(AND($C62<=V$3+6,$D62>=V$3),"■","")),"") -> ■
A63: Cayenne E3 II | B63: Google Ads | C63: 46143 | D63: 46264 | E63: =IFERROR(IF(OR($A63="",$A63="Model",LEFT($A63,5)="Markt"),"",IF(AND($C63<=E$3+6,$D63>=E$3),"■","")),"") -> ■ | F63: =IFERROR(IF(OR($A63="",$A63="Model",LEFT($A63,5)="Markt"),"",IF(AND($C63<=F$3+6,$D63>=F$3),"■","")),"") -> ■ | G63: =IFERROR(IF(OR($A63="",$A63="Model",LEFT($A63,5)="Markt"),"",IF(AND($C63<=G$3+6,$D63>=G$3),"■","")),"") -> ■ | H63: =IFERROR(IF(OR($A63="",$A63="Model",LEFT($A63,5)="Markt"),"",IF(AND($C63<=H$3+6,$D63>=H$3),"■","")),"") -> ■ | I63: =IFERROR(IF(OR($A63="",$A63="Model",LEFT($A63,5)="Markt"),"",IF(AND($C63<=I$3+6,$D63>=I$3),"■","")),"") -> ■ | J63: =IFERROR(IF(OR($A63="",$A63="Model",LEFT($A63,5)="Markt"),"",IF(AND($C63<=J$3+6,$D63>=J$3),"■","")),"") -> ■ | K63: =IFERROR(IF(OR($A63="",$A63="Model",LEFT($A63,5)="Markt"),"",IF(AND($C63<=K$3+6,$D63>=K$3),"■","")),"") -> ■ | L63: =IFERROR(IF(OR($A63="",$A63="Model",LEFT($A63,5)="Markt"),"",IF(AND($C63<=L$3+6,$D63>=L$3),"■","")),"") -> ■ | ... V63: =IFERROR(IF(OR($A63="",$A63="Model",LEFT($A63,5)="Markt"),"",IF(AND($C63<=V$3+6,$D63>=V$3),"■","")),"") -> ■
A64: Cayenne E3 II | B64: Google Inventory Ads | C64: 46174 | D64: 46264 | E64: =IFERROR(IF(OR($A64="",$A64="Model",LEFT($A64,5)="Markt"),"",IF(AND($C64<=E$3+6,$D64>=E$3),"■","")),"") | F64: =IFERROR(IF(OR($A64="",$A64="Model",LEFT($A64,5)="Markt"),"",IF(AND($C64<=F$3+6,$D64>=F$3),"■","")),"") | G64: =IFERROR(IF(OR($A64="",$A64="Model",LEFT($A64,5)="Markt"),"",IF(AND($C64<=G$3+6,$D64>=G$3),"■","")),"") | H64: =IFERROR(IF(OR($A64="",$A64="Model",LEFT($A64,5)="Markt"),"",IF(AND($C64<=H$3+6,$D64>=H$3),"■","")),"") | I64: =IFERROR(IF(OR($A64="",$A64="Model",LEFT($A64,5)="Markt"),"",IF(AND($C64<=I$3+6,$D64>=I$3),"■","")),"") | J64: =IFERROR(IF(OR($A64="",$A64="Model",LEFT($A64,5)="Markt"),"",IF(AND($C64<=J$3+6,$D64>=J$3),"■","")),"") -> ■ | K64: =IFERROR(IF(OR($A64="",$A64="Model",LEFT($A64,5)="Markt"),"",IF(AND($C64<=K$3+6,$D64>=K$3),"■","")),"") -> ■ | L64: =IFERROR(IF(OR($A64="",$A64="Model",LEFT($A64,5)="Markt"),"",IF(AND($C64<=L$3+6,$D64>=L$3),"■","")),"") -> ■ | ... V64: =IFERROR(IF(OR($A64="",$A64="Model",LEFT($A64,5)="Markt"),"",IF(AND($C64<=V$3+6,$D64>=V$3),"■","")),"") -> ■
A65: Cayenne E3 II | B65: META Inventory Ads | C65: 46143 | D65: 46264 | E65: =IFERROR(IF(OR($A65="",$A65="Model",LEFT($A65,5)="Markt"),"",IF(AND($C65<=E$3+6,$D65>=E$3),"■","")),"") -> ■ | F65: =IFERROR(IF(OR($A65="",$A65="Model",LEFT($A65,5)="Markt"),"",IF(AND($C65<=F$3+6,$D65>=F$3),"■","")),"") -> ■ | G65: =IFERROR(IF(OR($A65="",$A65="Model",LEFT($A65,5)="Markt"),"",IF(AND($C65<=G$3+6,$D65>=G$3),"■","")),"") -> ■ | H65: =IFERROR(IF(OR($A65="",$A65="Model",LEFT($A65,5)="Markt"),"",IF(AND($C65<=H$3+6,$D65>=H$3),"■","")),"") -> ■ | I65: =IFERROR(IF(OR($A65="",$A65="Model",LEFT($A65,5)="Markt"),"",IF(AND($C65<=I$3+6,$D65>=I$3),"■","")),"") -> ■ | J65: =IFERROR(IF(OR($A65="",$A65="Model",LEFT($A65,5)="Markt"),"",IF(AND($C65<=J$3+6,$D65>=J$3),"■","")),"") -> ■ | K65: =IFERROR(IF(OR($A65="",$A65="Model",LEFT($A65,5)="Markt"),"",IF(AND($C65<=K$3+6,$D65>=K$3),"■","")),"") -> ■ | L65: =IFERROR(IF(OR($A65="",$A65="Model",LEFT($A65,5)="Markt"),"",IF(AND($C65<=L$3+6,$D65>=L$3),"■","")),"") -> ■ | ... V65: =IFERROR(IF(OR($A65="",$A65="Model",LEFT($A65,5)="Markt"),"",IF(AND($C65<=V$3+6,$D65>=V$3),"■","")),"") -> ■
A66: Cayenne E3 II | B66: Paid Social | C66: 46204 | D66: 46264 | E66: =IFERROR(IF(OR($A66="",$A66="Model",LEFT($A66,5)="Markt"),"",IF(AND($C66<=E$3+6,$D66>=E$3),"■","")),"") | F66: =IFERROR(IF(OR($A66="",$A66="Model",LEFT($A66,5)="Markt"),"",IF(AND($C66<=F$3+6,$D66>=F$3),"■","")),"") | G66: =IFERROR(IF(OR($A66="",$A66="Model",LEFT($A66,5)="Markt"),"",IF(AND($C66<=G$3+6,$D66>=G$3),"■","")),"") | H66: =IFERROR(IF(OR($A66="",$A66="Model",LEFT($A66,5)="Markt"),"",IF(AND($C66<=H$3+6,$D66>=H$3),"■","")),"") | I66: =IFERROR(IF(OR($A66="",$A66="Model",LEFT($A66,5)="Markt"),"",IF(AND($C66<=I$3+6,$D66>=I$3),"■","")),"") | J66: =IFERROR(IF(OR($A66="",$A66="Model",LEFT($A66,5)="Markt"),"",IF(AND($C66<=J$3+6,$D66>=J$3),"■","")),"") | K66: =IFERROR(IF(OR($A66="",$A66="Model",LEFT($A66,5)="Markt"),"",IF(AND($C66<=K$3+6,$D66>=K$3),"■","")),"") | L66: =IFERROR(IF(OR($A66="",$A66="Model",LEFT($A66,5)="Markt"),"",IF(AND($C66<=L$3+6,$D66>=L$3),"■","")),"") | ... V66: =IFERROR(IF(OR($A66="",$A66="Model",LEFT($A66,5)="Markt"),"",IF(AND($C66<=V$3+6,$D66>=V$3),"■","")),"") -> ■
A67: Cayenne E4 | B67: Google Ads | C67: 46143 | D67: 46264 | E67: =IFERROR(IF(OR($A67="",$A67="Model",LEFT($A67,5)="Markt"),"",IF(AND($C67<=E$3+6,$D67>=E$3),"■","")),"") -> ■ | F67: =IFERROR(IF(OR($A67="",$A67="Model",LEFT($A67,5)="Markt"),"",IF(AND($C67<=F$3+6,$D67>=F$3),"■","")),"") -> ■ | G67: =IFERROR(IF(OR($A67="",$A67="Model",LEFT($A67,5)="Markt"),"",IF(AND($C67<=G$3+6,$D67>=G$3),"■","")),"") -> ■ | H67: =IFERROR(IF(OR($A67="",$A67="Model",LEFT($A67,5)="Markt"),"",IF(AND($C67<=H$3+6,$D67>=H$3),"■","")),"") -> ■ | I67: =IFERROR(IF(OR($A67="",$A67="Model",LEFT($A67,5)="Markt"),"",IF(AND($C67<=I$3+6,$D67>=I$3),"■","")),"") -> ■ | J67: =IFERROR(IF(OR($A67="",$A67="Model",LEFT($A67,5)="Markt"),"",IF(AND($C67<=J$3+6,$D67>=J$3),"■","")),"") -> ■ | K67: =IFERROR(IF(OR($A67="",$A67="Model",LEFT($A67,5)="Markt"),"",IF(AND($C67<=K$3+6,$D67>=K$3),"■","")),"") -> ■ | L67: =IFERROR(IF(OR($A67="",$A67="Model",LEFT($A67,5)="Markt"),"",IF(AND($C67<=L$3+6,$D67>=L$3),"■","")),"") -> ■ | ... V67: =IFERROR(IF(OR($A67="",$A67="Model",LEFT($A67,5)="Markt"),"",IF(AND($C67<=V$3+6,$D67>=V$3),"■","")),"") -> ■
A68: Cayenne E4 | B68: Google Inventory Ads | C68: 46204 | D68: 46264 | E68: =IFERROR(IF(OR($A68="",$A68="Model",LEFT($A68,5)="Markt"),"",IF(AND($C68<=E$3+6,$D68>=E$3),"■","")),"") | F68: =IFERROR(IF(OR($A68="",$A68="Model",LEFT($A68,5)="Markt"),"",IF(AND($C68<=F$3+6,$D68>=F$3),"■","")),"") | G68: =IFERROR(IF(OR($A68="",$A68="Model",LEFT($A68,5)="Markt"),"",IF(AND($C68<=G$3+6,$D68>=G$3),"■","")),"") | H68: =IFERROR(IF(OR($A68="",$A68="Model",LEFT($A68,5)="Markt"),"",IF(AND($C68<=H$3+6,$D68>=H$3),"■","")),"") | I68: =IFERROR(IF(OR($A68="",$A68="Model",LEFT($A68,5)="Markt"),"",IF(AND($C68<=I$3+6,$D68>=I$3),"■","")),"") | J68: =IFERROR(IF(OR($A68="",$A68="Model",LEFT($A68,5)="Markt"),"",IF(AND($C68<=J$3+6,$D68>=J$3),"■","")),"") | K68: =IFERROR(IF(OR($A68="",$A68="Model",LEFT($A68,5)="Markt"),"",IF(AND($C68<=K$3+6,$D68>=K$3),"■","")),"") | L68: =IFERROR(IF(OR($A68="",$A68="Model",LEFT($A68,5)="Markt"),"",IF(AND($C68<=L$3+6,$D68>=L$3),"■","")),"") | ... V68: =IFERROR(IF(OR($A68="",$A68="Model",LEFT($A68,5)="Markt"),"",IF(AND($C68<=V$3+6,$D68>=V$3),"■","")),"") -> ■
A69: Cayenne E4 | B69: META Inventory Ads | C69: 46204 | D69: 46264 | E69: =IFERROR(IF(OR($A69="",$A69="Model",LEFT($A69,5)="Markt"),"",IF(AND($C69<=E$3+6,$D69>=E$3),"■","")),"") | F69: =IFERROR(IF(OR($A69="",$A69="Model",LEFT($A69,5)="Markt"),"",IF(AND($C69<=F$3+6,$D69>=F$3),"■","")),"") | G69: =IFERROR(IF(OR($A69="",$A69="Model",LEFT($A69,5)="Markt"),"",IF(AND($C69<=G$3+6,$D69>=G$3),"■","")),"") | H69: =IFERROR(IF(OR($A69="",$A69="Model",LEFT($A69,5)="Markt"),"",IF(AND($C69<=H$3+6,$D69>=H$3),"■","")),"") | I69: =IFERROR(IF(OR($A69="",$A69="Model",LEFT($A69,5)="Markt"),"",IF(AND($C69<=I$3+6,$D69>=I$3),"■","")),"") | J69: =IFERROR(IF(OR($A69="",$A69="Model",LEFT($A69,5)="Markt"),"",IF(AND($C69<=J$3+6,$D69>=J$3),"■","")),"") | K69: =IFERROR(IF(OR($A69="",$A69="Model",LEFT($A69,5)="Markt"),"",IF(AND($C69<=K$3+6,$D69>=K$3),"■","")),"") | L69: =IFERROR(IF(OR($A69="",$A69="Model",LEFT($A69,5)="Markt"),"",IF(AND($C69<=L$3+6,$D69>=L$3),"■","")),"") | ... V69: =IFERROR(IF(OR($A69="",$A69="Model",LEFT($A69,5)="Markt"),"",IF(AND($C69<=V$3+6,$D69>=V$3),"■","")),"") -> ■
A70: Cayenne E4 | B70: Paid Social | C70: 46204 | D70: 46264 | E70: =IFERROR(IF(OR($A70="",$A70="Model",LEFT($A70,5)="Markt"),"",IF(AND($C70<=E$3+6,$D70>=E$3),"■","")),"") | F70: =IFERROR(IF(OR($A70="",$A70="Model",LEFT($A70,5)="Markt"),"",IF(AND($C70<=F$3+6,$D70>=F$3),"■","")),"") | G70: =IFERROR(IF(OR($A70="",$A70="Model",LEFT($A70,5)="Markt"),"",IF(AND($C70<=G$3+6,$D70>=G$3),"■","")),"") | H70: =IFERROR(IF(OR($A70="",$A70="Model",LEFT($A70,5)="Markt"),"",IF(AND($C70<=H$3+6,$D70>=H$3),"■","")),"") | I70: =IFERROR(IF(OR($A70="",$A70="Model",LEFT($A70,5)="Markt"),"",IF(AND($C70<=I$3+6,$D70>=I$3),"■","")),"") | J70: =IFERROR(IF(OR($A70="",$A70="Model",LEFT($A70,5)="Markt"),"",IF(AND($C70<=J$3+6,$D70>=J$3),"■","")),"") | K70: =IFERROR(IF(OR($A70="",$A70="Model",LEFT($A70,5)="Markt"),"",IF(AND($C70<=K$3+6,$D70>=K$3),"■","")),"") | L70: =IFERROR(IF(OR($A70="",$A70="Model",LEFT($A70,5)="Markt"),"",IF(AND($C70<=L$3+6,$D70>=L$3),"■","")),"") | ... V70: =IFERROR(IF(OR($A70="",$A70="Model",LEFT($A70,5)="Markt"),"",IF(AND($C70<=V$3+6,$D70>=V$3),"■","")),"") -> ■
A71: Markt: TRK | X71: Markt: TRK (Survey)
A72: Model | B72: CTG Measure | C72: Start | D72: Ende | E72: CW18 | F72: CW19 | G72: CW20 | H72: CW21 | I72: CW22 | J72: CW23 | K72: CW24 | L72: CW25 | M72: CW26 | N72: CW27 | O72: CW28 | P72: CW29 | Q72: CW30 | R72: CW31 | S72: CW32 | T72: CW33 | U72: CW34 | V72: CW35 | X72: Model | Y72: Local Measure | Z72: Start | AA72: Ende | AB72: CW18 | AC72: CW19 | AD72: CW20 | AE72: CW21 | AF72: CW22 | AG72: CW23 | AH72: CW24 | AI72: CW25 | AJ72: CW26 | AK72: CW27 | AL72: CW28 | AM72: CW29 | AN72: CW30 | AO72: CW31 | AP72: CW32 | AQ72: CW33 | AR72: CW34 | AS72: CW35 | AT72: Channel | AU72: Budget | AV72: KPI | AW72: Audience
A73: Macan BEV | B73: Google Ads | C73: 46143 | D73: 46264 | E73: =IFERROR(IF(OR($A73="",$A73="Model",LEFT($A73,5)="Markt"),"",IF(AND($C73<=E$3+6,$D73>=E$3),"■","")),"") -> ■ | F73: =IFERROR(IF(OR($A73="",$A73="Model",LEFT($A73,5)="Markt"),"",IF(AND($C73<=F$3+6,$D73>=F$3),"■","")),"") -> ■ | G73: =IFERROR(IF(OR($A73="",$A73="Model",LEFT($A73,5)="Markt"),"",IF(AND($C73<=G$3+6,$D73>=G$3),"■","")),"") -> ■ | H73: =IFERROR(IF(OR($A73="",$A73="Model",LEFT($A73,5)="Markt"),"",IF(AND($C73<=H$3+6,$D73>=H$3),"■","")),"") -> ■ | I73: =IFERROR(IF(OR($A73="",$A73="Model",LEFT($A73,5)="Markt"),"",IF(AND($C73<=I$3+6,$D73>=I$3),"■","")),"") -> ■ | J73: =IFERROR(IF(OR($A73="",$A73="Model",LEFT($A73,5)="Markt"),"",IF(AND($C73<=J$3+6,$D73>=J$3),"■","")),"") -> ■ | K73: =IFERROR(IF(OR($A73="",$A73="Model",LEFT($A73,5)="Markt"),"",IF(AND($C73<=K$3+6,$D73>=K$3),"■","")),"") -> ■ | L73: =IFERROR(IF(OR($A73="",$A73="Model",LEFT($A73,5)="Markt"),"",IF(AND($C73<=L$3+6,$D73>=L$3),"■","")),"") -> ■ | ... V73: =IFERROR(IF(OR($A73="",$A73="Model",LEFT($A73,5)="Markt"),"",IF(AND($C73<=V$3+6,$D73>=V$3),"■","")),"") -> ■ | X73: Macan H2 | Y73: DCO Programmatic Macan Electric | Z73: 46202 | AA73: 46294 | AB73: =IF(AND($Z73<=(AB$3+6),$AA73>=AB$3),"■","") | AC73: =IF(AND($Z73<=(AC$3+6),$AA73>=AC$3),"■","") | AD73: =IF(AND($Z73<=(AD$3+6),$AA73>=AD$3),"■","") | AE73: =IF(AND($Z73<=(AE$3+6),$AA73>=AE$3),"■","") | AF73: =IF(AND($Z73<=(AF$3+6),$AA73>=AF$3),"■","") | AG73: =IF(AND($Z73<=(AG$3+6),$AA73>=AG$3),"■","") | AH73: =IF(AND($Z73<=(AH$3+6),$AA73>=AH$3),"■","") | AI73: =IF(AND($Z73<=(AI$3+6),$AA73>=AI$3),"■","") | ... AS73: =IF(AND($Z73<=(AS$3+6),$AA73>=AS$3),"■","") -> ■ | AT73: Programmatic | AU73: This campaign is still at the planning stage, the market budget allocation is not confirmed yet. | AV73: Configuration | AW73: Turkey website visitors and car configurator visitors / Performance and Luxury Vehicle Enthusiasts
A74: Macan BEV | B74: META Inventory Ads | C74: 46143 | D74: 46264 | E74: =IFERROR(IF(OR($A74="",$A74="Model",LEFT($A74,5)="Markt"),"",IF(AND($C74<=E$3+6,$D74>=E$3),"■","")),"") -> ■ | F74: =IFERROR(IF(OR($A74="",$A74="Model",LEFT($A74,5)="Markt"),"",IF(AND($C74<=F$3+6,$D74>=F$3),"■","")),"") -> ■ | G74: =IFERROR(IF(OR($A74="",$A74="Model",LEFT($A74,5)="Markt"),"",IF(AND($C74<=G$3+6,$D74>=G$3),"■","")),"") -> ■ | H74: =IFERROR(IF(OR($A74="",$A74="Model",LEFT($A74,5)="Markt"),"",IF(AND($C74<=H$3+6,$D74>=H$3),"■","")),"") -> ■ | I74: =IFERROR(IF(OR($A74="",$A74="Model",LEFT($A74,5)="Markt"),"",IF(AND($C74<=I$3+6,$D74>=I$3),"■","")),"") -> ■ | J74: =IFERROR(IF(OR($A74="",$A74="Model",LEFT($A74,5)="Markt"),"",IF(AND($C74<=J$3+6,$D74>=J$3),"■","")),"") -> ■ | K74: =IFERROR(IF(OR($A74="",$A74="Model",LEFT($A74,5)="Markt"),"",IF(AND($C74<=K$3+6,$D74>=K$3),"■","")),"") -> ■ | L74: =IFERROR(IF(OR($A74="",$A74="Model",LEFT($A74,5)="Markt"),"",IF(AND($C74<=L$3+6,$D74>=L$3),"■","")),"") -> ■ | ... V74: =IFERROR(IF(OR($A74="",$A74="Model",LEFT($A74,5)="Markt"),"",IF(AND($C74<=V$3+6,$D74>=V$3),"■","")),"") -> ■ | X74: Cayenne E4 | Y74: 20168871_20168871_POR_CAY_SUV_CEE_T1_NU_EUR_2026-02-28_2026-09-29_LOCAL-DCOPROGRAMMATICCAYENNEELECTRIC-CAYENNE | Z74: 46082 | AA74: 46294 | AB74: =IF(AND($Z74<=(AB$3+6),$AA74>=AB$3),"■","") -> ■ | AC74: =IF(AND($Z74<=(AC$3+6),$AA74>=AC$3),"■","") -> ■ | AD74: =IF(AND($Z74<=(AD$3+6),$AA74>=AD$3),"■","") -> ■ | AE74: =IF(AND($Z74<=(AE$3+6),$AA74>=AE$3),"■","") -> ■ | AF74: =IF(AND($Z74<=(AF$3+6),$AA74>=AF$3),"■","") -> ■ | AG74: =IF(AND($Z74<=(AG$3+6),$AA74>=AG$3),"■","") -> ■ | AH74: =IF(AND($Z74<=(AH$3+6),$AA74>=AH$3),"■","") -> ■ | AI74: =IF(AND($Z74<=(AI$3+6),$AA74>=AI$3),"■","") -> ■ | ... AS74: =IF(AND($Z74<=(AS$3+6),$AA74>=AS$3),"■","") -> ■ | AT74: Programmatic | AU74: Turkey budget: 672,888 CZK | AV74: Configuration | AW74: Turkey website visitors and car configurator page visitors / Auto enthusiasts
A75: Macan BEV | B75: Paid Social | C75: 46204 | D75: 46264 | E75: =IFERROR(IF(OR($A75="",$A75="Model",LEFT($A75,5)="Markt"),"",IF(AND($C75<=E$3+6,$D75>=E$3),"■","")),"") | F75: =IFERROR(IF(OR($A75="",$A75="Model",LEFT($A75,5)="Markt"),"",IF(AND($C75<=F$3+6,$D75>=F$3),"■","")),"") | G75: =IFERROR(IF(OR($A75="",$A75="Model",LEFT($A75,5)="Markt"),"",IF(AND($C75<=G$3+6,$D75>=G$3),"■","")),"") | H75: =IFERROR(IF(OR($A75="",$A75="Model",LEFT($A75,5)="Markt"),"",IF(AND($C75<=H$3+6,$D75>=H$3),"■","")),"") | I75: =IFERROR(IF(OR($A75="",$A75="Model",LEFT($A75,5)="Markt"),"",IF(AND($C75<=I$3+6,$D75>=I$3),"■","")),"") | J75: =IFERROR(IF(OR($A75="",$A75="Model",LEFT($A75,5)="Markt"),"",IF(AND($C75<=J$3+6,$D75>=J$3),"■","")),"") | K75: =IFERROR(IF(OR($A75="",$A75="Model",LEFT($A75,5)="Markt"),"",IF(AND($C75<=K$3+6,$D75>=K$3),"■","")),"") | L75: =IFERROR(IF(OR($A75="",$A75="Model",LEFT($A75,5)="Markt"),"",IF(AND($C75<=L$3+6,$D75>=L$3),"■","")),"") | ... V75: =IFERROR(IF(OR($A75="",$A75="Model",LEFT($A75,5)="Markt"),"",IF(AND($C75<=V$3+6,$D75>=V$3),"■","")),"") -> ■
A76: Cayenne E3 II | B76: Google Ads | C76: 46174 | D76: 46264 | E76: =IFERROR(IF(OR($A76="",$A76="Model",LEFT($A76,5)="Markt"),"",IF(AND($C76<=E$3+6,$D76>=E$3),"■","")),"") | F76: =IFERROR(IF(OR($A76="",$A76="Model",LEFT($A76,5)="Markt"),"",IF(AND($C76<=F$3+6,$D76>=F$3),"■","")),"") | G76: =IFERROR(IF(OR($A76="",$A76="Model",LEFT($A76,5)="Markt"),"",IF(AND($C76<=G$3+6,$D76>=G$3),"■","")),"") | H76: =IFERROR(IF(OR($A76="",$A76="Model",LEFT($A76,5)="Markt"),"",IF(AND($C76<=H$3+6,$D76>=H$3),"■","")),"") | I76: =IFERROR(IF(OR($A76="",$A76="Model",LEFT($A76,5)="Markt"),"",IF(AND($C76<=I$3+6,$D76>=I$3),"■","")),"") | J76: =IFERROR(IF(OR($A76="",$A76="Model",LEFT($A76,5)="Markt"),"",IF(AND($C76<=J$3+6,$D76>=J$3),"■","")),"") -> ■ | K76: =IFERROR(IF(OR($A76="",$A76="Model",LEFT($A76,5)="Markt"),"",IF(AND($C76<=K$3+6,$D76>=K$3),"■","")),"") -> ■ | L76: =IFERROR(IF(OR($A76="",$A76="Model",LEFT($A76,5)="Markt"),"",IF(AND($C76<=L$3+6,$D76>=L$3),"■","")),"") -> ■ | ... V76: =IFERROR(IF(OR($A76="",$A76="Model",LEFT($A76,5)="Markt"),"",IF(AND($C76<=V$3+6,$D76>=V$3),"■","")),"") -> ■
A77: Cayenne E3 II | B77: META Inventory Ads | C77: 46143 | D77: 46264 | E77: =IFERROR(IF(OR($A77="",$A77="Model",LEFT($A77,5)="Markt"),"",IF(AND($C77<=E$3+6,$D77>=E$3),"■","")),"") -> ■ | F77: =IFERROR(IF(OR($A77="",$A77="Model",LEFT($A77,5)="Markt"),"",IF(AND($C77<=F$3+6,$D77>=F$3),"■","")),"") -> ■ | G77: =IFERROR(IF(OR($A77="",$A77="Model",LEFT($A77,5)="Markt"),"",IF(AND($C77<=G$3+6,$D77>=G$3),"■","")),"") -> ■ | H77: =IFERROR(IF(OR($A77="",$A77="Model",LEFT($A77,5)="Markt"),"",IF(AND($C77<=H$3+6,$D77>=H$3),"■","")),"") -> ■ | I77: =IFERROR(IF(OR($A77="",$A77="Model",LEFT($A77,5)="Markt"),"",IF(AND($C77<=I$3+6,$D77>=I$3),"■","")),"") -> ■ | J77: =IFERROR(IF(OR($A77="",$A77="Model",LEFT($A77,5)="Markt"),"",IF(AND($C77<=J$3+6,$D77>=J$3),"■","")),"") -> ■ | K77: =IFERROR(IF(OR($A77="",$A77="Model",LEFT($A77,5)="Markt"),"",IF(AND($C77<=K$3+6,$D77>=K$3),"■","")),"") -> ■ | L77: =IFERROR(IF(OR($A77="",$A77="Model",LEFT($A77,5)="Markt"),"",IF(AND($C77<=L$3+6,$D77>=L$3),"■","")),"") -> ■ | ... V77: =IFERROR(IF(OR($A77="",$A77="Model",LEFT($A77,5)="Markt"),"",IF(AND($C77<=V$3+6,$D77>=V$3),"■","")),"") -> ■
A78: Cayenne E3 II | B78: Paid Social | C78: 46204 | D78: 46264 | E78: =IFERROR(IF(OR($A78="",$A78="Model",LEFT($A78,5)="Markt"),"",IF(AND($C78<=E$3+6,$D78>=E$3),"■","")),"") | F78: =IFERROR(IF(OR($A78="",$A78="Model",LEFT($A78,5)="Markt"),"",IF(AND($C78<=F$3+6,$D78>=F$3),"■","")),"") | G78: =IFERROR(IF(OR($A78="",$A78="Model",LEFT($A78,5)="Markt"),"",IF(AND($C78<=G$3+6,$D78>=G$3),"■","")),"") | H78: =IFERROR(IF(OR($A78="",$A78="Model",LEFT($A78,5)="Markt"),"",IF(AND($C78<=H$3+6,$D78>=H$3),"■","")),"") | I78: =IFERROR(IF(OR($A78="",$A78="Model",LEFT($A78,5)="Markt"),"",IF(AND($C78<=I$3+6,$D78>=I$3),"■","")),"") | J78: =IFERROR(IF(OR($A78="",$A78="Model",LEFT($A78,5)="Markt"),"",IF(AND($C78<=J$3+6,$D78>=J$3),"■","")),"") | K78: =IFERROR(IF(OR($A78="",$A78="Model",LEFT($A78,5)="Markt"),"",IF(AND($C78<=K$3+6,$D78>=K$3),"■","")),"") | L78: =IFERROR(IF(OR($A78="",$A78="Model",LEFT($A78,5)="Markt"),"",IF(AND($C78<=L$3+6,$D78>=L$3),"■","")),"") | ... V78: =IFERROR(IF(OR($A78="",$A78="Model",LEFT($A78,5)="Markt"),"",IF(AND($C78<=V$3+6,$D78>=V$3),"■","")),"") -> ■
A79: Cayenne E4 | B79: Google Ads | C79: 46143 | D79: 46264 | E79: =IFERROR(IF(OR($A79="",$A79="Model",LEFT($A79,5)="Markt"),"",IF(AND($C79<=E$3+6,$D79>=E$3),"■","")),"") -> ■ | F79: =IFERROR(IF(OR($A79="",$A79="Model",LEFT($A79,5)="Markt"),"",IF(AND($C79<=F$3+6,$D79>=F$3),"■","")),"") -> ■ | G79: =IFERROR(IF(OR($A79="",$A79="Model",LEFT($A79,5)="Markt"),"",IF(AND($C79<=G$3+6,$D79>=G$3),"■","")),"") -> ■ | H79: =IFERROR(IF(OR($A79="",$A79="Model",LEFT($A79,5)="Markt"),"",IF(AND($C79<=H$3+6,$D79>=H$3),"■","")),"") -> ■ | I79: =IFERROR(IF(OR($A79="",$A79="Model",LEFT($A79,5)="Markt"),"",IF(AND($C79<=I$3+6,$D79>=I$3),"■","")),"") -> ■ | J79: =IFERROR(IF(OR($A79="",$A79="Model",LEFT($A79,5)="Markt"),"",IF(AND($C79<=J$3+6,$D79>=J$3),"■","")),"") -> ■ | K79: =IFERROR(IF(OR($A79="",$A79="Model",LEFT($A79,5)="Markt"),"",IF(AND($C79<=K$3+6,$D79>=K$3),"■","")),"") -> ■ | L79: =IFERROR(IF(OR($A79="",$A79="Model",LEFT($A79,5)="Markt"),"",IF(AND($C79<=L$3+6,$D79>=L$3),"■","")),"") -> ■ | ... V79: =IFERROR(IF(OR($A79="",$A79="Model",LEFT($A79,5)="Markt"),"",IF(AND($C79<=V$3+6,$D79>=V$3),"■","")),"") -> ■
A80: Cayenne E4 | B80: META Inventory Ads | C80: 46204 | D80: 46264 | E80: =IFERROR(IF(OR($A80="",$A80="Model",LEFT($A80,5)="Markt"),"",IF(AND($C80<=E$3+6,$D80>=E$3),"■","")),"") | F80: =IFERROR(IF(OR($A80="",$A80="Model",LEFT($A80,5)="Markt"),"",IF(AND($C80<=F$3+6,$D80>=F$3),"■","")),"") | G80: =IFERROR(IF(OR($A80="",$A80="Model",LEFT($A80,5)="Markt"),"",IF(AND($C80<=G$3+6,$D80>=G$3),"■","")),"") | H80: =IFERROR(IF(OR($A80="",$A80="Model",LEFT($A80,5)="Markt"),"",IF(AND($C80<=H$3+6,$D80>=H$3),"■","")),"") | I80: =IFERROR(IF(OR($A80="",$A80="Model",LEFT($A80,5)="Markt"),"",IF(AND($C80<=I$3+6,$D80>=I$3),"■","")),"") | J80: =IFERROR(IF(OR($A80="",$A80="Model",LEFT($A80,5)="Markt"),"",IF(AND($C80<=J$3+6,$D80>=J$3),"■","")),"") | K80: =IFERROR(IF(OR($A80="",$A80="Model",LEFT($A80,5)="Markt"),"",IF(AND($C80<=K$3+6,$D80>=K$3),"■","")),"") | L80: =IFERROR(IF(OR($A80="",$A80="Model",LEFT($A80,5)="Markt"),"",IF(AND($C80<=L$3+6,$D80>=L$3),"■","")),"") | ... V80: =IFERROR(IF(OR($A80="",$A80="Model",LEFT($A80,5)="Markt"),"",IF(AND($C80<=V$3+6,$D80>=V$3),"■","")),"") -> ■
A81: Cayenne E4 | B81: Paid Social | C81: 46204 | D81: 46264 | E81: =IFERROR(IF(OR($A81="",$A81="Model",LEFT($A81,5)="Markt"),"",IF(AND($C81<=E$3+6,$D81>=E$3),"■","")),"") | F81: =IFERROR(IF(OR($A81="",$A81="Model",LEFT($A81,5)="Markt"),"",IF(AND($C81<=F$3+6,$D81>=F$3),"■","")),"") | G81: =IFERROR(IF(OR($A81="",$A81="Model",LEFT($A81,5)="Markt"),"",IF(AND($C81<=G$3+6,$D81>=G$3),"■","")),"") | H81: =IFERROR(IF(OR($A81="",$A81="Model",LEFT($A81,5)="Markt"),"",IF(AND($C81<=H$3+6,$D81>=H$3),"■","")),"") | I81: =IFERROR(IF(OR($A81="",$A81="Model",LEFT($A81,5)="Markt"),"",IF(AND($C81<=I$3+6,$D81>=I$3),"■","")),"") | J81: =IFERROR(IF(OR($A81="",$A81="Model",LEFT($A81,5)="Markt"),"",IF(AND($C81<=J$3+6,$D81>=J$3),"■","")),"") | K81: =IFERROR(IF(OR($A81="",$A81="Model",LEFT($A81,5)="Markt"),"",IF(AND($C81<=K$3+6,$D81>=K$3),"■","")),"") | L81: =IFERROR(IF(OR($A81="",$A81="Model",LEFT($A81,5)="Markt"),"",IF(AND($C81<=L$3+6,$D81>=L$3),"■","")),"") | ... V81: =IFERROR(IF(OR($A81="",$A81="Model",LEFT($A81,5)="Markt"),"",IF(AND($C81<=V$3+6,$D81>=V$3),"■","")),"") -> ■
A82: Markt: PCL | X82: Markt: PCL (Survey) | AT82: {=_xlfn.LET(_xlpm.mL,A82,_xlpm.aL,B82,_xlpm.mR,X82,_xlpm.aR,Y82,_xlpm.useR,AND(_xlpm.mR<>"",_xlpm.mR<>"Model",LEFT(_xlpm.mR,6)<>"Markt:"),_xlpm.m,IF(_xlpm.useR,_xlpm.mR,_xlpm.mL),_xlpm.a,IF(_xlpm.useR,_xlpm.aR,_xlpm.aL),_xlpm.rng,IF(_xlpm.useR,X$1:X82,A$1:A82),IF(OR(_xlpm.m="",_xlpm.m="Model",LEFT(_xlpm.m,6)="Markt:"),"",_xlfn.LET(_xlpm.mkt,LOOKUP(2,1/(LEFT(_xlpm.rng,6)="Markt:"),_xlpm.rng),_xlpm.mktNameRaw,TRIM(MID(_xlpm.mkt,FIND(":",_xlpm.mkt)+1,99)),_xlpm.mktName,TRIM(SUBSTITUTE(_xlpm.mktNameRaw,"(Survey)","")),_xlfn.XLOOKUP(_xlpm.mktName&"|"&SUBSTITUTE(_xlpm.m," ","")&"|"&_xlpm.a,tblMassnahmen[Key],tblMassnahmen[Kanal],""))))} | AU82: {=_xlfn.LET(_xlpm.mL,A82,_xlpm.aL,B82,_xlpm.mR,X82,_xlpm.aR,Y82,_xlpm.useR,AND(_xlpm.mR<>"",_xlpm.mR<>"Model",LEFT(_xlpm.mR,6)<>"Markt:"),_xlpm.m,IF(_xlpm.useR,_xlpm.mR,_xlpm.mL),_xlpm.a,IF(_xlpm.useR,_xlpm.aR,_xlpm.aL),_xlpm.rng,IF(_xlpm.useR,X$1:X82,A$1:A82),IF(OR(_xlpm.m="",_xlpm.m="Model",LEFT(_xlpm.m,6)="Markt:"),"",_xlfn.LET(_xlpm.mkt,LOOKUP(2,1/(LEFT(_xlpm.rng,6)="Markt:"),_xlpm.rng),_xlpm.mktNameRaw,TRIM(MID(_xlpm.mkt,FIND(":",_xlpm.mkt)+1,99)),_xlpm.mktName,TRIM(SUBSTITUTE(_xlpm.mktNameRaw,"(Survey)","")),_xlfn.XLOOKUP(_xlpm.mktName&"|"&SUBSTITUTE(_xlpm.m," ","")&"|"&_xlpm.a,tblMassnahmen[Key],tblMassnahmen[Budget],""))))} | AV82: {=_xlfn.LET(_xlpm.mL,A82,_xlpm.aL,B82,_xlpm.mR,X82,_xlpm.aR,Y82,_xlpm.useR,AND(_xlpm.mR<>"",_xlpm.mR<>"Model",LEFT(_xlpm.mR,6)<>"Markt:"),_xlpm.m,IF(_xlpm.useR,_xlpm.mR,_xlpm.mL),_xlpm.a,IF(_xlpm.useR,_xlpm.aR,_xlpm.aL),_xlpm.rng,IF(_xlpm.useR,X$1:X82,A$1:A82),IF(OR(_xlpm.m="",_xlpm.m="Model",LEFT(_xlpm.m,6)="Markt:"),"",_xlfn.LET(_xlpm.mkt,LOOKUP(2,1/(LEFT(_xlpm.rng,6)="Markt:"),_xlpm.rng),_xlpm.mktNameRaw,TRIM(MID(_xlpm.mkt,FIND(":",_xlpm.mkt)+1,99)),_xlpm.mktName,TRIM(SUBSTITUTE(_xlpm.mktNameRaw,"(Survey)","")),_xlfn.XLOOKUP(_xlpm.mktName&"|"&SUBSTITUTE(_xlpm.m," ","")&"|"&_xlpm.a,tblMassnahmen[Key],tblMassnahmen[KPI],""))))}
A83: Model | B83: CTG Measure | C83: Start | D83: Ende | E83: CW18 | F83: CW19 | G83: CW20 | H83: CW21 | I83: CW22 | J83: CW23 | K83: CW24 | L83: CW25 | M83: CW26 | N83: CW27 | O83: CW28 | P83: CW29 | Q83: CW30 | R83: CW31 | S83: CW32 | T83: CW33 | U83: CW34 | V83: CW35 | X83: Model | Y83: Local Measure | Z83: Start | AA83: Ende | AB83: CW18 | AC83: CW19 | AD83: CW20 | AE83: CW21 | AF83: CW22 | AG83: CW23 | AH83: CW24 | AI83: CW25 | AJ83: CW26 | AK83: CW27 | AL83: CW28 | AM83: CW29 | AN83: CW30 | AO83: CW31 | AP83: CW32 | AQ83: CW33 | AR83: CW34 | AS83: CW35 | AT83: Channel | AU83: Budget | AV83: KPI | AW83: Audience
A84: Macan BEV | B84: Google Ads | C84: 46143 | D84: 46264 | E84: =IFERROR(IF(OR($A84="",$A84="Model",LEFT($A84,5)="Markt"),"",IF(AND($C84<=E$3+6,$D84>=E$3),"■","")),"") -> ■ | F84: =IFERROR(IF(OR($A84="",$A84="Model",LEFT($A84,5)="Markt"),"",IF(AND($C84<=F$3+6,$D84>=F$3),"■","")),"") -> ■ | G84: =IFERROR(IF(OR($A84="",$A84="Model",LEFT($A84,5)="Markt"),"",IF(AND($C84<=G$3+6,$D84>=G$3),"■","")),"") -> ■ | H84: =IFERROR(IF(OR($A84="",$A84="Model",LEFT($A84,5)="Markt"),"",IF(AND($C84<=H$3+6,$D84>=H$3),"■","")),"") -> ■ | I84: =IFERROR(IF(OR($A84="",$A84="Model",LEFT($A84,5)="Markt"),"",IF(AND($C84<=I$3+6,$D84>=I$3),"■","")),"") -> ■ | J84: =IFERROR(IF(OR($A84="",$A84="Model",LEFT($A84,5)="Markt"),"",IF(AND($C84<=J$3+6,$D84>=J$3),"■","")),"") -> ■ | K84: =IFERROR(IF(OR($A84="",$A84="Model",LEFT($A84,5)="Markt"),"",IF(AND($C84<=K$3+6,$D84>=K$3),"■","")),"") -> ■ | L84: =IFERROR(IF(OR($A84="",$A84="Model",LEFT($A84,5)="Markt"),"",IF(AND($C84<=L$3+6,$D84>=L$3),"■","")),"") -> ■ | ... V84: =IFERROR(IF(OR($A84="",$A84="Model",LEFT($A84,5)="Markt"),"",IF(AND($C84<=V$3+6,$D84>=V$3),"■","")),"") -> ■ | X84: Macan H2 | Y84: Macan Family (ID: 20053156) | Z84: 46131 | AA84: 46233 | AB84: =IF(AND($Z84<=(AB$3+6),$AA84>=AB$3),"■","") -> ■ | AC84: =IF(AND($Z84<=(AC$3+6),$AA84>=AC$3),"■","") -> ■ | AD84: =IF(AND($Z84<=(AD$3+6),$AA84>=AD$3),"■","") -> ■ | AE84: =IF(AND($Z84<=(AE$3+6),$AA84>=AE$3),"■","") -> ■ | AF84: =IF(AND($Z84<=(AF$3+6),$AA84>=AF$3),"■","") -> ■ | AG84: =IF(AND($Z84<=(AG$3+6),$AA84>=AG$3),"■","") -> ■ | AH84: =IF(AND($Z84<=(AH$3+6),$AA84>=AH$3),"■","") -> ■ | AI84: =IF(AND($Z84<=(AI$3+6),$AA84>=AI$3),"■","") -> ■ | ... AS84: =IF(AND($Z84<=(AS$3+6),$AA84>=AS$3),"■","") | AT84: Social,Search,Programmatic | AU84: $1M CAD | AV84: Impressions,Dealer contact form submitted (DCFS),Others, PF VDP view, Vehicle list saved, Contact form start, CPA, CPC | AW84: Contextually target Conquesting EV intenders retarget META Ad Engagers Website Visitors and Initiate Checkout and View Content and Search Conversions Porsche Macan BEV but excl Lead Conversion in the last ninety days / Brand protect and conquest Luxury and EV intenders
A85: Macan BEV | B85: Google Inventory Ads | C85: 46143 | D85: 46264 | E85: =IFERROR(IF(OR($A85="",$A85="Model",LEFT($A85,5)="Markt"),"",IF(AND($C85<=E$3+6,$D85>=E$3),"■","")),"") -> ■ | F85: =IFERROR(IF(OR($A85="",$A85="Model",LEFT($A85,5)="Markt"),"",IF(AND($C85<=F$3+6,$D85>=F$3),"■","")),"") -> ■ | G85: =IFERROR(IF(OR($A85="",$A85="Model",LEFT($A85,5)="Markt"),"",IF(AND($C85<=G$3+6,$D85>=G$3),"■","")),"") -> ■ | H85: =IFERROR(IF(OR($A85="",$A85="Model",LEFT($A85,5)="Markt"),"",IF(AND($C85<=H$3+6,$D85>=H$3),"■","")),"") -> ■ | I85: =IFERROR(IF(OR($A85="",$A85="Model",LEFT($A85,5)="Markt"),"",IF(AND($C85<=I$3+6,$D85>=I$3),"■","")),"") -> ■ | J85: =IFERROR(IF(OR($A85="",$A85="Model",LEFT($A85,5)="Markt"),"",IF(AND($C85<=J$3+6,$D85>=J$3),"■","")),"") -> ■ | K85: =IFERROR(IF(OR($A85="",$A85="Model",LEFT($A85,5)="Markt"),"",IF(AND($C85<=K$3+6,$D85>=K$3),"■","")),"") -> ■ | L85: =IFERROR(IF(OR($A85="",$A85="Model",LEFT($A85,5)="Markt"),"",IF(AND($C85<=L$3+6,$D85>=L$3),"■","")),"") -> ■ | ... V85: =IFERROR(IF(OR($A85="",$A85="Model",LEFT($A85,5)="Markt"),"",IF(AND($C85<=V$3+6,$D85>=V$3),"■","")),"") -> ■ | X85: Cayenne E3 II | Y85: Cayenne Family (ID: 20053155) | Z85: 46138 | AA85: 46325 | AB85: =IF(AND($Z85<=(AB$3+6),$AA85>=AB$3),"■","") -> ■ | AC85: =IF(AND($Z85<=(AC$3+6),$AA85>=AC$3),"■","") -> ■ | AD85: =IF(AND($Z85<=(AD$3+6),$AA85>=AD$3),"■","") -> ■ | AE85: =IF(AND($Z85<=(AE$3+6),$AA85>=AE$3),"■","") -> ■ | AF85: =IF(AND($Z85<=(AF$3+6),$AA85>=AF$3),"■","") -> ■ | AG85: =IF(AND($Z85<=(AG$3+6),$AA85>=AG$3),"■","") -> ■ | AH85: =IF(AND($Z85<=(AH$3+6),$AA85>=AH$3),"■","") -> ■ | AI85: =IF(AND($Z85<=(AI$3+6),$AA85>=AI$3),"■","") -> ■ | ... AS85: =IF(AND($Z85<=(AS$3+6),$AA85>=AS$3),"■","") -> ■ | AT85: Social,Search,Programmatic | AU85: $1.5M CAD | AV85: Click Through Rate (CTR),Dealer contact form submitted (DCFS),Others, PF VDP view, PF save listing, Cost per acquisition, CPC | AW85: Retarget audience who have not converted from Cayenne Electric also conquest and custom / Luxury car enthusiasts and EV intenders and affinity luxury
A86: Macan BEV | B86: META Inventory Ads | C86: 46143 | D86: 46264 | E86: =IFERROR(IF(OR($A86="",$A86="Model",LEFT($A86,5)="Markt"),"",IF(AND($C86<=E$3+6,$D86>=E$3),"■","")),"") -> ■ | F86: =IFERROR(IF(OR($A86="",$A86="Model",LEFT($A86,5)="Markt"),"",IF(AND($C86<=F$3+6,$D86>=F$3),"■","")),"") -> ■ | G86: =IFERROR(IF(OR($A86="",$A86="Model",LEFT($A86,5)="Markt"),"",IF(AND($C86<=G$3+6,$D86>=G$3),"■","")),"") -> ■ | H86: =IFERROR(IF(OR($A86="",$A86="Model",LEFT($A86,5)="Markt"),"",IF(AND($C86<=H$3+6,$D86>=H$3),"■","")),"") -> ■ | I86: =IFERROR(IF(OR($A86="",$A86="Model",LEFT($A86,5)="Markt"),"",IF(AND($C86<=I$3+6,$D86>=I$3),"■","")),"") -> ■ | J86: =IFERROR(IF(OR($A86="",$A86="Model",LEFT($A86,5)="Markt"),"",IF(AND($C86<=J$3+6,$D86>=J$3),"■","")),"") -> ■ | K86: =IFERROR(IF(OR($A86="",$A86="Model",LEFT($A86,5)="Markt"),"",IF(AND($C86<=K$3+6,$D86>=K$3),"■","")),"") -> ■ | L86: =IFERROR(IF(OR($A86="",$A86="Model",LEFT($A86,5)="Markt"),"",IF(AND($C86<=L$3+6,$D86>=L$3),"■","")),"") -> ■ | ... V86: =IFERROR(IF(OR($A86="",$A86="Model",LEFT($A86,5)="Markt"),"",IF(AND($C86<=V$3+6,$D86>=V$3),"■","")),"") -> ■ | X86: Cayenne E4 | Y86: E4 Launch (ID: 20053154) | Z86: 46096 | AA86: 46141 | AB86: =IF(AND($Z86<=(AB$3+6),$AA86>=AB$3),"■","") -> ■ | AC86: =IF(AND($Z86<=(AC$3+6),$AA86>=AC$3),"■","") | AD86: =IF(AND($Z86<=(AD$3+6),$AA86>=AD$3),"■","") | AE86: =IF(AND($Z86<=(AE$3+6),$AA86>=AE$3),"■","") | AF86: =IF(AND($Z86<=(AF$3+6),$AA86>=AF$3),"■","") | AG86: =IF(AND($Z86<=(AG$3+6),$AA86>=AG$3),"■","") | AH86: =IF(AND($Z86<=(AH$3+6),$AA86>=AH$3),"■","") | AI86: =IF(AND($Z86<=(AI$3+6),$AA86>=AI$3),"■","") | ... AS86: =IF(AND($Z86<=(AS$3+6),$AA86>=AS$3),"■","") | AT86: Social,Search,Programmatic,Other Online Channel, CTV, DOOH | AU86: $460K CAD | AV86: Impressions,Cost per Million (CPM),Click Through Rate (CTR),Others, Cost per Reach, Cost per video view, | AW86: PRIZM Suburban middle aged families with an average household income x Urban older and mature families with an average household income of x and conquest / luxury SUV owners intenders
A87: Macan BEV | B87: Paid Social | C87: 46204 | D87: 46264 | E87: =IFERROR(IF(OR($A87="",$A87="Model",LEFT($A87,5)="Markt"),"",IF(AND($C87<=E$3+6,$D87>=E$3),"■","")),"") | F87: =IFERROR(IF(OR($A87="",$A87="Model",LEFT($A87,5)="Markt"),"",IF(AND($C87<=F$3+6,$D87>=F$3),"■","")),"") | G87: =IFERROR(IF(OR($A87="",$A87="Model",LEFT($A87,5)="Markt"),"",IF(AND($C87<=G$3+6,$D87>=G$3),"■","")),"") | H87: =IFERROR(IF(OR($A87="",$A87="Model",LEFT($A87,5)="Markt"),"",IF(AND($C87<=H$3+6,$D87>=H$3),"■","")),"") | I87: =IFERROR(IF(OR($A87="",$A87="Model",LEFT($A87,5)="Markt"),"",IF(AND($C87<=I$3+6,$D87>=I$3),"■","")),"") | J87: =IFERROR(IF(OR($A87="",$A87="Model",LEFT($A87,5)="Markt"),"",IF(AND($C87<=J$3+6,$D87>=J$3),"■","")),"") | K87: =IFERROR(IF(OR($A87="",$A87="Model",LEFT($A87,5)="Markt"),"",IF(AND($C87<=K$3+6,$D87>=K$3),"■","")),"") | L87: =IFERROR(IF(OR($A87="",$A87="Model",LEFT($A87,5)="Markt"),"",IF(AND($C87<=L$3+6,$D87>=L$3),"■","")),"") | ... V87: =IFERROR(IF(OR($A87="",$A87="Model",LEFT($A87,5)="Markt"),"",IF(AND($C87<=V$3+6,$D87>=V$3),"■","")),"") -> ■
A88: Cayenne E3 II | B88: Google Ads | C88: 46143 | D88: 46264 | E88: =IFERROR(IF(OR($A88="",$A88="Model",LEFT($A88,5)="Markt"),"",IF(AND($C88<=E$3+6,$D88>=E$3),"■","")),"") -> ■ | F88: =IFERROR(IF(OR($A88="",$A88="Model",LEFT($A88,5)="Markt"),"",IF(AND($C88<=F$3+6,$D88>=F$3),"■","")),"") -> ■ | G88: =IFERROR(IF(OR($A88="",$A88="Model",LEFT($A88,5)="Markt"),"",IF(AND($C88<=G$3+6,$D88>=G$3),"■","")),"") -> ■ | H88: =IFERROR(IF(OR($A88="",$A88="Model",LEFT($A88,5)="Markt"),"",IF(AND($C88<=H$3+6,$D88>=H$3),"■","")),"") -> ■ | I88: =IFERROR(IF(OR($A88="",$A88="Model",LEFT($A88,5)="Markt"),"",IF(AND($C88<=I$3+6,$D88>=I$3),"■","")),"") -> ■ | J88: =IFERROR(IF(OR($A88="",$A88="Model",LEFT($A88,5)="Markt"),"",IF(AND($C88<=J$3+6,$D88>=J$3),"■","")),"") -> ■ | K88: =IFERROR(IF(OR($A88="",$A88="Model",LEFT($A88,5)="Markt"),"",IF(AND($C88<=K$3+6,$D88>=K$3),"■","")),"") -> ■ | L88: =IFERROR(IF(OR($A88="",$A88="Model",LEFT($A88,5)="Markt"),"",IF(AND($C88<=L$3+6,$D88>=L$3),"■","")),"") -> ■ | ... V88: =IFERROR(IF(OR($A88="",$A88="Model",LEFT($A88,5)="Markt"),"",IF(AND($C88<=V$3+6,$D88>=V$3),"■","")),"") -> ■
A89: Cayenne E3 II | B89: Google Inventory Ads | C89: 46143 | D89: 46264 | E89: =IFERROR(IF(OR($A89="",$A89="Model",LEFT($A89,5)="Markt"),"",IF(AND($C89<=E$3+6,$D89>=E$3),"■","")),"") -> ■ | F89: =IFERROR(IF(OR($A89="",$A89="Model",LEFT($A89,5)="Markt"),"",IF(AND($C89<=F$3+6,$D89>=F$3),"■","")),"") -> ■ | G89: =IFERROR(IF(OR($A89="",$A89="Model",LEFT($A89,5)="Markt"),"",IF(AND($C89<=G$3+6,$D89>=G$3),"■","")),"") -> ■ | H89: =IFERROR(IF(OR($A89="",$A89="Model",LEFT($A89,5)="Markt"),"",IF(AND($C89<=H$3+6,$D89>=H$3),"■","")),"") -> ■ | I89: =IFERROR(IF(OR($A89="",$A89="Model",LEFT($A89,5)="Markt"),"",IF(AND($C89<=I$3+6,$D89>=I$3),"■","")),"") -> ■ | J89: =IFERROR(IF(OR($A89="",$A89="Model",LEFT($A89,5)="Markt"),"",IF(AND($C89<=J$3+6,$D89>=J$3),"■","")),"") -> ■ | K89: =IFERROR(IF(OR($A89="",$A89="Model",LEFT($A89,5)="Markt"),"",IF(AND($C89<=K$3+6,$D89>=K$3),"■","")),"") -> ■ | L89: =IFERROR(IF(OR($A89="",$A89="Model",LEFT($A89,5)="Markt"),"",IF(AND($C89<=L$3+6,$D89>=L$3),"■","")),"") -> ■ | ... V89: =IFERROR(IF(OR($A89="",$A89="Model",LEFT($A89,5)="Markt"),"",IF(AND($C89<=V$3+6,$D89>=V$3),"■","")),"") -> ■
A90: Cayenne E3 II | B90: META Inventory Ads | C90: 46143 | D90: 46264 | E90: =IFERROR(IF(OR($A90="",$A90="Model",LEFT($A90,5)="Markt"),"",IF(AND($C90<=E$3+6,$D90>=E$3),"■","")),"") -> ■ | F90: =IFERROR(IF(OR($A90="",$A90="Model",LEFT($A90,5)="Markt"),"",IF(AND($C90<=F$3+6,$D90>=F$3),"■","")),"") -> ■ | G90: =IFERROR(IF(OR($A90="",$A90="Model",LEFT($A90,5)="Markt"),"",IF(AND($C90<=G$3+6,$D90>=G$3),"■","")),"") -> ■ | H90: =IFERROR(IF(OR($A90="",$A90="Model",LEFT($A90,5)="Markt"),"",IF(AND($C90<=H$3+6,$D90>=H$3),"■","")),"") -> ■ | I90: =IFERROR(IF(OR($A90="",$A90="Model",LEFT($A90,5)="Markt"),"",IF(AND($C90<=I$3+6,$D90>=I$3),"■","")),"") -> ■ | J90: =IFERROR(IF(OR($A90="",$A90="Model",LEFT($A90,5)="Markt"),"",IF(AND($C90<=J$3+6,$D90>=J$3),"■","")),"") -> ■ | K90: =IFERROR(IF(OR($A90="",$A90="Model",LEFT($A90,5)="Markt"),"",IF(AND($C90<=K$3+6,$D90>=K$3),"■","")),"") -> ■ | L90: =IFERROR(IF(OR($A90="",$A90="Model",LEFT($A90,5)="Markt"),"",IF(AND($C90<=L$3+6,$D90>=L$3),"■","")),"") -> ■ | ... V90: =IFERROR(IF(OR($A90="",$A90="Model",LEFT($A90,5)="Markt"),"",IF(AND($C90<=V$3+6,$D90>=V$3),"■","")),"") -> ■
A91: Cayenne E3 II | B91: Paid Social | C91: 46204 | D91: 46264 | E91: =IFERROR(IF(OR($A91="",$A91="Model",LEFT($A91,5)="Markt"),"",IF(AND($C91<=E$3+6,$D91>=E$3),"■","")),"") | F91: =IFERROR(IF(OR($A91="",$A91="Model",LEFT($A91,5)="Markt"),"",IF(AND($C91<=F$3+6,$D91>=F$3),"■","")),"") | G91: =IFERROR(IF(OR($A91="",$A91="Model",LEFT($A91,5)="Markt"),"",IF(AND($C91<=G$3+6,$D91>=G$3),"■","")),"") | H91: =IFERROR(IF(OR($A91="",$A91="Model",LEFT($A91,5)="Markt"),"",IF(AND($C91<=H$3+6,$D91>=H$3),"■","")),"") | I91: =IFERROR(IF(OR($A91="",$A91="Model",LEFT($A91,5)="Markt"),"",IF(AND($C91<=I$3+6,$D91>=I$3),"■","")),"") | J91: =IFERROR(IF(OR($A91="",$A91="Model",LEFT($A91,5)="Markt"),"",IF(AND($C91<=J$3+6,$D91>=J$3),"■","")),"") | K91: =IFERROR(IF(OR($A91="",$A91="Model",LEFT($A91,5)="Markt"),"",IF(AND($C91<=K$3+6,$D91>=K$3),"■","")),"") | L91: =IFERROR(IF(OR($A91="",$A91="Model",LEFT($A91,5)="Markt"),"",IF(AND($C91<=L$3+6,$D91>=L$3),"■","")),"") | ... V91: =IFERROR(IF(OR($A91="",$A91="Model",LEFT($A91,5)="Markt"),"",IF(AND($C91<=V$3+6,$D91>=V$3),"■","")),"") -> ■
A92: Cayenne E4 | B92: Google Ads | C92: 46143 | D92: 46264 | E92: =IFERROR(IF(OR($A92="",$A92="Model",LEFT($A92,5)="Markt"),"",IF(AND($C92<=E$3+6,$D92>=E$3),"■","")),"") -> ■ | F92: =IFERROR(IF(OR($A92="",$A92="Model",LEFT($A92,5)="Markt"),"",IF(AND($C92<=F$3+6,$D92>=F$3),"■","")),"") -> ■ | G92: =IFERROR(IF(OR($A92="",$A92="Model",LEFT($A92,5)="Markt"),"",IF(AND($C92<=G$3+6,$D92>=G$3),"■","")),"") -> ■ | H92: =IFERROR(IF(OR($A92="",$A92="Model",LEFT($A92,5)="Markt"),"",IF(AND($C92<=H$3+6,$D92>=H$3),"■","")),"") -> ■ | I92: =IFERROR(IF(OR($A92="",$A92="Model",LEFT($A92,5)="Markt"),"",IF(AND($C92<=I$3+6,$D92>=I$3),"■","")),"") -> ■ | J92: =IFERROR(IF(OR($A92="",$A92="Model",LEFT($A92,5)="Markt"),"",IF(AND($C92<=J$3+6,$D92>=J$3),"■","")),"") -> ■ | K92: =IFERROR(IF(OR($A92="",$A92="Model",LEFT($A92,5)="Markt"),"",IF(AND($C92<=K$3+6,$D92>=K$3),"■","")),"") -> ■ | L92: =IFERROR(IF(OR($A92="",$A92="Model",LEFT($A92,5)="Markt"),"",IF(AND($C92<=L$3+6,$D92>=L$3),"■","")),"") -> ■ | ... V92: =IFERROR(IF(OR($A92="",$A92="Model",LEFT($A92,5)="Markt"),"",IF(AND($C92<=V$3+6,$D92>=V$3),"■","")),"") -> ■
A93: Cayenne E4 | B93: Google Inventory Ads | C93: 46204 | D93: 46264 | E93: =IFERROR(IF(OR($A93="",$A93="Model",LEFT($A93,5)="Markt"),"",IF(AND($C93<=E$3+6,$D93>=E$3),"■","")),"") | F93: =IFERROR(IF(OR($A93="",$A93="Model",LEFT($A93,5)="Markt"),"",IF(AND($C93<=F$3+6,$D93>=F$3),"■","")),"") | G93: =IFERROR(IF(OR($A93="",$A93="Model",LEFT($A93,5)="Markt"),"",IF(AND($C93<=G$3+6,$D93>=G$3),"■","")),"") | H93: =IFERROR(IF(OR($A93="",$A93="Model",LEFT($A93,5)="Markt"),"",IF(AND($C93<=H$3+6,$D93>=H$3),"■","")),"") | I93: =IFERROR(IF(OR($A93="",$A93="Model",LEFT($A93,5)="Markt"),"",IF(AND($C93<=I$3+6,$D93>=I$3),"■","")),"") | J93: =IFERROR(IF(OR($A93="",$A93="Model",LEFT($A93,5)="Markt"),"",IF(AND($C93<=J$3+6,$D93>=J$3),"■","")),"") | K93: =IFERROR(IF(OR($A93="",$A93="Model",LEFT($A93,5)="Markt"),"",IF(AND($C93<=K$3+6,$D93>=K$3),"■","")),"") | L93: =IFERROR(IF(OR($A93="",$A93="Model",LEFT($A93,5)="Markt"),"",IF(AND($C93<=L$3+6,$D93>=L$3),"■","")),"") | ... V93: =IFERROR(IF(OR($A93="",$A93="Model",LEFT($A93,5)="Markt"),"",IF(AND($C93<=V$3+6,$D93>=V$3),"■","")),"") -> ■
A94: Cayenne E4 | B94: META Inventory Ads | C94: 46204 | D94: 46264 | E94: =IFERROR(IF(OR($A94="",$A94="Model",LEFT($A94,5)="Markt"),"",IF(AND($C94<=E$3+6,$D94>=E$3),"■","")),"") | F94: =IFERROR(IF(OR($A94="",$A94="Model",LEFT($A94,5)="Markt"),"",IF(AND($C94<=F$3+6,$D94>=F$3),"■","")),"") | G94: =IFERROR(IF(OR($A94="",$A94="Model",LEFT($A94,5)="Markt"),"",IF(AND($C94<=G$3+6,$D94>=G$3),"■","")),"") | H94: =IFERROR(IF(OR($A94="",$A94="Model",LEFT($A94,5)="Markt"),"",IF(AND($C94<=H$3+6,$D94>=H$3),"■","")),"") | I94: =IFERROR(IF(OR($A94="",$A94="Model",LEFT($A94,5)="Markt"),"",IF(AND($C94<=I$3+6,$D94>=I$3),"■","")),"") | J94: =IFERROR(IF(OR($A94="",$A94="Model",LEFT($A94,5)="Markt"),"",IF(AND($C94<=J$3+6,$D94>=J$3),"■","")),"") | K94: =IFERROR(IF(OR($A94="",$A94="Model",LEFT($A94,5)="Markt"),"",IF(AND($C94<=K$3+6,$D94>=K$3),"■","")),"") | L94: =IFERROR(IF(OR($A94="",$A94="Model",LEFT($A94,5)="Markt"),"",IF(AND($C94<=L$3+6,$D94>=L$3),"■","")),"") | ... V94: =IFERROR(IF(OR($A94="",$A94="Model",LEFT($A94,5)="Markt"),"",IF(AND($C94<=V$3+6,$D94>=V$3),"■","")),"") -> ■
A95: Cayenne E4 | B95: Paid Social | C95: 46204 | D95: 46264 | E95: =IFERROR(IF(OR($A95="",$A95="Model",LEFT($A95,5)="Markt"),"",IF(AND($C95<=E$3+6,$D95>=E$3),"■","")),"") | F95: =IFERROR(IF(OR($A95="",$A95="Model",LEFT($A95,5)="Markt"),"",IF(AND($C95<=F$3+6,$D95>=F$3),"■","")),"") | G95: =IFERROR(IF(OR($A95="",$A95="Model",LEFT($A95,5)="Markt"),"",IF(AND($C95<=G$3+6,$D95>=G$3),"■","")),"") | H95: =IFERROR(IF(OR($A95="",$A95="Model",LEFT($A95,5)="Markt"),"",IF(AND($C95<=H$3+6,$D95>=H$3),"■","")),"") | I95: =IFERROR(IF(OR($A95="",$A95="Model",LEFT($A95,5)="Markt"),"",IF(AND($C95<=I$3+6,$D95>=I$3),"■","")),"") | J95: =IFERROR(IF(OR($A95="",$A95="Model",LEFT($A95,5)="Markt"),"",IF(AND($C95<=J$3+6,$D95>=J$3),"■","")),"") | K95: =IFERROR(IF(OR($A95="",$A95="Model",LEFT($A95,5)="Markt"),"",IF(AND($C95<=K$3+6,$D95>=K$3),"■","")),"") | L95: =IFERROR(IF(OR($A95="",$A95="Model",LEFT($A95,5)="Markt"),"",IF(AND($C95<=L$3+6,$D95>=L$3),"■","")),"") | ... V95: =IFERROR(IF(OR($A95="",$A95="Model",LEFT($A95,5)="Markt"),"",IF(AND($C95<=V$3+6,$D95>=V$3),"■","")),"") -> ■
A96: Markt: PIB SPA | X96: Markt: PIB SPA (Survey) | AT96: {=_xlfn.LET(_xlpm.mL,A96,_xlpm.aL,B96,_xlpm.mR,X96,_xlpm.aR,Y96,_xlpm.useR,AND(_xlpm.mR<>"",_xlpm.mR<>"Model",LEFT(_xlpm.mR,6)<>"Markt:"),_xlpm.m,IF(_xlpm.useR,_xlpm.mR,_xlpm.mL),_xlpm.a,IF(_xlpm.useR,_xlpm.aR,_xlpm.aL),_xlpm.rng,IF(_xlpm.useR,X$1:X96,A$1:A96),IF(OR(_xlpm.m="",_xlpm.m="Model",LEFT(_xlpm.m,6)="Markt:"),"",_xlfn.LET(_xlpm.mkt,LOOKUP(2,1/(LEFT(_xlpm.rng,6)="Markt:"),_xlpm.rng),_xlpm.mktNameRaw,TRIM(MID(_xlpm.mkt,FIND(":",_xlpm.mkt)+1,99)),_xlpm.mktName,TRIM(SUBSTITUTE(_xlpm.mktNameRaw,"(Survey)","")),_xlfn.XLOOKUP(_xlpm.mktName&"|"&SUBSTITUTE(_xlpm.m," ","")&"|"&_xlpm.a,tblMassnahmen[Key],tblMassnahmen[Kanal],""))))} | AU96: {=_xlfn.LET(_xlpm.mL,A96,_xlpm.aL,B96,_xlpm.mR,X96,_xlpm.aR,Y96,_xlpm.useR,AND(_xlpm.mR<>"",_xlpm.mR<>"Model",LEFT(_xlpm.mR,6)<>"Markt:"),_xlpm.m,IF(_xlpm.useR,_xlpm.mR,_xlpm.mL),_xlpm.a,IF(_xlpm.useR,_xlpm.aR,_xlpm.aL),_xlpm.rng,IF(_xlpm.useR,X$1:X96,A$1:A96),IF(OR(_xlpm.m="",_xlpm.m="Model",LEFT(_xlpm.m,6)="Markt:"),"",_xlfn.LET(_xlpm.mkt,LOOKUP(2,1/(LEFT(_xlpm.rng,6)="Markt:"),_xlpm.rng),_xlpm.mktNameRaw,TRIM(MID(_xlpm.mkt,FIND(":",_xlpm.mkt)+1,99)),_xlpm.mktName,TRIM(SUBSTITUTE(_xlpm.mktNameRaw,"(Survey)","")),_xlfn.XLOOKUP(_xlpm.mktName&"|"&SUBSTITUTE(_xlpm.m," ","")&"|"&_xlpm.a,tblMassnahmen[Key],tblMassnahmen[Budget],""))))} | AV96: {=_xlfn.LET(_xlpm.mL,A96,_xlpm.aL,B96,_xlpm.mR,X96,_xlpm.aR,Y96,_xlpm.useR,AND(_xlpm.mR<>"",_xlpm.mR<>"Model",LEFT(_xlpm.mR,6)<>"Markt:"),_xlpm.m,IF(_xlpm.useR,_xlpm.mR,_xlpm.mL),_xlpm.a,IF(_xlpm.useR,_xlpm.aR,_xlpm.aL),_xlpm.rng,IF(_xlpm.useR,X$1:X96,A$1:A96),IF(OR(_xlpm.m="",_xlpm.m="Model",LEFT(_xlpm.m,6)="Markt:"),"",_xlfn.LET(_xlpm.mkt,LOOKUP(2,1/(LEFT(_xlpm.rng,6)="Markt:"),_xlpm.rng),_xlpm.mktNameRaw,TRIM(MID(_xlpm.mkt,FIND(":",_xlpm.mkt)+1,99)),_xlpm.mktName,TRIM(SUBSTITUTE(_xlpm.mktNameRaw,"(Survey)","")),_xlfn.XLOOKUP(_xlpm.mktName&"|"&SUBSTITUTE(_xlpm.m," ","")&"|"&_xlpm.a,tblMassnahmen[Key],tblMassnahmen[KPI],""))))}
A97: Model | B97: CTG Measure | C97: Start | D97: Ende | E97: CW18 | F97: CW19 | G97: CW20 | H97: CW21 | I97: CW22 | J97: CW23 | K97: CW24 | L97: CW25 | M97: CW26 | N97: CW27 | O97: CW28 | P97: CW29 | Q97: CW30 | R97: CW31 | S97: CW32 | T97: CW33 | U97: CW34 | V97: CW35 | X97: Model | Y97: Local Measure | Z97: Start | AA97: Ende | AB97: CW18 | AC97: CW19 | AD97: CW20 | AE97: CW21 | AF97: CW22 | AG97: CW23 | AH97: CW24 | AI97: CW25 | AJ97: CW26 | AK97: CW27 | AL97: CW28 | AM97: CW29 | AN97: CW30 | AO97: CW31 | AP97: CW32 | AQ97: CW33 | AR97: CW34 | AS97: CW35 | AT97: Channel | AU97: Budget | AV97: KPI | AW97: Audience
A98: Macan BEV | B98: Google Ads | C98: 46143 | D98: 46264 | E98: =IFERROR(IF(OR($A98="",$A98="Model",LEFT($A98,5)="Markt"),"",IF(AND($C98<=E$3+6,$D98>=E$3),"■","")),"") -> ■ | F98: =IFERROR(IF(OR($A98="",$A98="Model",LEFT($A98,5)="Markt"),"",IF(AND($C98<=F$3+6,$D98>=F$3),"■","")),"") -> ■ | G98: =IFERROR(IF(OR($A98="",$A98="Model",LEFT($A98,5)="Markt"),"",IF(AND($C98<=G$3+6,$D98>=G$3),"■","")),"") -> ■ | H98: =IFERROR(IF(OR($A98="",$A98="Model",LEFT($A98,5)="Markt"),"",IF(AND($C98<=H$3+6,$D98>=H$3),"■","")),"") -> ■ | I98: =IFERROR(IF(OR($A98="",$A98="Model",LEFT($A98,5)="Markt"),"",IF(AND($C98<=I$3+6,$D98>=I$3),"■","")),"") -> ■ | J98: =IFERROR(IF(OR($A98="",$A98="Model",LEFT($A98,5)="Markt"),"",IF(AND($C98<=J$3+6,$D98>=J$3),"■","")),"") -> ■ | K98: =IFERROR(IF(OR($A98="",$A98="Model",LEFT($A98,5)="Markt"),"",IF(AND($C98<=K$3+6,$D98>=K$3),"■","")),"") -> ■ | L98: =IFERROR(IF(OR($A98="",$A98="Model",LEFT($A98,5)="Markt"),"",IF(AND($C98<=L$3+6,$D98>=L$3),"■","")),"") -> ■ | ... V98: =IFERROR(IF(OR($A98="",$A98="Model",LEFT($A98,5)="Markt"),"",IF(AND($C98<=V$3+6,$D98>=V$3),"■","")),"") -> ■ | X98: Macan H2 | Y98: Always On SEM (Jan-Dec) | Z98: 46022 | AA98: 46386 | AB98: =IF(AND($Z98<=(AB$3+6),$AA98>=AB$3),"■","") -> ■ | AC98: =IF(AND($Z98<=(AC$3+6),$AA98>=AC$3),"■","") -> ■ | AD98: =IF(AND($Z98<=(AD$3+6),$AA98>=AD$3),"■","") -> ■ | AE98: =IF(AND($Z98<=(AE$3+6),$AA98>=AE$3),"■","") -> ■ | AF98: =IF(AND($Z98<=(AF$3+6),$AA98>=AF$3),"■","") -> ■ | AG98: =IF(AND($Z98<=(AG$3+6),$AA98>=AG$3),"■","") -> ■ | AH98: =IF(AND($Z98<=(AH$3+6),$AA98>=AH$3),"■","") -> ■ | AI98: =IF(AND($Z98<=(AI$3+6),$AA98>=AI$3),"■","") -> ■ | ... AS98: =IF(AND($Z98<=(AS$3+6),$AA98>=AS$3),"■","") -> ■ | AT98: Search | AU98: 50K | AV98: Impressions,Cost per Million (CPM),Click Through Rate (CTR),Model page visit | AW98: primary / secondary
A99: Macan BEV | B99: Google Inventory Ads | C99: 46143 | D99: 46264 | E99: =IFERROR(IF(OR($A99="",$A99="Model",LEFT($A99,5)="Markt"),"",IF(AND($C99<=E$3+6,$D99>=E$3),"■","")),"") -> ■ | F99: =IFERROR(IF(OR($A99="",$A99="Model",LEFT($A99,5)="Markt"),"",IF(AND($C99<=F$3+6,$D99>=F$3),"■","")),"") -> ■ | G99: =IFERROR(IF(OR($A99="",$A99="Model",LEFT($A99,5)="Markt"),"",IF(AND($C99<=G$3+6,$D99>=G$3),"■","")),"") -> ■ | H99: =IFERROR(IF(OR($A99="",$A99="Model",LEFT($A99,5)="Markt"),"",IF(AND($C99<=H$3+6,$D99>=H$3),"■","")),"") -> ■ | I99: =IFERROR(IF(OR($A99="",$A99="Model",LEFT($A99,5)="Markt"),"",IF(AND($C99<=I$3+6,$D99>=I$3),"■","")),"") -> ■ | J99: =IFERROR(IF(OR($A99="",$A99="Model",LEFT($A99,5)="Markt"),"",IF(AND($C99<=J$3+6,$D99>=J$3),"■","")),"") -> ■ | K99: =IFERROR(IF(OR($A99="",$A99="Model",LEFT($A99,5)="Markt"),"",IF(AND($C99<=K$3+6,$D99>=K$3),"■","")),"") -> ■ | L99: =IFERROR(IF(OR($A99="",$A99="Model",LEFT($A99,5)="Markt"),"",IF(AND($C99<=L$3+6,$D99>=L$3),"■","")),"") -> ■ | ... V99: =IFERROR(IF(OR($A99="",$A99="Model",LEFT($A99,5)="Markt"),"",IF(AND($C99<=V$3+6,$D99>=V$3),"■","")),"") -> ■ | X99: Macan H2 | Y99: Macan 4 Spirit Pack (Feb - May) | Z99: 46064 | AA99: 46151 | AB99: =IF(AND($Z99<=(AB$3+6),$AA99>=AB$3),"■","") -> ■ | AC99: =IF(AND($Z99<=(AC$3+6),$AA99>=AC$3),"■","") -> ■ | AD99: =IF(AND($Z99<=(AD$3+6),$AA99>=AD$3),"■","") | AE99: =IF(AND($Z99<=(AE$3+6),$AA99>=AE$3),"■","") | AF99: =IF(AND($Z99<=(AF$3+6),$AA99>=AF$3),"■","") | AG99: =IF(AND($Z99<=(AG$3+6),$AA99>=AG$3),"■","") | AH99: =IF(AND($Z99<=(AH$3+6),$AA99>=AH$3),"■","") | AI99: =IF(AND($Z99<=(AI$3+6),$AA99>=AI$3),"■","") | ... AS99: =IF(AND($Z99<=(AS$3+6),$AA99>=AS$3),"■","") | AT99: Social,Programmatic,Other Online Channel, Brand Days | AU99: 225K | AV99: Impressions,Cost per Million (CPM),Click Through Rate (CTR),Model page visit,Others, Lead generation & order income | AW99: primary / secondary
A100: Macan BEV | B100: META Inventory Ads | C100: 46143 | D100: 46264 | E100: =IFERROR(IF(OR($A100="",$A100="Model",LEFT($A100,5)="Markt"),"",IF(AND($C100<=E$3+6,$D100>=E$3),"■","")),"") -> ■ | F100: =IFERROR(IF(OR($A100="",$A100="Model",LEFT($A100,5)="Markt"),"",IF(AND($C100<=F$3+6,$D100>=F$3),"■","")),"") -> ■ | G100: =IFERROR(IF(OR($A100="",$A100="Model",LEFT($A100,5)="Markt"),"",IF(AND($C100<=G$3+6,$D100>=G$3),"■","")),"") -> ■ | H100: =IFERROR(IF(OR($A100="",$A100="Model",LEFT($A100,5)="Markt"),"",IF(AND($C100<=H$3+6,$D100>=H$3),"■","")),"") -> ■ | I100: =IFERROR(IF(OR($A100="",$A100="Model",LEFT($A100,5)="Markt"),"",IF(AND($C100<=I$3+6,$D100>=I$3),"■","")),"") -> ■ | J100: =IFERROR(IF(OR($A100="",$A100="Model",LEFT($A100,5)="Markt"),"",IF(AND($C100<=J$3+6,$D100>=J$3),"■","")),"") -> ■ | K100: =IFERROR(IF(OR($A100="",$A100="Model",LEFT($A100,5)="Markt"),"",IF(AND($C100<=K$3+6,$D100>=K$3),"■","")),"") -> ■ | L100: =IFERROR(IF(OR($A100="",$A100="Model",LEFT($A100,5)="Markt"),"",IF(AND($C100<=L$3+6,$D100>=L$3),"■","")),"") -> ■ | ... V100: =IFERROR(IF(OR($A100="",$A100="Model",LEFT($A100,5)="Markt"),"",IF(AND($C100<=V$3+6,$D100>=V$3),"■","")),"") -> ■ | X100: Macan H2 | Y100: Macan with Equipment Pack (September - October) | Z100: 46279 | AA100: 46340 | AB100: =IF(AND($Z100<=(AB$3+6),$AA100>=AB$3),"■","") | AC100: =IF(AND($Z100<=(AC$3+6),$AA100>=AC$3),"■","") | AD100: =IF(AND($Z100<=(AD$3+6),$AA100>=AD$3),"■","") | AE100: =IF(AND($Z100<=(AE$3+6),$AA100>=AE$3),"■","") | AF100: =IF(AND($Z100<=(AF$3+6),$AA100>=AF$3),"■","") | AG100: =IF(AND($Z100<=(AG$3+6),$AA100>=AG$3),"■","") | AH100: =IF(AND($Z100<=(AH$3+6),$AA100>=AH$3),"■","") | AI100: =IF(AND($Z100<=(AI$3+6),$AA100>=AI$3),"■","") | ... AS100: =IF(AND($Z100<=(AS$3+6),$AA100>=AS$3),"■","") | AT100: Social | AU100: 15K (we will have DOOH as well with a big part of the investment) | AV100: Impressions,Cost per Million (CPM),Click Through Rate (CTR),Model page visit,Others, Lead generation and order income | AW100: primary / secondary
...

Sheet Survey Rohdaten_20.4.
A1: StartDate | B1: EndDate | C1: Status | D1: IPAddress | E1: Progress | F1: Duration (in seconds) | G1: Finished | H1: RecordedDate | I1: ResponseId | J1: RecipientLastName | K1: RecipientFirstName | L1: RecipientEmail | M1: ExternalReference | N1: LocationLatitude | O1: LocationLongitude | P1: DistributionChannel | Q1: UserLanguage | R1: Market | S1: Campaign/ Model | T1: Campaign/ Model_1_TEXT | U1: Campaign/ Model_2_TEXT | V1: Campaign/ Model_3_TEXT | W1: Campaign/ Model_4_TEXT | X1: Campaign/ Model_5_TEXT | Y1: Campaign/ Model_6_TEXT | Z1: Campaign/ Model_7_TEXT | AA1: Campaign/ Model_8_TEXT | AB1: Campaign/ Model_9_TEXT | AC1: Channel_1 | AD1: Channel_1_7_TEXT | AE1: Business objective_1 | AF1: KPIs_1 | AG1: KPIs_1_12_TEXT | AH1: Total budget_1 | AI1: Flight Date_1_1 | AJ1: Flight Date_1_2 | AK1: Flexibility_1 | AL1: Audience_1_1 | AM1: Audience_1_2 | AN1: Audience_1.1_1 | AO1: Audience_1.1_2 | AP1: Audience_1.1_3 | AQ1: Assets_1 | AR1: Channel_2 | AS1: Channel_2_7_TEXT | AT1: Business objective_2 | AU1: KPIs_2 | AV1: KPIs_2_12_TEXT | AW1: Total budget_2 | AX1: Flight Date_2_1 | AY1: Flight Date_2_2 | AZ1: Flexibility_2 | BA1: Audience_2_1 | BB1: Audience_2_2 | BC1: Audience_2.1_1 | BD1: Audience_2.1_2 | BE1: Audience_2.1_3 | BF1: Assets_2 | BG1: Channel_3 | BH1: Channel_3_7_TEXT | BI1: Business objective_3 | BJ1: KPIs_3 | BK1: KPIs_3_12_TEXT | BL1: Total budget_3 | BM1: Flight Date_3_1 | BN1: Flight Date_3_2 | BO1: Flexibility_3 | BP1: Audience_3_1 | BQ1: Audience_3_2 | BR1: Audience_3.1_1 | BS1: Audience_3.1_2 | BT1: Audience_3.1_3 | BU1: Assets_3 | BV1: Channel_4 | BW1: Channel_4_7_TEXT | BX1: Business objective_4 | BY1: KPIs_4 | BZ1: KPIs_4_12_TEXT | CA1: Total budget_4 | CB1: Flight Date_4_1 | CC1: Flight Date_4_2 | CD1: Flexibility_4 | CE1: Audience_4_1 | CF1: Audience_4_2 | CG1: Audience_4.1_1 | CH1: Audience_4.1_2 | CI1: Audience_4.1_3 | CJ1: Assets_4 | CK1: Channel_5 | CL1: Channel_5_7_TEXT | CM1: Business objective_5 | CN1: KPIs_5 | CO1: KPIs_5_12_TEXT | CP1: Total budget_5 | CQ1: Flight Date_5_1 | CR1: Flight Date_5_2 | CS1: Flexibility_5 | CT1: Audience_5_1 | CU1: Audience_5_2 | CV1: Audience_5.1_1 | CW1: Audience_5.1_2 | CX1: Audience_5.1_3 | CY1: Assets_5 | CZ1: Channel_6 | DA1: Channel_6_7_TEXT | DB1: Business objective_6 | DC1: KPIs_6 | DD1: KPIs_6_12_TEXT | DE1: Total budget_6 | DF1: Flight Date_6_1 | DG1: Flight Date_6_2 | DH1: Flexibility_6 | DI1: Audience_6_1 | DJ1: Audience_6_2 | DK1: Audience_6.1_1 | DL1: Audience_6.1_2 | DM1: Audience_6.1_3 | DN1: Assets_6 | DO1: Channel_7 | DP1: Channel_7_7_TEXT | DQ1: Business objective_7 | DR1: KPIs_7 | DS1: KPIs_7_12_TEXT | DT1: Total budget_7 | DU1: Flight Date_7_1 | DV1: Flight Date_7_2 | DW1: Flexibility_7 | DX1: Audience_7_1 | DY1: Audience_7_2 | DZ1: Audience_7.1_1 | EA1: Audience_7.1_2 | EB1: Audience_7.1_3 | EC1: Assets_7 | ED1: Channel_8 | EE1: Channel_8_7_TEXT | EF1: Business objective_8 | EG1: KPIs_8 | EH1: KPIs_8_12_TEXT | EI1: Total budget_8 | EJ1: Flight Date_8_1 | EK1: Flight Date_8_2 | EL1: Flexibility_8 | EM1: Audience_8_1 | EN1: Audience_8_2 | EO1: Audience_8.1_1 | EP1: Audience_8.1_2 | EQ1: Audience_8.1_3 | ER1: Assets_8 | ES1: Channel_9 | ET1: Channel_9_7_TEXT | EU1: Business objective_9 | EV1: KPIs_9 | EW1: KPIs_9_12_TEXT | EX1: Total budget_9 | EY1: Flight Date_9_1 | EZ1: Flight Date_9_2 | FA1: Flexibility_9 | FB1: Audience_9_1 | FC1: Audience_9_2 | FD1: Audience_9.1_1 | FE1: Audience_9.1_2 | FF1: Audience_9.1_3 | FG1: Assets_9 | FH1: Feedback | FI1: CURRENT_YEAR | FJ1: Q_DataPolicyViolations
A2: Start Date | B2: End Date | C2: Response Type | D2: IP Address | E2: Progress | F2: Duration (in seconds) | G2: Finished | H2: Recorded Date | I2: Response ID | J2: Recipient Last Name | K2: Recipient First Name | L2: Recipient Email | M2: External Data Reference | N2: Location Latitude | O2: Location Longitude | P2: Distribution Channel | Q2: User Language | R2: Please select the market you are representing from the list below. | S2: Which campaigns do you use for the models listed below? Please type in the campaign name you are using for the respective model. (If available, please use PlanIt naming convention) - Selected Choice | T2: Which campaigns do you use for the models listed below? Please type in the campaign name you are using for the respective model. (If available, please use PlanIt naming convention) - Campaign 1 (Cayenne E3II): - Text | U2: Which campaigns do you use for the models listed below? Please type in the campaign name you are using for the respective model. (If available, please use PlanIt naming convention) - Campaign 2 (Cayenne E3II): - Text | V2: Which campaigns do you use for the models listed below? Please type in the campaign name you are using for the respective model. (If available, please use PlanIt naming convention) - Campaign 3 (Cayenne E3II): - Text | W2: Which campaigns do you use for the models listed below? Please type in the campaign name you are using for the respective model. (If available, please use PlanIt naming convention) - Campaign 4 (Cayenne E4): - Text | X2: Which campaigns do you use for the models listed below? Please type in the campaign name you are using for the respective model. (If available, please use PlanIt naming convention) - Campaign 5 (Cayenne E4): - Text | Y2: Which campaigns do you use for the models listed below? Please type in the campaign name you are using for the respective model. (If available, please use PlanIt naming convention) - Campaign 6 (Cayenne E4): - Text | Z2: Which campaigns do you use for the models listed below? Please type in the campaign name you are using for the respective model. (If available, please use PlanIt naming convention) - Campaign 7 (Macan H2): - Text | AA2: Which campaigns do you use for the models listed below? Please type in the campaign name you are using for the respective model. (If available, please use PlanIt naming convention) - Campaign 8 (Macan H2): - Text | AB2: Which campaigns do you use for the models listed below? Please type in the campaign name you are using for the respective model. (If available, please use PlanIt naming convention) - Campaign 9 (Macan H2): - Text | AC2: Please select all the channels that apply for the campaign [QID62-ChoiceTextEntryValue-1] you have selected: - Selected Choice | AD2: Please select all the channels that apply for the campaign [QID62-ChoiceTextEntryValue-1] you have selected: - Other Online Channel - Text | AE2: Please select the business objective for the campaign [QID62-ChoiceTextEntryValue-1] you have selected: | AF2: Please select the KPIs you are using for the campaign [QID62-ChoiceTextEntryValue-1] you have selected: - Selected Choice | AG2: Please select the KPIs you are using for the campaign [QID62-ChoiceTextEntryValue-1] you have selected: - Others - Text | AH2: Please type in the total budget you have allocated for the campaign [QID62-ChoiceTextEntryValue-1] you have selected: | AI2: Please type in the Flight Start Date and the Flight End Date for the campaign [QID62-ChoiceTextEntryValue-1] you have selected: - Flight Start Date | AJ2: Please type in the Flight Start Date and the Flight End Date for the campaign [QID62-ChoiceTextEntryValue-1] you have selected: - Flight End Date | AK2: Is this campaign [QID62-ChoiceTextEntryValue-1] you have selected flexible? | AL2: Please type in the primary audience and the secondary audience for the campaign [QID62-ChoiceTextEntryValue-1] you have selected: - Primary Audience | AM2: Please type in the primary audience and the secondary audience for the campaign [QID62-ChoiceTextEntryValue-1] you have selected: - Secondary Audience | AN2: Please select if you have used specific audiences or included remarketing for the campaign [QID62-ChoiceTextEntryValue-1] you have selected: - Custom Audiences? | AO2: Please select if you have used specific audiences or included remarketing for the campaign [QID62-ChoiceTextEntryValue-1] you have selected: - Lookalike/ Similar Audiences | AP2: Please select if you have used specific audiences or included remarketing for the campaign [QID62-ChoiceTextEntryValue-1] you have selected: - Remarketing | AQ2: Do you have assets ready? | AR2: Please select all the channels that apply the campaign [QID62-ChoiceTextEntryValue-2] you have selected: - Selected Choice | AS2: Please select all the channels that apply the campaign [QID62-ChoiceTextEntryValue-2] you have selected: - Other Online Channel - Text | AT2: Please select the business objective for the campaign [QID62-ChoiceTextEntryValue-2] you have selected: | AU2: Please select the KPIs you are using for the campaign [QID62-ChoiceTextEntryValue-2] you have selected: - Selected Choice | AV2: Please select the KPIs you are using for the campaign [QID62-ChoiceTextEntryValue-2] you have selected: - Others - Text | AW2: Please type in the total budget you have allocated for the campaign [QID62-ChoiceTextEntryValue-2] you have selected: | AX2: Please type in the Flight Start Date and the Flight End Date for the campaign [QID62-ChoiceTextEntryValue-2] you have selected: - Flight Start Date | AY2: Please type in the Flight Start Date and the Flight End Date for the campaign [QID62-ChoiceTextEntryValue-2] you have selected: - Flight End Date | AZ2: Is this campaign [QID62-ChoiceTextEntryValue-2] you have selected flexible? | BA2: Please type in the primary audience and the secondary audience for the campaign [QID62-ChoiceTextEntryValue-2] you have selected: - Primary Audience | BB2: Please type in the primary audience and the secondary audience for the campaign [QID62-ChoiceTextEntryValue-2] you have selected: - Secondary Audience | BC2: Please select if you have used specific audiences or included remarketing for the campaign [QID62-ChoiceTextEntryValue-2] you have selected: - Custom Audiences? | BD2: Please select if you have used specific audiences or included remarketing for the campaign [QID62-ChoiceTextEntryValue-2] you have selected: - Lookalike/ Similar Audiences | BE2: Please select if you have used specific audiences or included remarketing for the campaign [QID62-ChoiceTextEntryValue-2] you have selected: - Remarketing | BF2: Do you have assets ready? | BG2: Please select all the channels that apply the campaign [QID62-ChoiceTextEntryValue-3] you have selected: - Selected Choice | BH2: Please select all the channels that apply the campaign [QID62-ChoiceTextEntryValue-3] you have selected: - Other Online Channel - Text | BI2: Please select the business objective for the campaign [QID62-ChoiceTextEntryValue-3] you have selected: | BJ2: Please select the KPIs you are using for the campaign [QID62-ChoiceTextEntryValue-3] you have selected: - Selected Choice | BK2: Please select the KPIs you are using for the campaign [QID62-ChoiceTextEntryValue-3] you have selected: - Others - Text | BL2: Please type in the total budget you have allocated for the campaign [QID62-ChoiceTextEntryValue-3] you have selected: | BM2: Please type in the Flight Start Date and the Flight End Date for the campaign [QID62-ChoiceTextEntryValue-3] you have selected: - Flight Start Date | BN2: Please type in the Flight Start Date and the Flight End Date for the campaign [QID62-ChoiceTextEntryValue-3] you have selected: - Flight End Date | BO2: Is this campaign [QID62-ChoiceTextEntryValue-3] you have selected flexible? | BP2: Please type in the primary audience and the secondary audience for the campaign [QID62-ChoiceTextEntryValue-3] you have selected: - Primary Audience | BQ2: Please type in the primary audience and the secondary audience for the campaign [QID62-ChoiceTextEntryValue-3] you have selected: - Secondary Audience | BR2: Please select if you have used specific audiences or included remarketing for the campaign [QID62-ChoiceTextEntryValue-3] you have selected: - Custom Audiences? | BS2: Please select if you have used specific audiences or included remarketing for the campaign [QID62-ChoiceTextEntryValue-3] you have selected: - Lookalike/ Similar Audiences | BT2: Please select if you have used specific audiences or included remarketing for the campaign [QID62-ChoiceTextEntryValue-3] you have selected: - Remarketing | BU2: Do you have assets ready? | BV2: Please select all the channels that apply the campaign [QID62-ChoiceTextEntryValue-4] you have selected: - Selected Choice | BW2: Please select all the channels that apply the campaign [QID62-ChoiceTextEntryValue-4] you have selected: - Other Online Channel - Text | BX2: Please select the business objective for the campaign [QID62-ChoiceTextEntryValue-4] you have selected: | BY2: Please select the KPIs you are using for the campaign [QID62-ChoiceTextEntryValue-4] you have selected: - Selected Choice | BZ2: Please select the KPIs you are using for the campaign [QID62-ChoiceTextEntryValue-4] you have selected: - Others - Text | CA2: Please type in the total budget you have allocated for the campaign [QID62-ChoiceTextEntryValue-4] you have selected: | CB2: Please type in the Flight Start Date and the Flight End Date for the campaign [QID62-ChoiceTextEntryValue-4] you have selected: - Flight Start Date | CC2: Please type in the Flight Start Date and the Flight End Date for the campaign [QID62-ChoiceTextEntryValue-4] you have selected: - Flight End Date | CD2: Is this campaign [QID62-ChoiceTextEntryValue-4] you have selected flexible? | CE2: Please type in the primary audience and the secondary audience for the campaign [QID62-ChoiceTextEntryValue-4] you have selected: - Primary Audience | CF2: Please type in the primary audience and the secondary audience for the campaign [QID62-ChoiceTextEntryValue-4] you have selected: - Secondary Audience | CG2: Please select if you have used specific audiences or included remarketing for the campaign [QID62-ChoiceTextEntryValue-4] you have selected: - Custom Audiences? | CH2: Please select if you have used specific audiences or included remarketing for the campaign [QID62-ChoiceTextEntryValue-4] you have selected: - Lookalike/ Similar Audiences | CI2: Please select if you have used specific audiences or included remarketing for the campaign [QID62-ChoiceTextEntryValue-4] you have selected: - Remarketing | CJ2: Do you have assets ready? | CK2: Please select all the channels that apply the campaign [QID62-ChoiceTextEntryValue-5] you have selected: - Selected Choice | CL2: Please select all the channels that apply the campaign [QID62-ChoiceTextEntryValue-5] you have selected: - Other Online Channel - Text | CM2: Please select the business objective for the campaign [QID62-ChoiceTextEntryValue-5] you have selected: | CN2: Please select the KPIs you are using for the campaign [QID62-ChoiceTextEntryValue-5] you have selected: - Selected Choice | CO2: Please select the KPIs you are using for the campaign [QID62-ChoiceTextEntryValue-5] you have selected: - Others - Text | CP2: Please type in the total budget you have allocated for the campaign [QID62-ChoiceTextEntryValue-5] you have selected: | CQ2: Please type in the Flight Start Date and the Flight End Date for the campaign [QID62-ChoiceTextEntryValue-5] you have selected: - Flight Start Date | CR2: Please type in the Flight Start Date and the Flight End Date for the campaign [QID62-ChoiceTextEntryValue-5] you have selected: - Flight End Date | CS2: Is this campaign [QID62-ChoiceTextEntryValue-5] you have selected flexible? | CT2: Please type in the primary audience and the secondary audience for the campaign [QID62-ChoiceTextEntryValue-5] you have selected: - Primary Audience | CU2: Please type in the primary audience and the secondary audience for the campaign [QID62-ChoiceTextEntryValue-5] you have selected: - Secondary Audience | CV2: Please select if you have used specific audiences or included remarketing for the campaign [QID62-ChoiceTextEntryValue-5] you have selected: - Custom Audiences? | CW2: Please select if you have used specific audiences or included remarketing for the campaign [QID62-ChoiceTextEntryValue-5] you have selected: - Lookalike/ Similar Audiences | CX2: Please select if you have used specific audiences or included remarketing for the campaign [QID62-ChoiceTextEntryValue-5] you have selected: - Remarketing | CY2: Do you have assets ready? | CZ2: Please select all the channels that apply the campaign [QID62-ChoiceTextEntryValue-6] you have selected: - Selected Choice | DA2: Please select all the channels that apply the campaign [QID62-ChoiceTextEntryValue-6] you have selected: - Other Online Channel - Text | DB2: Please select the business objective for the campaign [QID62-ChoiceTextEntryValue-6] you have selected: | DC2: Please select the KPIs you are using for the campaign [QID62-ChoiceTextEntryValue-6] you have selected: - Selected Choice | DD2: Please select the KPIs you are using for the campaign [QID62-ChoiceTextEntryValue-6] you have selected: - Others - Text | DE2: Please type in the total budget you have allocated for the campaign [QID62-ChoiceTextEntryValue-6] you have selected: | DF2: Please type in the Flight Start Date and the Flight End Date for the campaign [QID62-ChoiceTextEntryValue-6] you have selected: - Flight Start Date | DG2: Please type in the Flight Start Date and the Flight End Date for the campaign [QID62-ChoiceTextEntryValue-6] you have selected: - Flight End Date | DH2: Is this campaign [QID62-ChoiceTextEntryValue-6] you have selected flexible? | DI2: Please type in the primary audience and the secondary audience for the campaign [QID62-ChoiceTextEntryValue-6] you have selected: - Primary Audience | DJ2: Please type in the primary audience and the secondary audience for the campaign [QID62-ChoiceTextEntryValue-6] you have selected: - Secondary Audience | DK2: Please select if you have used specific audiences or included remarketing for the campaign [QID62-ChoiceTextEntryValue-6] you have selected: - Custom Audiences? | DL2: Please select if you have used specific audiences or included remarketing for the campaign [QID62-ChoiceTextEntryValue-6] you have selected: - Lookalike/ Similar Audiences | DM2: Please select if you have used specific audiences or included remarketing for the campaign [QID62-ChoiceTextEntryValue-6] you have selected: - Remarketing | DN2: Do you have assets ready? | DO2: Please select all the channels that apply the campaign [QID62-ChoiceTextEntryValue-7] you have selected: - Selected Choice | DP2: Please select all the channels that apply the campaign [QID62-ChoiceTextEntryValue-7] you have selected: - Other Online Channel - Text | DQ2: Please select the business objective for the campaign [QID62-ChoiceTextEntryValue-7] you have selected: | DR2: Please select the KPIs you are using for the campaign [QID62-ChoiceTextEntryValue-7] you have selected: - Selected Choice | DS2: Please select the KPIs you are using for the campaign [QID62-ChoiceTextEntryValue-7] you have selected: - Others - Text | DT2: Please type in the total budget you have allocated for the campaign [QID62-ChoiceTextEntryValue-7] you have selected: | DU2: Please type in the Flight Start Date and the Flight End Date for the campaign [QID62-ChoiceTextEntryValue-7] you have selected: - Flight Start Date | DV2: Please type in the Flight Start Date and the Flight End Date for the campaign [QID62-ChoiceTextEntryValue-7] you have selected: - Flight End Date | DW2: Is this campaign [QID62-ChoiceTextEntryValue-7] you have selected flexible? | DX2: Please type in the primary audience and the secondary audience for the campaign [QID62-ChoiceTextEntryValue-7] you have selected: - Primary Audience | DY2: Please type in the primary audience and the secondary audience for the campaign [QID62-ChoiceTextEntryValue-7] you have selected: - Secondary Audience | DZ2: Please select if you have used specific audiences or included remarketing for the campaign [QID62-ChoiceTextEntryValue-7] you have selected: - Custom Audiences? | EA2: Please select if you have used specific audiences or included remarketing for the campaign [QID62-ChoiceTextEntryValue-7] you have selected: - Lookalike/ Similar Audiences | EB2: Please select if you have used specific audiences or included remarketing for the campaign [QID62-ChoiceTextEntryValue-7] you have selected: - Remarketing | EC2: Do you have assets ready? | ED2: Please select all the channels that apply the campaign [QID62-ChoiceTextEntryValue-8] you have selected: - Selected Choice | EE2: Please select all the channels that apply the campaign [QID62-ChoiceTextEntryValue-8] you have selected: - Other Online Channel - Text | EF2: Please select the business objective for the campaign [QID62-ChoiceTextEntryValue-8] you have selected: | EG2: Please select the KPIs you are using for the campaign [QID62-ChoiceTextEntryValue-8] you have selected: - Selected Choice | EH2: Please select the KPIs you are using for the campaign [QID62-ChoiceTextEntryValue-8] you have selected: - Others - Text | EI2: Please type in the total budget you have allocated for the campaign [QID62-ChoiceTextEntryValue-8] you have selected: | EJ2: Please type in the Flight Start Date and the Flight End Date for the campaign [QID62-ChoiceTextEntryValue-8] you have selected: - Flight Start Date | EK2: Please type in the Flight Start Date and the Flight End Date for the campaign [QID62-ChoiceTextEntryValue-8] you have selected: - Flight End Date | EL2: Is this campaign [QID62-ChoiceTextEntryValue-8] you have selected flexible? | EM2: Please type in the primary audience and the secondary audience for the campaign [QID62-ChoiceTextEntryValue-8] you have selected: - Primary Audience | EN2: Please type in the primary audience and the secondary audience for the campaign [QID62-ChoiceTextEntryValue-8] you have selected: - Secondary Audience | EO2: Please select if you have used specific audiences or included remarketing for the campaign [QID62-ChoiceTextEntryValue-8] you have selected: - Custom Audiences? | EP2: Please select if you have used specific audiences or included remarketing for the campaign [QID62-ChoiceTextEntryValue-8] you have selected: - Lookalike/ Similar Audiences | EQ2: Please select if you have used specific audiences or included remarketing for the campaign [QID62-ChoiceTextEntryValue-8] you have selected: - Remarketing | ER2: Do you have assets ready? | ES2: Please select all the channels that apply the campaign [QID62-ChoiceTextEntryValue-9] you have selected: - Selected Choice | ET2: Please select all the channels that apply the campaign [QID62-ChoiceTextEntryValue-9] you have selected: - Other Online Channel - Text | EU2: Please select the business objective for the campaign [QID62-ChoiceTextEntryValue-9] you have selected: | EV2: Please select the KPIs you are using for the campaign [QID62-ChoiceTextEntryValue-9] you have selected: - Selected Choice | EW2: Please select the KPIs you are using for the campaign [QID62-ChoiceTextEntryValue-9] you have selected: - Others - Text | EX2: Please type in the total budget you have allocated for the campaign [QID62-ChoiceTextEntryValue-9] you have selected: | EY2: Please type in the Flight Start Date and the Flight End Date for the campaign [QID62-ChoiceTextEntryValue-9] you have selected: - Flight Start Date | EZ2: Please type in the Flight Start Date and the Flight End Date for the campaign [QID62-ChoiceTextEntryValue-9] you have selected: - Flight End Date | FA2: Is this campaign [QID62-ChoiceTextEntryValue-9] you have selected flexible? | FB2: Please type in the primary audience and the secondary audience for the campaign [QID62-ChoiceTextEntryValue-9] you have selected: - Primary Audience | FC2: Please type in the primary audience and the secondary audience for the campaign [QID62-ChoiceTextEntryValue-9] you have selected: - Secondary Audience | FD2: Please select if you have used specific audiences or included remarketing for the campaign [QID62-ChoiceTextEntryValue-9] you have selected: - Custom Audiences? | FE2: Please select if you have used specific audiences or included remarketing for the campaign [QID62-ChoiceTextEntryValue-9] you have selected: - Lookalike/ Similar Audiences | FF2: Please select if you have used specific audiences or included remarketing for the campaign [QID62-ChoiceTextEntryValue-9] you have selected: - Remarketing | FG2: Do you have assets ready? | FH2: Additional comments or feedback | FI2: CURRENT_YEAR | FJ2: Q_DataPolicyViolations
A3: 46120.089 | B3: 46120.129 | C3: IP Address | D3: 163.116.215.97 | E3: 100 | F3: 3455 | G3: True | H3: 46120.129 | I3: R_4Qm6t5493VGlEEy | N3: -37.8159 | O3: 144.9669 | P3: anonymous | Q3: EN | R3: PCA | S3: Campaign 1 (Cayenne E3II):,Campaign 7 (Macan H2): | T3: 20196850_20196850_POR_CAY_SUV_AUS_T2_NU_AUD_2026-03-01_2026-04-16_LOCAL-CAYENNEBLACKEDITIONH12026-CAYENNEBLACKEDITIONH12026 | Z3: 20253810_20253810_POR_MAC_SUV_AUS_T1_NU_AUD_2026-04-26_2026-06-07_LOCAL-MACANGTSH12026-MACANGTSH12026 | AC3: Programmatic | AE3: Awareness | AF3: Impressions,Cost per Million (CPM) | AH3: $141,841 | AI3: 02/03/2026 | AJ3: 17/04/2026 | AK3: Yes | AL3: People aged thirty five and over with High Net Wealth | AM3: Not applicable | AN3: Yes | AO3: Yes | AQ3: Yes | DO3: Programmatic | DQ3: Awareness | DR3: Impressions,Cost per Million (CPM) | DT3: $27,341 | DU3: 27/04/2026 | DV3: 08/06/2026 | DW3: Yes | DX3: People aged thirty five and over with a high net wealth | DY3: Not applicable | DZ3: Yes | EA3: Yes | EC3: No | FI3: 2026
A4: 46120.545 | B4: 46120.566 | C4: IP Address | D4: 84.14.20.227 | E4: 100 | F4: 1852 | G4: True | H4: 46120.566 | I4: R_8X1fW9wfvCznl9n | N4: 40.4153 | O4: -3.694 | P4: anonymous | Q4: EN | R4: PIB SPA | S4: Campaign 1 (Cayenne E3II):,Campaign 2 (Cayenne E3II):,Campaign 4 (Cayenne E4):,Campaign 5 (Cayenne E4):,Campaign 6 (Cayenne E4):,Campaign 7 (Macan H2):,Campaign 8 (Macan H2):,Campaign 9 (Macan H2): | T4: Black Edition Campaign (March-August) | U4: Always On SEM (Jan-Dec) | W4: Cayenne Electric Launch Campaign (March - August) | X4: Cayenne Coupé TVC (May) | Y4: Always On SEM (Jan-Dec) | Z4: Macan 4 Spirit Pack (Feb - May) | AA4: Macan with Equipment Pack (September - October) | AB4: Always On SEM (Jan-Dec) | AC4: Social,Search,Programmatic,Other Online Channel | AD4: Branded Content, YouTube, CTV, Cinemas | AE4: Engagement,Conversion | AF4: Impressions,Cost per Million (CPM),Click Through Rate (CTR),Model page visit,Others | AG4: Lead & incoming orders generation | AH4: 200K | AI4: 13/03/2026 | AJ4: 09/08/2026 | AK4: Yes | AL4: primary | AM4: secondary | AN4: Yes | AO4: Yes | AP4: No | AQ4: Yes | AR4: Search | AT4: Conversion | AU4: Impressions,Click Through Rate (CTR),Model page visit | AW4: 50K | AX4: 01/01/2026 | AY4: 31/12/2026 | AZ4: Yes | BA4: primary | BB4: secondary | BC4: No | BD4: No | BE4: No | BF4: No | BV4: Social,Search,Programmatic,Other Online Channel | BW4: YouTube & CTV | BX4: Awareness,Attraction,Engagement,Conversion | BY4: Impressions,Cost per Million (CPM),Click Through Rate (CTR),Model page visit,Others | BZ4: Lead conversion & order income | CA4: 150K | CB4: 16/03/2026 | CC4: 09/08/2026 | CD4: Yes | CE4: primary | CF4: secondary | CG4: Yes | CH4: Yes | CI4: No | CJ4: Yes | CK4: Other Online Channel | CL4: CTV | CM4: Awareness,Conversion | CN4: Impressions,Model page visit | CP4: 140K | CQ4: 03/05/2026 | CR4: 03/06/2026 | CS4: Yes | CT4: primary | CU4: secondary | CV4: No | CW4: No | CX4: No | CY4: No | CZ4: Search | DB4: Conversion | DC4: Impressions,Model page visit | DE4: 50K | DF4: 01/01/2026 | DG4: 31/12/2026 | DH4: Yes | DI4: primary | DJ4: secondary | DK4: No | DL4: No | DM4: No | DN4: No | DO4: Social,Programmatic,Other Online Channel | DP4: Brand Days | DQ4: Conversion | DR4: Impressions,Cost per Million (CPM),Click Through Rate (CTR),Model page visit,Others | DS4: Lead generation & order income | DT4: 225K | DU4: 12/02/2026 | DV4: 10/05/2026 | DW4: Yes | DX4: primary | DY4: secondary | DZ4: Yes | EA4: Yes | EB4: No | EC4: Yes | ED4: Social | EF4: Awareness,Engagement,Conversion | EG4: Impressions,Cost per Million (CPM),Click Through Rate (CTR),Model page visit,Others | EH4: Lead generation and order income | EI4: 15K (we will have DOOH as well with a big part of the investment) | EJ4: 15/09/2026 | EK4: 15/11/2026 | EL4: Yes | EM4: primary | EN4: secondary | EO4: No | EP4: Yes | EQ4: No | ER4: No | ES4: Search | EU4: Conversion | EV4: Impressions,Cost per Million (CPM),Click Through Rate (CTR),Model page visit | EX4: 50K | EY4: 01/01/2026 | EZ4: 31/12/2026 | FA4: Yes | FB4: primary | FC4: secondary | FD4: No | FE4: No | FF4: No | FG4: No | FH4: We need to speak with our PHD Team about Audiences in order to complete the questionnarie | FI4: 2026
A5: 46121.549 | B5: 46121.567 | C5: IP Address | D5: 217.192.62.33 | E5: 100 | F5: 1580 | G5: True | H5: 46121.567 | I5: R_2FrobhtgIFhiXd8 | N5: 46.9912 | O5: 8.5212 | P5: anonymous | Q5: EN | R5: PCH | S5: Campaign 4 (Cayenne E4):,Campaign 5 (Cayenne E4):,Campaign 6 (Cayenne E4):,Campaign 7 (Macan H2):,Campaign 8 (Macan H2): | W5: PlanIt-ID = 20161912 | X5: PlanIt-ID = 20057186 (different model types) | Y5: Additional digital campaign in september (no set up yet) | Z5: PlanIt-ID = 20057186 (different model types) | AA5: Additional digital campaign in september (no set up yet) | BV5: Social,Search,Programmatic,Other Online Channel | BW5: CTV | BX5: Awareness,Engagement,Conversion | BY5: Cost per Million (CPM),Click Through Rate (CTR),Model page visit,Cost per Lead (CPL) | CA5: CHF 380'000.- | CB5: 26.06.2026 | CC5: 26.07.2026 | CD5: No | CE5: Strategic Target Groups | CF5: Exsiting Targes Group | CG5: Yes | CH5: Yes | CI5: Yes | CJ5: No | CK5: Search | CM5: Engagement,Conversion | CN5: Model page visit,Configuration | CP5: CHF 100'000.- | CQ5: 01.01.2026 | CR5: 31.12.2026 | CS5: No | CT5: Age targeting | CU5: Key Words | CV5: No | CW5: No | CX5: No | CY5: Yes | CZ5: Social,Other Online Channel | DA5: Display | DB5: Engagement,Conversion | DC5: Configuration,Dealer contact form submitted (DCFS),Cost per Lead (CPL) | DE5: CHF 150'000.- | DF5: 07.09.2026 | DG5: 05.10.2026 | DH5: No | DI5: Stragetic target groups | DJ5: excisting targes group | DK5: Yes | DL5: Yes | DM5: Yes | DN5: No | DO5: Search | DQ5: Engagement,Conversion | DR5: Model page visit,Configuration,Dealer contact form submitted (DCFS) | DT5: CHF 100'000.- | DU5: 01.01.2026 | DV5: 31.12.2026 | DW5: No | DX5: Age targeting | DY5: Keywords | DZ5: No | EA5: No | EB5: No | EC5: Yes | ED5: Social,Other Online Channel | EE5: Display | EF5: Engagement,Conversion | EG5: Configuration,Dealer contact form submitted (DCFS),Cost per Lead (CPL) | EI5: CHF 150'000.- | EJ5: 07.09.2026 | EK5: 05.10.2026 | EL5: No | EM5: Strategic target groups | EN5: Excisting target group | EO5: Yes | EP5: Yes | EQ5: Yes | ER5: No | FI5: 2026
A6: 46119.711 | B6: 46125.475 | C6: IP Address | D6: 62.101.125.121 | E6: 100 | F6: 498063 | G6: True | H6: 46125.475 | I6: R_81sa7WxhWrVZi1v | N6: 45.413 | O6: 11.8806 | P6: anonymous | Q6: EN | R6: PIT | S6: Campaign 4 (Cayenne E4):,Campaign 5 (Cayenne E4):,Campaign 7 (Macan H2): | W6: Cayenne E4 | X6: Campagna DCO | Z6: Campagna DCO | BV6: Social,Programmatic | BX6: Awareness,Conversion | BY6: Cost per Million (CPM),Dealer contact form submitted (DCFS) | CA6: 100.000€ | CB6: 15/02/2026 | CC6: 31/12/2026 | CD6: Yes | CE6: Custom affinity audience | CF6: Retargeting audience | CG6: Yes | CH6: Yes | CI6: Yes | CJ6: Yes | CK6: Programmatic | CM6: Awareness,Engagement | CN6: Dealer contact form submitted (DCFS) | CP6: 100.000€ | CQ6: 15/02/2026 | CR6: 31/12/2026 | CS6: Yes | CT6: Custom affinity audience | CU6: Retargeting | CV6: Yes | CW6: Yes | CX6: Yes | CY6: Yes | DO6: Social,Programmatic | DQ6: Awareness,Conversion | DR6: Impressions,Dealer contact form submitted (DCFS) | DT6: 190.000€ | DU6: 15/02/2026 | DV6: 31/12/2026 | DW6: Yes | DX6: Custom adience | DY6: retargeting and cdp | DZ6: Yes | EA6: Yes | EB6: Yes | EC6: Yes | FH6: There is an error on the firts E4 Campaign, that one was related to the period nov 25-jan 26 | FI6: 2026
A7: 46119.708 | B7: 46125.512 | C7: IP Address | D7: 163.116.173.33 | E7: 100 | F7: 501480 | G7: True | H7: 46125.512 | I7: R_2amLuZthLB8sfL7 | N7: 51.2222 | O7: 6.7788 | P7: anonymous | Q7: EN | R7: PD | S7: Campaign 1 (Cayenne E3II):,Campaign 2 (Cayenne E3II):,Campaign 3 (Cayenne E3II):,Campaign 4 (Cayenne E4):,Campaign 5 (Cayenne E4):,Campaign 6 (Cayenne E4):,Campaign 7 (Macan H2):,Campaign 8 (Macan H2):,Campaign 9 (Macan H2): | T7: 20130912_20130912_POR_RNG_RNG_DEU_T1_NU_EUR_2026-02-22_2026-12-30_LOCAL-AOPROGRAMMATICPERFORMANCE2026 | U7: 20056448_20056448_POR_RNG_RNG_DEU_T1_NU_EUR_2025-12-31_2026-12-30_LOCAL-SEANATIONAL2026 | V7: 20205848_20205848_POR_CAY_SUV_DEU_T1_NU_EUR_2025-12-31_2026-12-30_LOCAL-CAYENNEE4CAYENNEFAMILY | W7: 20130912_20130912_POR_RNG_RNG_DEU_T1_NU_EUR_2026-02-22_2026-12-30_LOCAL-AOPROGRAMMATICPERFORMANCE2026 | X7: 20056448_20056448_POR_RNG_RNG_DEU_T1_NU_EUR_2025-12-31_2026-12-30_LOCAL-SEANATIONAL2026 | Y7: 20205848_20205848_POR_CAY_SUV_DEU_T1_NU_EUR_2025-12-31_2026-12-30_LOCAL-CAYENNEE4CAYENNEFAMILY | Z7: 20172604_20172604_POR_MAC_SUV_DEU_T1_NU_EUR_2026-02-20_2026-10-31_LOCAL-MACANDIENSTWAGENPUSH2026 | AA7: 20130912_20130912_POR_RNG_RNG_DEU_T1_NU_EUR_2026-02-22_2026-12-30_LOCAL-AOPROGRAMMATICPERFORMANCE2026 | AB7: 20056448_20056448_POR_RNG_RNG_DEU_T1_NU_EUR_2025-12-31_2026-12-30_LOCAL-SEANATIONAL2026 | AC7: Programmatic | AE7: Conversion | AF7: Dealer contact form submitted (DCFS) | AH7: 185000 € (HY2 is not yet planned out but a separate budget is allocated for it) | AI7: 23.02.2026 | AJ7: 30.06.2026 | AK7: Yes | AL7: Complex Audience Setup including Prospecting and LAL and Retargeting Audiences | AM7: see above | AN7: Yes | AO7: Yes | AP7: Yes | AQ7: Yes | AR7: Search | AT7: Conversion | AU7: Dealer contact form submitted (DCFS) | AW7: 182500 € | AX7: 05.01.2026 | AY7: 31.12.2026 | AZ7: Yes | BA7: Keyword Targeting | BB7: see above | BC7: No | BD7: No | BE7: No | BF7: Yes | BG7: Programmatic | BI7: Attraction,Engagement | BJ7: Configuration | BL7: 70000 € | BM7: 18.05.2026 | BN7: 28.06.2026 | BO7: Yes | BP7: tbd | BQ7: tbd | BR7: Yes | BS7: Yes | BT7: Yes | BU7: No | BV7: Programmatic | BX7: Conversion | BY7: Dealer contact form submitted (DCFS) | CA7: 190000 € | CB7: 23.02.2026 | CC7: 31.10.2026 | CD7: No | CE7: Complex Audience Setup including Prosecting LAL and Retargeting Audiences | CF7: see above | CG7: Yes | CH7: Yes | CI7: Yes | CJ7: Yes | CK7: Search | CM7: Conversion | CN7: Dealer contact form submitted (DCFS) | CP7: 146000 € | CQ7: 05.01.2026 | CR7: 31.12.2026 | CS7: Yes | CT7: Keyword Targeting | CU7: see above | CV7: No | CW7: No | CX7: No | CY7: Yes | CZ7: Programmatic | DB7: Attraction,Engagement | DC7: Configuration | DE7: 70000 € | DF7: 18.05.2026 | DG7: 28.06.2026 | DH7: Yes | DI7: tbd | DJ7: tbd | DK7: Yes | DL7: Yes | DM7: Yes | DN7: No | DO7: Social,Programmatic | DQ7: Engagement,Conversion | DR7: Model page visit,Dealer contact form submitted (DCFS) | DT7: 170000 € | DU7: 07.04.2026 | DV7: 16.08.2026 | DW7: No | DX7: Business People with high income who look for a luxury company car | DY7: Retargeting on Macan Interest like Page Visitors or Dealer Contact Starters for a Macan | DZ7: Yes | EA7: No | EB7: Yes | EC7: Yes | ED7: Programmatic | EF7: Conversion | EG7: Dealer contact form submitted (DCFS) | EI7: 190000 € | EJ7: 23.02.2026 | EK7: 31.10.2026 | EL7: No | EM7: Complex Audience Setup including Prospecting LAL and Retargeting Audiences | EN7: see above | EO7: Yes | EP7: Yes | EQ7: Yes | ER7: Yes | ES7: Search | EU7: Conversion | EV7: Dealer contact form submitted (DCFS) | EX7: 182500 € | EY7: 05.01.2026 | EZ7: 31.12.2026 | FA7: No | FB7: Keyword Targeting | FC7: see above | FD7: No | FE7: No | FF7: No | FG7: Yes | FH7: The AOPROGRAMMATICPERFORMANCE2026 campaign contains all three models and is already live and running. We made a mistake for the Macan, the runtime is also 23.02. - 31.10.2026 and it's not flexible. The CAYENNEE4CAYENNEFAMILY campaign is not fully planned out yet for both models, so the info is still tbd right now. We had a Demand Gen Flight in mind, which could be planned out via CTG. The MACANDIENSTWAGENPUSH2026 campaign is only focussing on a specific Macan configuration (&lt;100.000€) as it now can be bought as a company car in Germany since last year, as we had a change in the tax laws. But only if it stays in the &lt;100.000€ budget. | FI7: 2026
A8: 46120.483 | B8: 46125.609 | C8: IP Address | D8: 165.85.12.42 | E8: 100 | F8: 442875 | G8: True | H8: 46125.609 | I8: R_8RxClnSSoMpb4D2 | N8: 52.2299 | O8: 21.0093 | P8: anonymous | Q8: EN | R8: PPL | S8: Campaign 1 (Cayenne E3II):,Campaign 7 (Macan H2): | T8: Q1 2026 digital campaign done, media incl.: YouTube, Demand Gen, Performance Max, Search, Meta, Display Ads, | Z8: Ongoing 2026 digital campaign starting in April, media incl.: Search & Meta Inventory Ads | AC8: Social,Search,Programmatic | AE8: Engagement,Conversion | AF8: Configuration,Cost Per Lead (CPL) | AH8: 2 651 250 PLN net (media) | AI8: 02/01/2026 | AJ8: 31/03/2026 | AK8: No | AL8: TBC | AM8: TBC | AQ8: Yes | DO8: Social,Search | DQ8: Engagement,Conversion | DR8: Configuration,Dealer contact form submitted (DCFS),Cost per Lead (CPL) | DT8: 593 300 PLN net | DU8: 10/04/2026 | DV8: 31/12/2026 | DW8: Yes | DX8: TBU | DY8: TBU | EC8: Yes | FH8: Regarding the audiences - let me confirm it with our PHD colleagues. Kindly ask you to follow up on it on emails. Thanks! | FI8: 2026
A9: 46120.566 | B9: 46125.616 | C9: IP Address | D9: 46.27.76.178 | E9: 100 | F9: 436326 | G9: True | H9: 46125.616 | I9: R_8ghXpShvcwYnCS4 | N9: 40.4153 | O9: -3.694 | P9: anonymous | Q9: EN | R9: PIB SPA | FI9: 2026
