Workbook
Name BrandLookup: INDEX('[1]Drop Downs'!$G$2:$G$12,MATCH('[1]Local PRF Calculator'!$E$6,'[1]Drop Downs'!$F$2:$F$12,0))
Name BrandLookup: INDEX('Drop Downs'!$G$2:$G$12,MATCH('Local PRF Calculator'!$E$6,'Drop Downs'!$F$2:$F$12,0))

Sheet User Guide
B1: V1.4
C4: General Instructions
C5: All blue cells should be completed in the Fee Summary, Local PRF Calculator and BAH Perf Fee Reconciliations tabs.
C6: Responsibility for completion of each entry is defined below by [Team] as relevant
C7: Local Fee Calculator inputs should be copied into the Local FTE Model / Local Commission Model tab as appropriate (based on local market fee structure) [Local Finance Team]
C8: FX Rates tab to be updated at start of year to reflect latest VWG FX rates
C12: Fee Summary
C13: Year, Brand, Market & Date updated [E5-E8] should be checked to ensure accuracy if revising a previously completed template. [All Users]
C14: Market Fee Type [E10] to be defined based on locally agreed terms. [Local Account Team / Finance]
C18: Local PRF Calculator
C19: Service Scores [J6-J8] - to be completed based on outcomes of biannual service surveys. Both scores are required for Service related components of the fee to calculate through. [Global Account Team]
C20: Media Pricing Delivery [I13-J14] - select Actual or Forecast to indicate whether result reflects final audited position and input % delivery. Prior to audit, OMG Global Investment can provide YTD / Forecast positions to allow a forecast bonus position to be calculated. Post-Audit, the EBQ aligned position can be input to finalise bonus position. Confirmation of Addressibility required to access Pricing related components. [Global Investment Team]
C21: Digital Guidelines Gate [E21] will autopopulate based on whether Digital Guidelines have been met [BAH Compliance Team]
... C53: Campaign Reconciled? [Column U] to be used to track where any relevant Reconciled Campaign Payment [Column AA] has been billed to client

Sheet PRF Structure

Sheet Fee Summary
B2: Please complete all highlighted cells
C5: =INDEX('Drop Downs'!$G$2:$G$12,MATCH('Local PRF Calculator'!$E$6,'Drop Downs'!$F$2:$F$12,0)) -> #VALUE! | D5: Year | E5: 2025
D6: Brand | E6: Porsche
D7: Market | E7: Australia
D8: Date Updated
D9: FX Rate (LC to EUR) | E9: =IFERROR(IF(E7="Select Market","Please complete Market",IF(E7="Central",VLOOKUP(E6&" "&E7,'FX Rates'!$B$4:$E$42,4,FALSE),VLOOKUP(E7,'FX Rates'!$B$4:$E$42,4,FALSE))),"FX Not Found") -> 0.62
D10: Market Fee Type | E10: FTE/Commission?
C14: Local Fee | D14: Local Currency | E14: EUR
C15: Local Nominal Fee (Total Committed fee) | D15: =IF(E10="FTE",#REF!,IF('Fee Summary'!E10="Commission",'Local Commission Model'!H15,IF(E10="Hybrid",#REF!+'Local Commission Model'!H15,"Please define fee type"))) -> Please define fee type | E15: =IFERROR(D15*$E$9,"Please complete Market") -> Please complete Market
C16: =IF(OR(E6="Porsche",E6="Bentley",E6="MAN Energy Solutions",E6="MAN Truck & Bus"),"","Local Base Fee (80% of Nominal Fee - paid through year)") | D16: =IFERROR(IF(OR(E6="Porsche",E6="Bentley",E6="MAN Energy Solutions",E6="MAN Truck & Bus"),"",D15*0.8),"TBC") | E16: =IFERROR(IF(OR(E6="Porsche",E6="Bentley",E6="MAN Energy Solutions",E6="MAN Truck & Bus"),"",E15*0.8),"TBC")
C18: Biddable Activation Hub (BAH) Fee
C19: BAH Nominal Fee (Total Commission exc Ad Ops Levy) | D19: ='BAH Perf Fee Reconciliations'!D15 -> 49062.5 | E19: =IFERROR(D19*E9,"TBC") -> 30418.75
C21: =IF(OR(E6="Porsche",E6="Bentley",E6="MAN Energy Solutions",E6="MAN Truck & Bus"),"","Total Fees")
C22: =IF(OR(E6="Porsche",E6="Bentley",E6="MAN Energy Solutions",E6="MAN Truck & Bus"),"","Total Fee eligible for bonus (Nominal Fees)") | D22: =IF(OR(E6="Porsche",E6="Bentley",E6="MAN Energy Solutions",E6="MAN Truck & Bus"),"",IFERROR(D19+D15,"TBC")) | E22: =IF(OR(E6="Porsche",E6="Bentley",E6="MAN Energy Solutions",E6="MAN Truck & Bus"),"",IFERROR(E19+E15,"TBC"))
C23: =IF(OR(E6="Porsche",E6="Bentley",E6="MAN Energy Solutions",E6="MAN Truck & Bus"),"","Billed fee (Local Base Fee + BAH Nominal Fee)") | D23: =IF(OR(E6="Porsche",E6="Bentley",E6="MAN Energy Solutions",E6="MAN Truck & Bus"),"",IFERROR(D19+D16,"TBC")) | E23: =IF(OR(E6="Porsche",E6="Bentley",E6="MAN Energy Solutions",E6="MAN Truck & Bus"),"",IFERROR(E19+E16,"TBC"))
D27: Local Currency | E27: EUR
C28: =IF(OR(E6="Porsche",E6="Bentley",E6="MAN Energy Solutions",E6="MAN Truck & Bus"),"","Total Fee @ Max Bonus (120% of Nominal Fee)") | D28: =IFERROR(IF(OR(E6="Porsche",E6="Bentley",E6="MAN Energy Solutions",E6="MAN Truck & Bus"),"",1.2*D22),"TBC") | E28: =IFERROR(IF(OR(E6="Porsche",E6="Bentley",E6="MAN Energy Solutions",E6="MAN Truck & Bus"),"",1.2*E22),"TBC")
C29: =IF(OR(E6="Porsche",E6="Bentley",E6="MAN Energy Solutions",E6="MAN Truck & Bus"),"","Actual Fee Payable (% of Nominal Fee)") | D29: =IF(OR(E6="Porsche",E6="Bentley",E6="MAN Energy Solutions",E6="MAN Truck & Bus"),"",'Local PRF Calculator'!E9)
C30: =IF(OR(E6="Porsche",E6="Bentley",E6="MAN Energy Solutions",E6="MAN Truck & Bus"),"Total Nominal Fee","Actual Fee Payable") -> Total Nominal Fee | D30: =IFERROR(IF(OR(E6="Porsche",E6="Bentley",E6="MAN Energy Solutions",E6="MAN Truck & Bus"),D19+D15,IFERROR(D22*D29,"TBC")),"TBC") -> TBC | E30: =IFERROR(IF(OR(E6="Porsche",E6="Bentley",E6="MAN Energy Solutions",E6="MAN Truck & Bus"),E19+E15,IFERROR(E22*D29,"TBC")),"TBC") -> TBC
C31: =IF(OR(E6="Porsche",E6="Bentley",E6="MAN Energy Solutions",E6="MAN Truck & Bus"),"","Reconciled Fee Payment (difference between Billed and Actual Fee Payable)") | D31: =IF(OR(E6="Porsche",E6="Bentley",E6="MAN Energy Solutions",E6="MAN Truck & Bus"),"",IFERROR(D30-D23,"TBC")) | E31: =IF(OR(E6="Porsche",E6="Bentley",E6="MAN Energy Solutions",E6="MAN Truck & Bus"),"",IFERROR(E30-E23,"TBC"))
C32: =IF(E5="Select Year","Total Annual Fee including Performance reconciliations & Ad Ops Levy","Total "&E5&" Fee including Biddable reconciliations & Ad Ops Levy") -> Total 2025 Fee including Biddable reconciliations & Ad Ops Levy | D32: =IFERROR(D30+'BAH Perf Fee Reconciliations'!D18+SUM('BAH Perf Fee Reconciliations'!G:G),"TBC") -> TBC | E32: =IFERROR(D32*$E$9,"TBC") -> TBC

Sheet Local FTE Model
B2: VWG Transformation 2025: FTE Calculator
B5: Market | C5: Australia
B6: Brand | C6: Porsche
B7: Year | C7: 2025
B8: FX Rate | C8: 0.62
B11: Scope | C11: Department/Specialism | D11: Staff Level | E11: Title | F11: Total 2025 Rate Card (LC) | I11: 2025 Agreed FTE % | J11: 2025 Agreed Fee | L11: 2026 Agreed FTE % | M11: 2026 Agreed Fee | O11: Variance FTE% | P11: Variance Fee (LC)
B13: Total Fees | J13: =SUM(J15:J18) -> 170056.1 | M13: =SUM(M15:M18) -> 288304.7 | P13: =M13-J13 -> 118248.6
B15: In-Scope Biddable (via %Commissions) | M15: =[2]MarketBrand_Commission!H35 -> 102500 | S15: linked to external file. But will be re-populated by finance team anyway
B16: In-Scope Central Data AdOps (via %Levy) | M16: =[2]MarketBrand_Commission!G35 -> 20000
B18: Local fees with 2026 Discount on Base Remuneration | I18: =I20 -> 2.205 | J18: =J20 -> 170056.1 | L18: =L20 -> 2.205 | M18: =M20*97.5% -> 165804.7 | O18: =L18-I18 -> 0 | P18: =M18-J18 -> -4251.4026
B20: Local Fees | I20: =SUM(I21:I190) -> 2.205 | J20: =SUM(J21:J190) -> 170056.1 | L20: =SUM(L21:L190) -> 2.205 | M20: =SUM(M21:M190) -> 170056.1 | O20: =SUM(O21:O190) -> 0 | P20: =SUM(P21:P190) -> 0
B21: In-Scope FTE Local | C21: Media Leadership, Process Management & Coordination | D21: Director | E21: Group Client Director | F21: 131084.8 | I21: 0.175 | J21: =IFERROR(F21*I21,0) -> 22939.84 | L21: 0.175 | M21: =IFERROR(F21*L21,0) -> 22939.84 | O21: =L21-I21 -> 0 | P21: =M21-J21 -> 0
B22: In-Scope FTE Local | C22: Media Planning | D22: Senior | E22: Senior Planning / Strategy /Operations Manager | F22: 85174.412 | I22: 0.175 | J22: =IFERROR(F22*I22,0) -> 14905.522 | L22: 0.175 | M22: =IFERROR(F22*L22,0) -> 14905.522 | O22: =L22-I22 -> 0 | P22: =M22-J22 -> 0
B23: In-Scope FTE Local | C23: Media Planning | D23: Manager | E23: Planning / Strategy / Operations Manager | F23: 74426.934 | I23: 0.175 | J23: =IFERROR(F23*I23,0) -> 13024.714 | L23: 0.175 | M23: =IFERROR(F23*L23,0) -> 13024.714 | O23: =L23-I23 -> 0 | P23: =M23-J23 -> 0
B24: In-Scope FTE Local | C24: Media Leadership, Process Management & Coordination | D24: Director | E24: Group Client Director | F24: 131084.8 | I24: 0.175 | J24: =IFERROR(F24*I24,0) -> 22939.84 | L24: 0.175 | M24: =IFERROR(F24*L24,0) -> 22939.84 | O24: =L24-I24 -> 0 | P24: =M24-J24 -> 0
B25: In-Scope FTE Local | C25: Media Planning | D25: Manager | E25: Planning / Strategy / Operations Manager | F25: 74426.934 | I25: 0.2625 | J25: =IFERROR(F25*I25,0) -> 19537.07 | L25: 0.2625 | M25: =IFERROR(F25*L25,0) -> 19537.07 | O25: =L25-I25 -> 0 | P25: =M25-J25 -> 0
B26: In-Scope FTE Local | C26: Media Planning | D26: Junior | E26: Planning / Strategy / Operations Executive/ Analyst | F26: 56004.274 | I26: 0.2625 | J26: =IFERROR(F26*I26,0) -> 14701.122 | L26: 0.2625 | M26: =IFERROR(F26*L26,0) -> 14701.122 | O26: =L26-I26 -> 0 | P26: =M26-J26 -> 0
B27: In-Scope FTE Local | C27: Media Planning | D27: Junior | E27: Planning / Strategy / Operations Executive/ Analyst | F27: 56004.274 | I27: 0.525 | J27: =IFERROR(F27*I27,0) -> 29402.244 | L27: 0.525 | M27: =IFERROR(F27*L27,0) -> 29402.244 | O27: =L27-I27 -> 0 | P27: =M27-J27 -> 0
B28: In-Scope FTE Local | C28: Media Buying Above The Line (ATL) | D28: Senior | E28: Senior Planning / Strategy /Operations Manager | F28: 95633.005 | I28: 0.035 | J28: =IFERROR(F28*I28,0) -> 3347.1552 | L28: 0.035 | M28: =IFERROR(F28*L28,0) -> 3347.1552 | O28: =L28-I28 -> 0 | P28: =M28-J28 -> 0
B29: In-Scope FTE Local | C29: Media Planning | D29: Manager | E29: Planning / Strategy / Operations Manager | F29: 74426.934 | I29: 0.04 | J29: =IFERROR(F29*I29,0) -> 2977.0774 | L29: 0.04 | M29: =IFERROR(F29*L29,0) -> 2977.0774 | O29: =L29-I29 -> 0 | P29: =M29-J29 -> 0
B30: In-Scope FTE Local | C30: Media Planning | D30: Junior | E30: Planning / Strategy / Operations Executive/ Analyst | F30: 56004.274 | I30: 0.09 | J30: =IFERROR(F30*I30,0) -> 5040.3846 | L30: 0.09 | M30: =IFERROR(F30*L30,0) -> 5040.3846 | O30: =L30-I30 -> 0 | P30: =M30-J30 -> 0
B31: In-Scope FTE Local | C31: Media Buying Above The Line (ATL) | D31: Director | E31: Planning / Strategy / Operations Director | F31: 127791.45 | I31: 0.05 | J31: =IFERROR(F31*I31,0) -> 6389.5724 | L31: 0.05 | M31: =IFERROR(F31*L31,0) -> 6389.5724 | O31: =L31-I31 -> 0 | P31: =M31-J31 -> 0
B32: In-Scope FTE Local | C32: Media Buying Above The Line (ATL) | D32: Junior | E32: Planning / Strategy / Operations Executive/ Analyst | F32: 57143.37 | I32: 0.2 | J32: =IFERROR(F32*I32,0) -> 11428.674 | L32: 0.2 | M32: =IFERROR(F32*L32,0) -> 11428.674 | O32: =L32-I32 -> 0 | P32: =M32-J32 -> 0
... B36: In-Scope FTE Local | C36: KPI Audit | D36: Junior | E36: Account Exec | F36: 61793.609 | I36: 0.01 | J36: =IFERROR(F36*I36,0) -> 617.93609 | L36: 0.01 | M36: =IFERROR(F36*L36,0) -> 617.93609 | O36: =L36-I36 -> 0 | P36: =M36-J36 -> 0

Sheet Local Commission Model
B2: VWG Transformation 2025: Commission Calculator
B5: Market | C5: ='Fee Summary'!E7 -> Australia
B6: Brand | C6: ='Fee Summary'!E6 -> Porsche
B7: Year | C7: ='Fee Summary'!E5 -> 2025
B8: FX Rate | C8: ='Fee Summary'!E9 -> 0.62
E11: Local - Biddable for non-Hubbed Markets
C12: Offline | D12: Online-Display | E12: Search | F12: Social | G12: Programmatic | H12: Total Local (LC)
B13: Spend (LC) | C13: 6504800 | D13: 15130816 | H13: =SUM(C13:G13) -> 21635616
B14: Commission Rate % | C14: 0.015 | D14: 0.028 | E14: 0.029 | F14: 0.029 | G14: 0.041
B15: Commission Fees (LC) | C15: =C13*C14 -> 97572 | D15: =D13*D14 -> 423662.85 | E15: =E13*E14 -> 0 | F15: =F13*F14 -> 0 | G15: =G13*G14 -> 0 | H15: =SUM(C15:G15) -> 521234.85
B18: 3rd Party Tech Data Fees (pass through) | D18: =D13*0.01 -> 151308.16
E21: Biddable Activation Hub (BAH)
E22: Search | F22: Social | G22: Programmatic | H22: Central Biddable (LC)
B23: Spend (LC) | E23: 1000000 | F23: 1000000 | G23: 1000000 | H23: =SUM(E23:G23) -> 3000000
B24: Commission Rate % | E24: 0.029 | F24: 0.029 | G24: 0.041
B25: Commission Fees (LC) | E25: =E23*E24 -> 29000 | F25: =F23*F24 -> 29000 | G25: =G23*G24 -> 41000 | H25: =SUM(E25:G25) -> 99000
B28: 3rd Party Tech Data Fees (pass through examples- Campaign Manager, GOA, SA360, Smartly) | E28: =E23*0.02 -> 20000 | F28: =F23*0.0275 -> 27500 | G28: =G23*0.1 -> 100000 | H28: =SUM(E28:G28) -> 147500
B29: Digital Tax (Google&Amazon) | E29: =E23*0.03 -> 30000 | F29: 0 | G29: 0 | H29: =SUM(E29:G29) -> 30000
B30: Governance Costs (Example - IAS, Sccope3) | E30: 0 | F30: =F23*0.02 -> 20000 | G30: =G23*0.02 -> 20000 | H30: =SUM(E30:G30) -> 40000
G33: AdOps Fees (LC) | H33: Biddable Revenue (LC)
G34: 0.0025
G35: =(SUM(D13:G13)+SUM(E23:G23))*G34 -> 45327.04 | H35: =SUM(E15:G15)+SUM(E25:G25) -> 99000

Sheet Local PRF Calculator
B2: Please complete all highlighted cells
C5: =INDEX('Drop Downs'!$G$2:$G$12,MATCH('Local PRF Calculator'!$E$6,'Drop Downs'!$F$2:$F$12,0)) -> #VALUE! | D5: Year | E5: =IF('Fee Summary'!E5="Select Year","Please Complete Summary Tab",'Fee Summary'!E5) -> 2025 | I5: Service Scores
D6: Brand | E6: =IF('Fee Summary'!E6="Select brand","Please Complete Summary Tab",'Fee Summary'!E6) -> Porsche | I6: =IF($E$5="Please complete summary tab","Previous Year H2",$E$5-1&" H2") -> 2024 H2 | J6: 3.3
D7: Market | E7: =IF('Fee Summary'!E7="Select Market","Please Complete Summary Tab",'Fee Summary'!E7) -> Australia | I7: =IF($E$5="Please complete summary tab","Current Year H1",$E$5&" H1") -> 2025 H1
D8: Date Updated | E8: =IF('Fee Summary'!E8="","",'Fee Summary'!E8) | I8: =IF($E$5="Please complete summary tab","Current Year H2",$E$5&" H2") -> 2025 H2
D9: Total Fee Earned (% of Nominal Fee) | E9: =IF(OR(E14="TBC",E15="TBC"),"TBC",0.8+SUM(E14:E15)+IF(E25="Yes",SUM(E30:E31))) -> TBC | I9: =IF($E$5="Please complete summary tab","Current Year Average",$E$5&" Average") -> 2025 Average | J9: =IFERROR(AVERAGE(J7:J8),"TBC") -> TBC
C13: Nominal Fee Component | D13: % Fee Available | E13: % Fee Achieved | I13: Media Pricing Delivery
C14: On Target Service Delivery | D14: 0.1 | E14: =IF(OR(J7="",J8=""),"TBC",IF(OR(AND(J6<2,J7<2),AND(J7<2,J8<2)),0,D14)) -> TBC | I14: Actual Delivery (%)
C15: On Target Pricing | D15: 0.1 | E15: =IF(J14="","TBC",IF(J15="Yes",IF(J14<-D15,0,IF(J14>-0.02,D15,D15+J14)),0)) -> TBC | I15: Addressability % achieved? | J15: Yes/No?
C19: Bonus Gates | E19: Gate Achieved?
C20: Nominal Value Gate (Full nominal fee achieved) | E20: =IF(OR(E15="TBC",E14="TBC"),"TBC",IF(SUM(E14:E15)=SUM(D14:D15),"Yes","No")) -> TBC
C21: Digital Guidelines Gate(Compliance with Digital Guidelines) | E21: =IF('Digital Media Guidelines'!C26="Compliant","Yes","No") -> No
C22: Digital Activation Hub Gate (Annual Biddable Media Performance) | E22: {=IF(E5=2025,"N/A",IF(SUMPRODUCT(IF('BAH Perf Fee Reconciliations'!P:P="Yes",1,0),'BAH Perf Fee Reconciliations'!O:O,'BAH Perf Fee Reconciliations'!E:E)/SUMIF('BAH Perf Fee Reconciliations'!P:P,"Yes",'BAH Perf Fee Reconciliations'!E:E)>=0,"Yes","No"))} -> N/A
C23: ="Affordability Gate ("&IF('Fee Summary'!E6="Select Brand","<Brand> met profit goals)",'Fee Summary'!E6&" met profit goals)") -> Affordability Gate (Porsche met profit goals) | E23: Yes/No?
C24: Media Price Savings Gate (2025 Only - global over-delivery achieved) | E24: Yes/No?
C25: Bonus Payable? | E25: =IF(E5=2025,IF(AND(E20="Yes",E21="Yes",E23="Yes",OR(E24="N/A",E24="Yes")),"Yes","No"),IF(AND(E20="Yes",E21="Yes",E22="Yes",E23="Yes"),"Yes","No")) -> No
C29: Bonus Component | D29: % Bonus Allocation | E29: % Bonus Achieved
C30: Brand/Business KPI over-delivery | D30: 0.1 | E30: =IF(E25="no","N/A",'BusinessBrand KPIs'!K18/12.5%*D30) -> N/A
C31: Exceptional Service | D31: 0.1 | E31: =IF(E25="No","N/A",IF(OR(J7="",J8=""),"TBC",IF(AND(J9>=3,J9<3.6),D31*0.5,IF(J9>=3.6,D31,0)))) -> N/A

Sheet Digital Media Guidelines
B2: Brand | C2: ='Fee Summary'!E6 -> Porsche
B3: Markets | C3: ='Fee Summary'!E7 -> Australia
B4: Platforms / Source of Truth | C4: Biddable Platforms
B5: Reporting Period | C5: Q2 2025
B6: Date of report | C6: 45853
B9: Principle | C9: Measurement Type | D9: Minimum Threshold | E9: Result | F9: Result vs Goal | G9: Hit / Miss | H9: Channel(s) Spend | I9: Non-Compliant Spend
B10: Campaign Naming Taxonomy | C10: > 98% Spend to be compliant | D10: 0.98
B11: Ad Verification | C11: > 90% Spend to be compliant | D11: 0.9
B12: Viewability | C12: < 12% share of programmatic spend below WFA benchmarks for viewability in the market | D12: 0.12
B13: Brand Unsafe Delivery | C13: < 3% share of programmatic spend on reported brand unsafe | D13: 0.03
B14: Working Media Rate | C14: Min of 83% working media rate | D14: 0.83
B16: Principle | C16: Measurement Type | D16: Market Variable Rate (WFA Viewability Target) | E16: Viewability Result | F16: Result vs WFA Viewability Target | G16: Weighted Average
B17: Viewability - Display | C17: WFA Target | F17: =E17-D17 -> 0
B18: Viewability - Video | C18: WFA Target | F18: =E18-D18 -> 0
B20: Compliance Outcome | C20: Spend (EUR) | D20: Target Compliance Spend %
B21: Total Biddable Spend (E2E)
B22: Programmatic Spend (DSP's)
B23: Programmatic Spend % Below Thresholds
B24: Total Biddable Spend Below Threshold | C24: =C23/C21 -> #DIV/0! | D24: 0.15
B25: Total Biddable Spend Above Threshold | C25: =100%-C24 -> #DIV/0! | D25: 0.85
B26: Final Compliance Result

Sheet BusinessBrand KPIs
B2: Please complete all highlighted cells
B5: =INDEX('Drop Downs'!$G$2:$G$12,MATCH('Local PRF Calculator'!$E$6,'Drop Downs'!$F$2:$F$12,0)) -> #VALUE! | D5: Year | E5: =IF('Fee Summary'!E5="Select Year","Please Complete Summary Tab",'Fee Summary'!E5) -> 2025
D6: Brand | E6: =IF('Fee Summary'!E6="Select brand","Please Complete Summary Tab",'Fee Summary'!E6) -> Porsche
D7: Market | E7: =IF('Fee Summary'!E7="Select Market","Please Complete Summary Tab",'Fee Summary'!E7) -> Australia
D8: Date Updated | E8: =IF('Fee Summary'!E8="","",'Fee Summary'!E8)
B12: Aligned KPIs | C12: KPI Name | D12: KPI Definition | E12: Source of Truth | F12: Weight | G12: Previous year / previous period achievement or benchmark | H12: Expected over achievement % | I12: This year's target | J12: Delivery | K12: Bonus Earned
B13: #1 | K13: =IF(J13>I13,F13,0) -> 0
B14: #2 | K14: =IF(J14>I14,F14,0) -> 0
B15: #3 | K15: =IF(J15>I15,F15,0) -> 0
B16: #4 | K16: =IF(J16>I16,F16,0) -> 0
B17: #5 | K17: =IF(J17>I17,F17,0) -> 0
B18: Overall | F18: =SUM(F13:F17) -> 0 | G18: =IF(NOT(F18=12.5%),"Please ensure total weight equals 12.5%","") -> Please ensure total weight equals 12.5% | K18: =SUM(K13:K17) -> 0

Sheet BAH Perf Fee Reconciliations
B2: Please complete all highlighted cells
B5: =INDEX('Drop Downs'!$G$2:$G$12,MATCH('Local PRF Calculator'!$E$6,'Drop Downs'!$F$2:$F$12,0)) -> #VALUE! | C5: Year | D5: =IF('Fee Summary'!E5="Select Year","Please Complete Summary Tab",'Fee Summary'!E5) -> 2025
C6: Brand | D6: =IF('Fee Summary'!E6="Select brand","Please Complete Summary Tab",'Fee Summary'!E6) -> Porsche
C7: Market | D7: =IF('Fee Summary'!E7="Select Market","Please Complete Summary Tab",'Fee Summary'!E7) -> Australia
C8: Date Updated | D8: =IF('Fee Summary'!E8="","",'Fee Summary'!E8)
B10: Social Base Commission % | D10: =IF($D$5="Please Complete Summary tab",0.03,IF($D$5=2025,0.03,IF($D$5=2026,0.029,0.0285))) -> 0.03
B11: Search Base Commission % | D11: =IF($D$5="Please Complete Summary tab",0.03,IF($D$5=2025,0.03,IF($D$5=2026,0.029,0.0285))) -> 0.03
B12: Programmatic Base Commission % | D12: =IF($D$5="Please Complete Summary tab",0.0425,IF($D$5=2025,0.0425,IF($D$5=2026,0.041,0.04))) -> 0.0425
D14: 100% Fee | E14: 80% Billed
B15: Total Nominal Fees - BAH Exc AdOps Levy (LC) | D15: =SUM(H:H) -> 49062.5 | E15: =IF($D$6="Porsche","N/A",SUM(J:J)) -> N/A
B16: Total Nominal Fees - BAH Inc AdOps Levy (LC) | D16: =SUM(I:I) -> 53125 | E16: =IF($D$6="Porsche","N/A",SUM(K:K)) -> N/A
B17: Total Reconciled Fees Inc Performance & AdOps Levy (LC) | D17: =SUM(S:S) -> 50125
B18: Reconciled Performance Fees (LC) | D18: =D17-D16 -> -3000
B21: Campaign Details | H21: Total Nominal Fees (@ 100%) | J21: Total Billed Fees (@ 80%) | L21: Campaign Metrics | Q21: Campaign Reconciliation
B22: Campaign Name | C22: Campaign Type | D22: Media Channel | E22: Budget (LC) | F22: Base Commission (%) | G22: AdOps Levy (LC) (0.25% on all Digital Investments) | H22: Total Nominal Fee (100%) BAH Exc AdOps Levy (LC) | I22: Total Base Fee (100%) BAH Inc AdOps Levy (LC) | J22: Total Billed Base Fee (80%) BAH Exc AdOps Levy (LC) | K22: Total Billed Base Fee (80%) BAH Inc AdOps Levy (LC) | L22: Metric Measured | M22: Target (LC) | N22: Result (LC) | O22: Result (% vs Target) | P22: Campaign included in Measurement? | Q22: Campaign Performance Fee (%) | R22: Campaign Performance Fee (LC) | S22: Campaign Total Billings (inc. Fees, Performance Fee & Ad Ops Levy) (LC) | T22: Reconciled Campaign Payment (LC) | U22: Campaign Reconciled?
B23: EXAMPLE (Please overwrite!) | C23: Used Cars | D23: Paid Search | E23: 100000 | F23: =IF(E23="","",IF(D23="Paid Search",$D$11,IF(D23="Paid Social",$D$10,$D$12))) -> 0.03 | G23: =IFERROR(IF(E23="","",E23*0.25%),"") -> 250 | H23: =IFERROR(F23*E23,"") -> 3000 | I23: =IFERROR(G23+H23,"") -> 3250 | J23: =IF(H23="","",IF($D$6="Porsche","N/A",IFERROR(H23*0.8,""))) -> N/A | K23: =IFERROR(IF(J23="","",J23+G23),"N/A") -> N/A | L23: Cost per Lead | M23: 25 | N23: 26 | O23: =IF(AND(M23="",N23=""),"",IF(OR(M23="",N23=""),"TBC",M23/N23-1)) -> -0.038461538 | P23: No | Q23: =IF(O23="","",IF(AND($D$5=2025,OR(C23="Used Cars",C23="Aftersales")),-10%,IF(IFERROR(E23*'Fee Summary'!$E$9,"TBC")<30000,"N/A - Campaign Less than €30k",IF(P23="No","N/A - Campaign Excluded",IF($D$6="Porsche",IF(O23="TBC","TBC",IF(O23<-0.5,-0.5,IF(O23>0.6,0.5,IF(O23<0,O23,IF(O23<0.1,0,O23-0.1))))),IF(O23="TBC","TBC",IF(O23<-0.2,-0.2,IF(O23>0.2,0.1,IF(O23<0,O23,IF(O23<0.1,0,O23-0.1)))))))))) -> -0.1 | R23: =IF(Q23="","",IFERROR(Q23*H23,"N/A")) -> -300 | S23: =IF($D$6="Porsche",I23,IF(R23="","",IF(R23="N/A",I23,I23+R23))) -> 3250 | T23: =IFERROR(S23-K23,"") | U23: Yes
B24: EXAMPLE (Please overwrite!) | C24: Aftersales | D24: Paid Search | E24: 1000000 | F24: =IF(E24="","",IF(D24="Paid Search",$D$11,IF(D24="Paid Social",$D$10,$D$12))) -> 0.03 | G24: =IFERROR(IF(E24="","",E24*0.25%),"") -> 2500 | H24: =IFERROR(F24*E24,"") -> 30000 | I24: =IFERROR(G24+H24,"") -> 32500 | J24: =IF(H24="","",IF($D$6="Porsche","N/A",IFERROR(H24*0.8,""))) -> N/A | K24: =IFERROR(IF(J24="","",J24+G24),"N/A") -> N/A | L24: Cost per reach | M24: 12 | N24: 11 | O24: =IF(AND(M24="",N24=""),"",IF(OR(M24="",N24=""),"TBC",M24/N24-1)) -> 0.090909091 | P24: No | Q24: =IF(O24="","",IF(AND($D$5=2025,OR(C24="Used Cars",C24="Aftersales")),-10%,IF(IFERROR(E24*'Fee Summary'!$E$9,"TBC")<30000,"N/A - Campaign Less than €30k",IF(P24="No","N/A - Campaign Excluded",IF($D$6="Porsche",IF(O24="TBC","TBC",IF(O24<-0.5,-0.5,IF(O24>0.6,0.5,IF(O24<0,O24,IF(O24<0.1,0,O24-0.1))))),IF(O24="TBC","TBC",IF(O24<-0.2,-0.2,IF(O24>0.2,0.1,IF(O24<0,O24,IF(O24<0.1,0,O24-0.1)))))))))) -> -0.1 | R24: =IF(Q24="","",IFERROR(Q24*H24,"N/A")) -> -3000 | S24: =IF(R24="","",IF(R24="N/A",I24,I24+R24)) -> 29500 | T24: =IFERROR(S24-K24,"") | U24: Yes
B25: EXAMPLE (Please overwrite!) | C25: New Cars | D25: Display | E25: 25000 | F25: =IF(E25="","",IF(D25="Paid Search",$D$11,IF(D25="Paid Social",$D$10,$D$12))) -> 0.0425 | G25: =IFERROR(IF(E25="","",E25*0.25%),"") -> 62.5 | H25: =IFERROR(F25*E25,"") -> 1062.5 | I25: =IFERROR(G25+H25,"") -> 1125 | J25: =IF(H25="","",IF($D$6="Porsche","N/A",IFERROR(H25*0.8,""))) -> N/A | K25: =IFERROR(IF(J25="","",J25+G25),"N/A") -> N/A | L25: Cost per test Drive | M25: 35 | N25: 32 | O25: =IF(AND(M25="",N25=""),"",IF(OR(M25="",N25=""),"TBC",M25/N25-1)) -> 0.09375 | P25: Yes | Q25: =IF(O25="","",IF(AND($D$5=2025,OR(C25="Used Cars",C25="Aftersales")),-10%,IF(IFERROR(E25*'Fee Summary'!$E$9,"TBC")<30000,"N/A - Campaign Less than €30k",IF(P25="No","N/A - Campaign Excluded",IF($D$6="Porsche",IF(O25="TBC","TBC",IF(O25<-0.5,-0.5,IF(O25>0.6,0.5,IF(O25<0,O25,IF(O25<0.1,0,O25-0.1))))),IF(O25="TBC","TBC",IF(O25<-0.2,-0.2,IF(O25>0.2,0.1,IF(O25<0,O25,IF(O25<0.1,0,O25-0.1)))))))))) -> N/A - Campaign Less than €30k | R25: =IF(Q25="","",IFERROR(Q25*H25,"N/A")) -> N/A | S25: =IF($D$6="Porsche",I25,IF(R25="","",IF(R25="N/A",I25,I25+R25))) -> 1125 | T25: =IFERROR(S25-K25,"") | U25: No
B26: EXAMPLE (Please overwrite!) | C26: New Cars | D26: Paid Social | E26: 500000 | F26: =IF(E26="","",IF(D26="Paid Search",$D$11,IF(D26="Paid Social",$D$10,$D$12))) -> 0.03 | G26: =IFERROR(IF(E26="","",E26*0.25%),"") -> 1250 | H26: =IFERROR(F26*E26,"") -> 15000 | I26: =IFERROR(G26+H26,"") -> 16250 | J26: =IF(H26="","",IF($D$6="Porsche","N/A",IFERROR(H26*0.8,""))) -> N/A | K26: =IFERROR(IF(J26="","",J26+G26),"N/A") -> N/A | L26: Cost per Lead | M26: 33 | N26: 30 | O26: =IF(AND(M26="",N26=""),"",IF(OR(M26="",N26=""),"TBC",M26/N26-1)) -> 0.1 | P26: Yes | Q26: =IF(O26="","",IF(AND($D$5=2025,OR(C26="Used Cars",C26="Aftersales")),-10%,IF(IFERROR(E26*'Fee Summary'!$E$9,"TBC")<30000,"N/A - Campaign Less than €30k",IF(P26="No","N/A - Campaign Excluded",IF($D$6="Porsche",IF(O26="TBC","TBC",IF(O26<-0.5,-0.5,IF(O26>0.6,0.5,IF(O26<0,O26,IF(O26<0.1,0,O26-0.1))))),IF(O26="TBC","TBC",IF(O26<-0.2,-0.2,IF(O26>0.2,0.1,IF(O26<0,O26,IF(O26<0.1,0,O26-0.1)))))))))) -> 8.3266727e-17 | R26: =IF(Q26="","",IFERROR(Q26*H26,"N/A")) -> 1.2490009e-12 | S26: =IF($D$6="Porsche",I26,IF(R26="","",IF(R26="N/A",I26,I26+R26))) -> 16250 | T26: =IFERROR(S26-K26,"") | U26: No
F27: =IF(E27="","",IF(D27="Paid Search",$D$11,IF(D27="Paid Social",$D$10,$D$12))) | G27: =IFERROR(IF(E27="","",E27*0.25%),"") | H27: =IFERROR(F27*E27,"") | I27: =IFERROR(G27+H27,"") | J27: =IF(H27="","",IF($D$6="Porsche","N/A",IFERROR(H27*0.8,""))) | K27: =IFERROR(IF(J27="","",J27+G27),"N/A") | O27: =IF(AND(M27="",N27=""),"",IF(OR(M27="",N27=""),"TBC",M27/N27-1)) | P27: =IF(E27="","",IF($D$6="Porsche","No",IF(IFERROR(E27*'Fee Summary'!$E$9,"TBC")<30000,"No","Yes/No?"))) | Q27: =IF(O27="","",IF(AND($D$5=2025,OR(C27="Used Cars",C27="Aftersales")),-10%,IF(IFERROR(E27*'Fee Summary'!$E$9,"TBC")<30000,"N/A - Campaign Less than €30k",IF(P27="No","N/A - Campaign Excluded",IF($D$6="Porsche",IF(O27="TBC","TBC",IF(O27<-0.5,-0.5,IF(O27>0.6,0.5,IF(O27<0,O27,IF(O27<0.1,0,O27-0.1))))),IF(O27="TBC","TBC",IF(O27<-0.2,-0.2,IF(O27>0.2,0.1,IF(O27<0,O27,IF(O27<0.1,0,O27-0.1)))))))))) | R27: =IF(Q27="","",IFERROR(Q27*H27,"N/A")) | S27: =IF($D$6="Porsche",I27,IF(R27="","",IF(R27="N/A",I27,I27+R27))) | T27: =IFERROR(S27-K27,"")
F28: =IF(E28="","",IF(D28="Paid Search",$D$11,IF(D28="Paid Social",$D$10,$D$12))) | G28: =IFERROR(IF(E28="","",E28*0.25%),"") | H28: =IFERROR(F28*E28,"") | I28: =IFERROR(G28+H28,"") | J28: =IF(H28="","",IF($D$6="Porsche","N/A",IFERROR(H28*0.8,""))) | K28: =IFERROR(IF(J28="","",J28+G28),"N/A") | O28: =IF(AND(M28="",N28=""),"",IF(OR(M28="",N28=""),"TBC",M28/N28-1)) | P28: =IF(E28="","",IF($D$6="Porsche","No",IF(IFERROR(E28*'Fee Summary'!$E$9,"TBC")<30000,"No","Yes/No?"))) | Q28: =IF(O28="","",IF(AND($D$5=2025,OR(C28="Used Cars",C28="Aftersales")),-10%,IF(IFERROR(E28*'Fee Summary'!$E$9,"TBC")<30000,"N/A - Campaign Less than €30k",IF(P28="No","N/A - Campaign Excluded",IF($D$6="Porsche",IF(O28="TBC","TBC",IF(O28<-0.5,-0.5,IF(O28>0.6,0.5,IF(O28<0,O28,IF(O28<0.1,0,O28-0.1))))),IF(O28="TBC","TBC",IF(O28<-0.2,-0.2,IF(O28>0.2,0.1,IF(O28<0,O28,IF(O28<0.1,0,O28-0.1)))))))))) | R28: =IF(Q28="","",IFERROR(Q28*H28,"N/A")) | S28: =IF($D$6="Porsche",I28,IF(R28="","",IF(R28="N/A",I28,I28+R28))) | T28: =IFERROR(S28-K28,"")
F29: =IF(E29="","",IF(D29="Paid Search",$D$11,IF(D29="Paid Social",$D$10,$D$12))) | G29: =IFERROR(IF(E29="","",E29*0.25%),"") | H29: =IFERROR(F29*E29,"") | I29: =IFERROR(G29+H29,"") | J29: =IF(H29="","",IF($D$6="Porsche","N/A",IFERROR(H29*0.8,""))) | K29: =IFERROR(IF(J29="","",J29+G29),"N/A") | O29: =IF(AND(M29="",N29=""),"",IF(OR(M29="",N29=""),"TBC",M29/N29-1)) | P29: =IF(E29="","",IF($D$6="Porsche","No",IF(IFERROR(E29*'Fee Summary'!$E$9,"TBC")<30000,"No","Yes/No?"))) | Q29: =IF(O29="","",IF(AND($D$5=2025,OR(C29="Used Cars",C29="Aftersales")),-10%,IF(IFERROR(E29*'Fee Summary'!$E$9,"TBC")<30000,"N/A - Campaign Less than €30k",IF(P29="No","N/A - Campaign Excluded",IF($D$6="Porsche",IF(O29="TBC","TBC",IF(O29<-0.5,-0.5,IF(O29>0.6,0.5,IF(O29<0,O29,IF(O29<0.1,0,O29-0.1))))),IF(O29="TBC","TBC",IF(O29<-0.2,-0.2,IF(O29>0.2,0.1,IF(O29<0,O29,IF(O29<0.1,0,O29-0.1)))))))))) | R29: =IF(Q29="","",IFERROR(Q29*H29,"N/A")) | S29: =IF($D$6="Porsche",I29,IF(R29="","",IF(R29="N/A",I29,I29+R29))) | T29: =IFERROR(S29-K29,"")
F30: =IF(E30="","",IF(D30="Paid Search",$D$11,IF(D30="Paid Social",$D$10,$D$12))) | G30: =IFERROR(IF(E30="","",E30*0.25%),"") | H30: =IFERROR(F30*E30,"") | I30: =IFERROR(G30+H30,"") | J30: =IF(H30="","",IF($D$6="Porsche","N/A",IFERROR(H30*0.8,""))) | K30: =IFERROR(IF(J30="","",J30+G30),"N/A") | O30: =IF(AND(M30="",N30=""),"",IF(OR(M30="",N30=""),"TBC",M30/N30-1)) | P30: =IF(E30="","",IF($D$6="Porsche","No",IF(IFERROR(E30*'Fee Summary'!$E$9,"TBC")<30000,"No","Yes/No?"))) | Q30: =IF(O30="","",IF(AND($D$5=2025,OR(C30="Used Cars",C30="Aftersales")),-10%,IF(IFERROR(E30*'Fee Summary'!$E$9,"TBC")<30000,"N/A - Campaign Less than €30k",IF(P30="No","N/A - Campaign Excluded",IF($D$6="Porsche",IF(O30="TBC","TBC",IF(O30<-0.5,-0.5,IF(O30>0.6,0.5,IF(O30<0,O30,IF(O30<0.1,0,O30-0.1))))),IF(O30="TBC","TBC",IF(O30<-0.2,-0.2,IF(O30>0.2,0.1,IF(O30<0,O30,IF(O30<0.1,0,O30-0.1)))))))))) | R30: =IF(Q30="","",IFERROR(Q30*H30,"N/A")) | S30: =IF($D$6="Porsche",I30,IF(R30="","",IF(R30="N/A",I30,I30+R30))) | T30: =IFERROR(S30-K30,"")
F31: =IF(E31="","",IF(D31="Paid Search",$D$11,IF(D31="Paid Social",$D$10,$D$12))) | G31: =IFERROR(IF(E31="","",E31*0.25%),"") | H31: =IFERROR(F31*E31,"") | I31: =IFERROR(G31+H31,"") | J31: =IF(H31="","",IF($D$6="Porsche","N/A",IFERROR(H31*0.8,""))) | K31: =IFERROR(IF(J31="","",J31+G31),"N/A") | O31: =IF(AND(M31="",N31=""),"",IF(OR(M31="",N31=""),"TBC",M31/N31-1)) | P31: =IF(E31="","",IF($D$6="Porsche","No",IF(IFERROR(E31*'Fee Summary'!$E$9,"TBC")<30000,"No","Yes/No?"))) | Q31: =IF(O31="","",IF(AND($D$5=2025,OR(C31="Used Cars",C31="Aftersales")),-10%,IF(IFERROR(E31*'Fee Summary'!$E$9,"TBC")<30000,"N/A - Campaign Less than €30k",IF(P31="No","N/A - Campaign Excluded",IF($D$6="Porsche",IF(O31="TBC","TBC",IF(O31<-0.5,-0.5,IF(O31>0.6,0.5,IF(O31<0,O31,IF(O31<0.1,0,O31-0.1))))),IF(O31="TBC","TBC",IF(O31<-0.2,-0.2,IF(O31>0.2,0.1,IF(O31<0,O31,IF(O31<0.1,0,O31-0.1)))))))))) | R31: =IF(Q31="","",IFERROR(Q31*H31,"N/A")) | S31: =IF($D$6="Porsche",I31,IF(R31="","",IF(R31="N/A",I31,I31+R31))) | T31: =IFERROR(S31-K31,"")
F32: =IF(E32="","",IF(D32="Paid Search",$D$11,IF(D32="Paid Social",$D$10,$D$12))) | G32: =IFERROR(IF(E32="","",E32*0.25%),"") | H32: =IFERROR(F32*E32,"") | I32: =IFERROR(G32+H32,"") | J32: =IF(H32="","",IF($D$6="Porsche","N/A",IFERROR(H32*0.8,""))) | K32: =IFERROR(IF(J32="","",J32+G32),"N/A") | O32: =IF(AND(M32="",N32=""),"",IF(OR(M32="",N32=""),"TBC",M32/N32-1)) | P32: =IF(E32="","",IF($D$6="Porsche","No",IF(IFERROR(E32*'Fee Summary'!$E$9,"TBC")<30000,"No","Yes/No?"))) | Q32: =IF(O32="","",IF(AND($D$5=2025,OR(C32="Used Cars",C32="Aftersales")),-10%,IF(IFERROR(E32*'Fee Summary'!$E$9,"TBC")<30000,"N/A - Campaign Less than €30k",IF(P32="No","N/A - Campaign Excluded",IF($D$6="Porsche",IF(O32="TBC","TBC",IF(O32<-0.5,-0.5,IF(O32>0.6,0.5,IF(O32<0,O32,IF(O32<0.1,0,O32-0.1))))),IF(O32="TBC","TBC",IF(O32<-0.2,-0.2,IF(O32>0.2,0.1,IF(O32<0,O32,IF(O32<0.1,0,O32-0.1)))))))))) | R32: =IF(Q32="","",IFERROR(Q32*H32,"N/A")) | S32: =IF($D$6="Porsche",I32,IF(R32="","",IF(R32="N/A",I32,I32+R32))) | T32: =IFERROR(S32-K32,"")
F33: =IF(E33="","",IF(D33="Paid Search",$D$11,IF(D33="Paid Social",$D$10,$D$12))) | G33: =IFERROR(IF(E33="","",E33*0.25%),"") | H33: =IFERROR(F33*E33,"") | I33: =IFERROR(G33+H33,"") | J33: =IF(H33="","",IF($D$6="Porsche","N/A",IFERROR(H33*0.8,""))) | K33: =IFERROR(IF(J33="","",J33+G33),"N/A") | O33: =IF(AND(M33="",N33=""),"",IF(OR(M33="",N33=""),"TBC",M33/N33-1)) | P33: =IF(E33="","",IF($D$6="Porsche","No",IF(IFERROR(E33*'Fee Summary'!$E$9,"TBC")<30000,"No","Yes/No?"))) | Q33: =IF(O33="","",IF(AND($D$5=2025,OR(C33="Used Cars",C33="Aftersales")),-10%,IF(IFERROR(E33*'Fee Summary'!$E$9,"TBC")<30000,"N/A - Campaign Less than €30k",IF(P33="No","N/A - Campaign Excluded",IF($D$6="Porsche",IF(O33="TBC","TBC",IF(O33<-0.5,-0.5,IF(O33>0.6,0.5,IF(O33<0,O33,IF(O33<0.1,0,O33-0.1))))),IF(O33="TBC","TBC",IF(O33<-0.2,-0.2,IF(O33>0.2,0.1,IF(O33<0,O33,IF(O33<0.1,0,O33-0.1)))))))))) | R33: =IF(Q33="","",IFERROR(Q33*H33,"N/A")) | S33: =IF($D$6="Porsche",I33,IF(R33="","",IF(R33="N/A",I33,I33+R33))) | T33: =IFERROR(S33-K33,"")
F34: =IF(E34="","",IF(D34="Paid Search",$D$11,IF(D34="Paid Social",$D$10,$D$12))) | G34: =IFERROR(IF(E34="","",E34*0.25%),"") | H34: =IFERROR(F34*E34,"") | I34: =IFERROR(G34+H34,"") | J34: =IF(H34="","",IF($D$6="Porsche","N/A",IFERROR(H34*0.8,""))) | K34: =IFERROR(IF(J34="","",J34+G34),"N/A") | O34: =IF(AND(M34="",N34=""),"",IF(OR(M34="",N34=""),"TBC",M34/N34-1)) | P34: =IF(E34="","",IF($D$6="Porsche","No",IF(IFERROR(E34*'Fee Summary'!$E$9,"TBC")<30000,"No","Yes/No?"))) | Q34: =IF(O34="","",IF(AND($D$5=2025,OR(C34="Used Cars",C34="Aftersales")),-10%,IF(IFERROR(E34*'Fee Summary'!$E$9,"TBC")<30000,"N/A - Campaign Less than €30k",IF(P34="No","N/A - Campaign Excluded",IF($D$6="Porsche",IF(O34="TBC","TBC",IF(O34<-0.5,-0.5,IF(O34>0.6,0.5,IF(O34<0,O34,IF(O34<0.1,0,O34-0.1))))),IF(O34="TBC","TBC",IF(O34<-0.2,-0.2,IF(O34>0.2,0.1,IF(O34<0,O34,IF(O34<0.1,0,O34-0.1)))))))))) | R34: =IF(Q34="","",IFERROR(Q34*H34,"N/A")) | S34: =IF($D$6="Porsche",I34,IF(R34="","",IF(R34="N/A",I34,I34+R34))) | T34: =IFERROR(S34-K34,"")
F35: =IF(E35="","",IF(D35="Paid Search",$D$11,IF(D35="Paid Social",$D$10,$D$12))) | G35: =IFERROR(IF(E35="","",E35*0.25%),"") | H35: =IFERROR(F35*E35,"") | I35: =IFERROR(G35+H35,"") | J35: =IF(H35="","",IF($D$6="Porsche","N/A",IFERROR(H35*0.8,""))) | K35: =IFERROR(IF(J35="","",J35+G35),"N/A") | O35: =IF(AND(M35="",N35=""),"",IF(OR(M35="",N35=""),"TBC",M35/N35-1)) | P35: =IF(E35="","",IF($D$6="Porsche","No",IF(IFERROR(E35*'Fee Summary'!$E$9,"TBC")<30000,"No","Yes/No?"))) | Q35: =IF(O35="","",IF(AND($D$5=2025,OR(C35="Used Cars",C35="Aftersales")),-10%,IF(IFERROR(E35*'Fee Summary'!$E$9,"TBC")<30000,"N/A - Campaign Less than €30k",IF(P35="No","N/A - Campaign Excluded",IF($D$6="Porsche",IF(O35="TBC","TBC",IF(O35<-0.5,-0.5,IF(O35>0.6,0.5,IF(O35<0,O35,IF(O35<0.1,0,O35-0.1))))),IF(O35="TBC","TBC",IF(O35<-0.2,-0.2,IF(O35>0.2,0.1,IF(O35<0,O35,IF(O35<0.1,0,O35-0.1)))))))))) | R35: =IF(Q35="","",IFERROR(Q35*H35,"N/A")) | S35: =IF($D$6="Porsche",I35,IF(R35="","",IF(R35="N/A",I35,I35+R35))) | T35: =IFERROR(S35-K35,"")
F36: =IF(E36="","",IF(D36="Paid Search",$D$11,IF(D36="Paid Social",$D$10,$D$12))) | G36: =IFERROR(IF(E36="","",E36*0.25%),"") | H36: =IFERROR(F36*E36,"") | I36: =IFERROR(G36+H36,"") | J36: =IF(H36="","",IF($D$6="Porsche","N/A",IFERROR(H36*0.8,""))) | K36: =IFERROR(IF(J36="","",J36+G36),"N/A") | O36: =IF(AND(M36="",N36=""),"",IF(OR(M36="",N36=""),"TBC",M36/N36-1)) | P36: =IF(E36="","",IF($D$6="Porsche","No",IF(IFERROR(E36*'Fee Summary'!$E$9,"TBC")<30000,"No","Yes/No?"))) | Q36: =IF(O36="","",IF(AND($D$5=2025,OR(C36="Used Cars",C36="Aftersales")),-10%,IF(IFERROR(E36*'Fee Summary'!$E$9,"TBC")<30000,"N/A - Campaign Less than €30k",IF(P36="No","N/A - Campaign Excluded",IF($D$6="Porsche",IF(O36="TBC","TBC",IF(O36<-0.5,-0.5,IF(O36>0.6,0.5,IF(O36<0,O36,IF(O36<0.1,0,O36-0.1))))),IF(O36="TBC","TBC",IF(O36<-0.2,-0.2,IF(O36>0.2,0.1,IF(O36<0,O36,IF(O36<0.1,0,O36-0.1)))))))))) | R36: =IF(Q36="","",IFERROR(Q36*H36,"N/A")) | S36: =IF($D$6="Porsche",I36,IF(R36="","",IF(R36="N/A",I36,I36+R36))) | T36: =IFERROR(S36-K36,"")
F37: =IF(E37="","",IF(D37="Paid Search",$D$11,IF(D37="Paid Social",$D$10,$D$12))) | G37: =IFERROR(IF(E37="","",E37*0.25%),"") | H37: =IFERROR(F37*E37,"") | I37: =IFERROR(G37+H37,"") | J37: =IF(H37="","",IF($D$6="Porsche","N/A",IFERROR(H37*0.8,""))) | K37: =IFERROR(IF(J37="","",J37+G37),"N/A") | O37: =IF(AND(M37="",N37=""),"",IF(OR(M37="",N37=""),"TBC",M37/N37-1)) | P37: =IF(E37="","",IF($D$6="Porsche","No",IF(IFERROR(E37*'Fee Summary'!$E$9,"TBC")<30000,"No","Yes/No?"))) | Q37: =IF(O37="","",IF(AND($D$5=2025,OR(C37="Used Cars",C37="Aftersales")),-10%,IF(IFERROR(E37*'Fee Summary'!$E$9,"TBC")<30000,"N/A - Campaign Less than €30k",IF(P37="No","N/A - Campaign Excluded",IF($D$6="Porsche",IF(O37="TBC","TBC",IF(O37<-0.5,-0.5,IF(O37>0.6,0.5,IF(O37<0,O37,IF(O37<0.1,0,O37-0.1))))),IF(O37="TBC","TBC",IF(O37<-0.2,-0.2,IF(O37>0.2,0.1,IF(O37<0,O37,IF(O37<0.1,0,O37-0.1)))))))))) | R37: =IF(Q37="","",IFERROR(Q37*H37,"N/A")) | S37: =IF($D$6="Porsche",I37,IF(R37="","",IF(R37="N/A",I37,I37+R37))) | T37: =IFERROR(S37-K37,"")
F38: =IF(E38="","",IF(D38="Paid Search",$D$11,IF(D38="Paid Social",$D$10,$D$12))) | G38: =IFERROR(IF(E38="","",E38*0.25%),"") | H38: =IFERROR(F38*E38,"") | I38: =IFERROR(G38+H38,"") | J38: =IF(H38="","",IF($D$6="Porsche","N/A",IFERROR(H38*0.8,""))) | K38: =IFERROR(IF(J38="","",J38+G38),"N/A") | O38: =IF(AND(M38="",N38=""),"",IF(OR(M38="",N38=""),"TBC",M38/N38-1)) | P38: =IF(E38="","",IF($D$6="Porsche","No",IF(IFERROR(E38*'Fee Summary'!$E$9,"TBC")<30000,"No","Yes/No?"))) | Q38: =IF(O38="","",IF(AND($D$5=2025,OR(C38="Used Cars",C38="Aftersales")),-10%,IF(IFERROR(E38*'Fee Summary'!$E$9,"TBC")<30000,"N/A - Campaign Less than €30k",IF(P38="No","N/A - Campaign Excluded",IF($D$6="Porsche",IF(O38="TBC","TBC",IF(O38<-0.5,-0.5,IF(O38>0.6,0.5,IF(O38<0,O38,IF(O38<0.1,0,O38-0.1))))),IF(O38="TBC","TBC",IF(O38<-0.2,-0.2,IF(O38>0.2,0.1,IF(O38<0,O38,IF(O38<0.1,0,O38-0.1)))))))))) | R38: =IF(Q38="","",IFERROR(Q38*H38,"N/A")) | S38: =IF($D$6="Porsche",I38,IF(R38="","",IF(R38="N/A",I38,I38+R38))) | T38: =IFERROR(S38-K38,"")
... F122: =IF(E122="","",IF(D122="Paid Search",$D$11,IF(D122="Paid Social",$D$10,$D$12))) | G122: =IFERROR(IF(E122="","",E122*0.25%),"") | H122: =IFERROR(F122*E122,"") | I122: =IFERROR(G122+H122,"") | J122: =IF(H122="","",IF($D$6="Porsche","N/A",IFERROR(H122*0.8,""))) | K122: =IFERROR(IF(J122="","",J122+G122),"N/A") | O122: =IF(AND(M122="",N122=""),"",IF(OR(M122="",N122=""),"TBC",M122/N122-1)) | P122: =IF(E122="","",IF($D$6="Porsche","No",IF(IFERROR(E122*'Fee Summary'!$E$9,"TBC")<30000,"No","Yes/No?"))) | Q122: =IF(O122="","",IF(AND($D$5=2025,OR(C122="Used Cars",C122="Aftersales")),-10%,IF(IFERROR(E122*'Fee Summary'!$E$9,"TBC")<30000,"N/A - Campaign Less than €30k",IF(P122="No","N/A - Campaign Excluded",IF($D$6="Porsche",IF(O122="TBC","TBC",IF(O122<-0.5,-0.5,IF(O122>0.6,0.5,IF(O122<0,O122,IF(O122<0.1,0,O122-0.1))))),IF(O122="TBC","TBC",IF(O122<-0.2,-0.2,IF(O122>0.2,0.1,IF(O122<0,O122,IF(O122<0.1,0,O122-0.1)))))))))) | R122: =IF(Q122="","",IFERROR(Q122*H122,"N/A")) | S122: =IF($D$6="Porsche",I122,IF(R122="","",IF(R122="N/A",I122,I122+R122))) | T122: =IFERROR(S122-K122,"")

Sheet Drop Downs
B2: Select Market | C2: Select Year | D2: Yes/No? | E2: Actual/Forecast? | F2: Please Complete Summary Tab | G2: #VALUE! | I2: FTE/Commission? | J2: Affiliates | K2: Please Select | L2: Business - Sales
B3: APAC | C3: 2025 | D3: Yes | E3: Actual Delivery (%) | F3: Select Brand | G3: #VALUE! | I3: FTE | J3: Audio (Inc. Radio) | K3: New Cars | L3: Business - Order Intakes
B4: Argentina | C4: 2026 | D4: No | E4: Forecast Delivery (%) | F4: Audi | G4: #VALUE! | I4: Commission | J4: Brand Sponsorship & Partnership | K4: Used Cars | L4: Business - Verified Importer Leads/Sales Opportunity
B5: Australia | C5: 2027 | D5: N/A | F5: Bentley | G5: #VALUE! | I5: Hybrid | J5: Cinema | K5: Aftersales | L5: Business - Market share
B6: Austria | C6: 2028 | F6: LCV | G6: #VALUE! | J6: Connected TV (CTV) | L6: Brand - Aided Brand Awareness
B7: Canada | C7: 2029 | F7: MAN Energy Solutions | G7: #VALUE! | J7: Corporate Sponsorship & Partnership | L7: Brand - Unaided Brand Awareness
B8: CEE | C8: 2030 | F8: MAN Truck & Bus | G8: #VALUE! | J8: Display | L8: Brand - Familiarity
B9: Central | F9: Porsche | G9: #VALUE! | J9: Event | L9: Brand - Likability
B10: China | F10: Seat/Cupra | G10: #VALUE! | J10: Influencer | L10: Brand - Unaided Brand Consideration
B11: Czechia | F11: Skoda | G11: #VALUE! | J11: iVideo | L11: Brand - Web Visits
B12: France | F12: VW Brand | G12: #VALUE! | J12: Other
B13: Germany | J13: Out of Home (OOH)
B14: India | J14: Paid Search
B15: Ireland | J15: Paid Social
B16: Italy | J16: Print
B17: LATAM | J17: TV
B18: Mexico
B19: Middle East
B20: Poland
B21: Portugal
B22: Singapore
B23: Slovakia
B24: South Africa
B25: South Korea
B26: Spain
B27: Sweden
B28: Switzerland
B29: Taiwan
... B31: USA

Sheet FX Rates
E2: 2025 FX Rates as provided by VWG
B3: Country Name | C3: Currency Name | D3: Country Code | E3: VWG FX (LC to EUR)
B4: APAC | C4: Dollar | D4: SGD | E4: 0.71
B5: Argentina | C5: Peso | D5: ARS | E5: 0.00094315
B6: Australia | C6: Dollar | D6: AUD | E6: 0.62
B7: Austria | C7: Schilling | D7: EUR | E7: 1
B8: Canada | C8: Dollar | D8: CAD | E8: 0.68
B9: CEE | C9: Euro | D9: EUR | E9: 1
B10: China | C10: Yuan (Renminbi) | D10: CNY | E10: 0.13
B11: Czechia | C11: Koruna | D11: CZK | E11: 0.04
B12: France | C12: Euro | D12: EUR | E12: 1
B13: Germany | C13: Euro | D13: EUR | E13: 1
B14: Hong Kong | C14: Dollar | D14: HKD | E14: 0.12
B15: India | C15: Rupee | D15: INR | E15: 0.01
... B45: VW Brand Central | C45: Euro | D45: EUR | E45: 1
